{
  "lastUpdated": "2026-04-21T15:58:56.600815+00:00",
  "locationCount": 31,
  "errors": [],
  "weatherCache": {
    "48.9162,-121.608": {
      "weatherByDay": {
        "2026-04-21": {
          "temperature_f": 64.0,
          "cloud_cover_pct": 59.86363636363637,
          "wind_speed_mph": 4.603116368,
          "wind_gust_mph": 9.206232736,
          "overnight_snowfall_in": 0.0,
          "overnight_low_f": 42.0,
          "humidity_pct": 68.72222222222223,
          "precipitation_in": 0.03999999910593,
          "visibility_mi": null,
          "precipitation_probability_pct": 50
        },
        "2026-04-22": {
          "temperature_f": 47.0,
          "cloud_cover_pct": 88.06666666666666,
          "wind_speed_mph": 5.466200687000001,
          "wind_gust_mph": 12.658570012,
          "overnight_snowfall_in": 0.0,
          "overnight_low_f": 40.0,
          "humidity_pct": 84.70588235294117,
          "precipitation_in": 0.269999999552961,
          "visibility_mi": null,
          "precipitation_probability_pct": 80
        },
        "2026-04-23": {
          "temperature_f": 49.0,
          "cloud_cover_pct": 44.285714285714285,
          "wind_speed_mph": 7.726659617714286,
          "wind_gust_mph": 17.26168638,
          "overnight_snowfall_in": 0.0,
          "overnight_low_f": 34.0,
          "humidity_pct": 66.14285714285714,
          "precipitation_in": 0.089999999850988,
          "visibility_mi": null,
          "precipitation_probability_pct": 49
        },
        "2026-04-24": {
          "temperature_f": 53.0,
          "cloud_cover_pct": 10.75,
          "wind_speed_mph": 7.562262604571428,
          "wind_gust_mph": 21.864802748000002,
          "overnight_snowfall_in": 0.0,
          "overnight_low_f": 33.0,
          "humidity_pct": 50.61904761904762,
          "precipitation_in": 0.0,
          "visibility_mi": null,
          "precipitation_probability_pct": 3
        },
        "2026-04-25": {
          "temperature_f": 55.0,
          "cloud_cover_pct": 14.0,
          "wind_speed_mph": 10.587167646400001,
          "wind_gust_mph": 23.01558184,
          "overnight_snowfall_in": 0.0,
          "overnight_low_f": 34.0,
          "humidity_pct": 43.421052631578945,
          "precipitation_in": 0.0,
          "visibility_mi": null,
          "precipitation_probability_pct": 6
        },
        "2026-04-26": {
          "temperature_f": 55.0,
          "cloud_cover_pct": 28.0,
          "wind_speed_mph": 7.726659617714286,
          "wind_gust_mph": 17.26168638,
          "overnight_snowfall_in": 0.0,
          "overnight_low_f": 35.0,
          "humidity_pct": 49.0,
          "precipitation_in": 0.0,
          "visibility_mi": null,
          "precipitation_probability_pct": 17
        },
        "2026-04-27": {
          "temperature_f": 53.0,
          "cloud_cover_pct": 46.0,
          "wind_speed_mph": 8.2856094624,
          "wind_gust_mph": 17.26168638,
          "overnight_snowfall_in": 0.0,
          "overnight_low_f": 37.0,
          "humidity_pct": 62.55,
          "precipitation_in": 0.019999999552965,
          "visibility_mi": null,
          "precipitation_probability_pct": 32
        }
      },
      "forecastUrl": "https://api.weather.gov/gridpoints/SEW/160,125/forecast",
      "source": "NWS"
    },
    "48.821,-121.601": {
      "weatherByDay": {
        "2026-04-21": {
          "temperature_f": 50.0,
          "cloud_cover_pct": 59.54545454545455,
          "wind_speed_mph": 6.904674552,
          "wind_gust_mph": 12.658570012,
          "overnight_snowfall_in": 0.0,
          "overnight_low_f": 33.0,
          "humidity_pct": 65.65217391304348,
          "precipitation_in": 0.059999998658895,
          "visibility_mi": null,
          "precipitation_probability_pct": 50
        },
        "2026-04-22": {
          "temperature_f": 33.0,
          "cloud_cover_pct": 88.07692307692308,
          "wind_speed_mph": 7.384165840333335,
          "wind_gust_mph": 14.960128196000001,
          "overnight_snowfall_in": 1.5000000298023202,
          "overnight_low_f": 30.0,
          "humidity_pct": 85.92857142857143,
          "precipitation_in": 0.27999999374151,
          "visibility_mi": null,
          "precipitation_probability_pct": 80
        },
        "2026-04-23": {
          "temperature_f": 36.0,
          "cloud_cover_pct": 50.57142857142857,
          "wind_speed_mph": 11.0762487605,
          "wind_gust_mph": 18.412465472,
          "overnight_snowfall_in": 0.90000003576279,
          "overnight_low_f": 25.0,
          "humidity_pct": 70.66666666666667,
          "precipitation_in": 0.099999999627471,
          "visibility_mi": null,
          "precipitation_probability_pct": 46
        },
        "2026-04-24": {
          "temperature_f": 41.0,
          "cloud_cover_pct": 10.25,
          "wind_speed_mph": 12.5147226255,
          "wind_gust_mph": 25.317140024,
          "overnight_snowfall_in": 0.0,
          "overnight_low_f": 24.0,
          "humidity_pct": 47.7,
          "precipitation_in": 0.0,
          "visibility_mi": null,
          "precipitation_probability_pct": 3
        },
        "2026-04-25": {
          "temperature_f": 42.0,
          "cloud_cover_pct": 13.0,
          "wind_speed_mph": 9.6665443728,
          "wind_gust_mph": 26.467919115999997,
          "overnight_snowfall_in": 0.0,
          "overnight_low_f": 26.0,
          "humidity_pct": 43.0,
          "precipitation_in": 0.0,
          "visibility_mi": null,
          "precipitation_probability_pct": 5
        },
        "2026-04-26": {
          "temperature_f": 43.0,
          "cloud_cover_pct": 27.0,
          "wind_speed_mph": 6.575880525714285,
          "wind_gust_mph": 21.864802748000002,
          "overnight_snowfall_in": 0.0,
          "overnight_low_f": 28.0,
          "humidity_pct": 48.45,
          "precipitation_in": 0.0,
          "visibility_mi": null,
          "precipitation_probability_pct": 16
        },
        "2026-04-27": {
          "temperature_f": 41.0,
          "cloud_cover_pct": 44.333333333333336,
          "wind_speed_mph": 7.1348303704000005,
          "wind_gust_mph": 21.864802748000002,
          "overnight_snowfall_in": 0.0,
          "overnight_low_f": 28.0,
          "humidity_pct": 61.04545454545455,
          "precipitation_in": 0.0099999997764826,
          "visibility_mi": null,
          "precipitation_probability_pct": 30
        }
      },
      "forecastUrl": "https://api.weather.gov/gridpoints/SEW/159,121/forecast",
      "source": "NWS"
    },
    "48.72,-121.815": {
      "weatherByDay": {
        "2026-04-21": {
          "temperature_f": 62.0,
          "cloud_cover_pct": 58.76190476190476,
          "wind_speed_mph": 4.8332721864,
          "wind_gust_mph": 9.206232736,
          "overnight_snowfall_in": 0.0,
          "overnight_low_f": 43.0,
          "humidity_pct": 64.45833333333333,
          "precipitation_in": 0.019999999552965,
          "visibility_mi": null,
          "precipitation_probability_pct": 48
        },
        "2026-04-22": {
          "temperature_f": 44.0,
          "cloud_cover_pct": 87.0,
          "wind_speed_mph": 6.800058270909091,
          "wind_gust_mph": 10.357011828,
          "overnight_snowfall_in": 0.0,
          "overnight_low_f": 39.0,
          "humidity_pct": 83.26315789473684,
          "precipitation_in": 0.270000003278255,
          "visibility_mi": null,
          "precipitation_probability_pct": 74
        },
        "2026-04-23": {
          "temperature_f": 47.0,
          "cloud_cover_pct": 47.125,
          "wind_speed_mph": 9.699423775428572,
          "wind_gust_mph": 14.960128196000001,
          "overnight_snowfall_in": 0.0,
          "overnight_low_f": 35.0,
          "humidity_pct": 67.46666666666667,
          "precipitation_in": 0.05999999865889501,
          "visibility_mi": null,
          "precipitation_probability_pct": 38
        },
        "2026-04-24": {
          "temperature_f": 53.0,
          "cloud_cover_pct": 8.5,
          "wind_speed_mph": 8.247250159333333,
          "wind_gust_mph": 17.26168638,
          "overnight_snowfall_in": 0.0,
          "overnight_low_f": 34.0,
          "humidity_pct": 47.35,
          "precipitation_in": 0.0,
          "visibility_mi": null,
          "precipitation_probability_pct": 1
        },
        "2026-04-25": {
          "temperature_f": 54.0,
          "cloud_cover_pct": 12.666666666666666,
          "wind_speed_mph": 8.822639705333334,
          "wind_gust_mph": 19.563244564,
          "overnight_snowfall_in": 0.0,
          "overnight_low_f": 36.0,
          "humidity_pct": 41.90909090909091,
          "precipitation_in": 0.0,
          "visibility_mi": null,
          "precipitation_probability_pct": 3
        },
        "2026-04-26": {
          "temperature_f": 53.0,
          "cloud_cover_pct": 23.25,
          "wind_speed_mph": 7.595142007200001,
          "wind_gust_mph": 16.110907288,
          "overnight_snowfall_in": 0.0,
          "overnight_low_f": 36.0,
          "humidity_pct": 47.1764705882353,
          "precipitation_in": 0.0,
          "visibility_mi": null,
          "precipitation_probability_pct": 14
        },
        "2026-04-27": {
          "temperature_f": 51.0,
          "cloud_cover_pct": 37.25,
          "wind_speed_mph": 6.740277538857143,
          "wind_gust_mph": 16.110907288,
          "overnight_snowfall_in": 0.0,
          "overnight_low_f": 37.0,
          "humidity_pct": 59.6,
          "precipitation_in": 0.019999999552965,
          "visibility_mi": null,
          "precipitation_probability_pct": 27
        }
      },
      "forecastUrl": "https://api.weather.gov/gridpoints/SEW/151,117/forecast",
      "source": "NWS"
    },
    "48.689,-121.139": {
      "weatherByDay": {
        "2026-04-21": {
          "temperature_f": 60.0,
          "cloud_cover_pct": 51.130434782608695,
          "wind_speed_mph": 6.616979778999999,
          "wind_gust_mph": 11.50779092,
          "overnight_snowfall_in": 0.0,
          "overnight_low_f": 43.0,
          "humidity_pct": 62.2,
          "precipitation_in": 0.050000000745058,
          "visibility_mi": null,
          "precipitation_probability_pct": 53
        },
        "2026-04-22": {
          "temperature_f": 43.0,
          "cloud_cover_pct": 80.42857142857143,
          "wind_speed_mph": 10.192614814857142,
          "wind_gust_mph": 16.110907288,
          "overnight_snowfall_in": 0.0,
          "overnight_low_f": 39.0,
          "humidity_pct": 81.94736842105263,
          "precipitation_in": 0.25000000372529,
          "visibility_mi": null,
          "precipitation_probability_pct": 76
        },
        "2026-04-23": {
          "temperature_f": 45.0,
          "cloud_cover_pct": 37.714285714285715,
          "wind_speed_mph": 9.9254696685,
          "wind_gust_mph": 19.563244564,
          "overnight_snowfall_in": 0.10000000149012,
          "overnight_low_f": 33.0,
          "humidity_pct": 68.22222222222223,
          "precipitation_in": 0.07999999821186,
          "visibility_mi": null,
          "precipitation_probability_pct": 46
        },
        "2026-04-24": {
          "temperature_f": 49.0,
          "cloud_cover_pct": 8.5,
          "wind_speed_mph": 7.562262604571429,
          "wind_gust_mph": 23.01558184,
          "overnight_snowfall_in": 0.0,
          "overnight_low_f": 32.0,
          "humidity_pct": 45.705882352941174,
          "precipitation_in": 0.0,
          "visibility_mi": null,
          "precipitation_probability_pct": 3
        },
        "2026-04-25": {
          "temperature_f": 51.0,
          "cloud_cover_pct": 12.666666666666666,
          "wind_speed_mph": 9.041835722857144,
          "wind_gust_mph": 25.317140024,
          "overnight_snowfall_in": 0.0,
          "overnight_low_f": 33.0,
          "humidity_pct": 43.625,
          "precipitation_in": 0.0,
          "visibility_mi": null,
          "precipitation_probability_pct": 7
        },
        "2026-04-26": {
          "temperature_f": 51.0,
          "cloud_cover_pct": 25.5,
          "wind_speed_mph": 7.8252978256,
          "wind_gust_mph": 19.563244564,
          "overnight_snowfall_in": 0.0,
          "overnight_low_f": 35.0,
          "humidity_pct": 47.714285714285715,
          "precipitation_in": 0.0,
          "visibility_mi": null,
          "precipitation_probability_pct": 17
        },
        "2026-04-27": {
          "temperature_f": 51.0,
          "cloud_cover_pct": 38.25,
          "wind_speed_mph": 7.891056630857143,
          "wind_gust_mph": 18.412465472,
          "overnight_snowfall_in": 0.0,
          "overnight_low_f": 36.0,
          "humidity_pct": 59.36842105263158,
          "precipitation_in": 0.0,
          "visibility_mi": null,
          "precipitation_probability_pct": 28
        }
      },
      "forecastUrl": "https://api.weather.gov/gridpoints/SEW/172,111/forecast",
      "source": "NWS"
    },
    "48.5175,-120.679": {
      "weatherByDay": {
        "2026-04-21": {
          "temperature_f": 55.0,
          "cloud_cover_pct": 51.7,
          "wind_speed_mph": 6.904674552,
          "wind_gust_mph": 13.809349104,
          "overnight_snowfall_in": 0.0,
          "overnight_low_f": 37.0,
          "humidity_pct": 63.529411764705884,
          "precipitation_in": 0.10999999940395001,
          "visibility_mi": null,
          "precipitation_probability_pct": 41
        },
        "2026-04-22": {
          "temperature_f": 42.0,
          "cloud_cover_pct": 71.53846153846153,
          "wind_speed_mph": 12.987364038285714,
          "wind_gust_mph": 27.618698208,
          "overnight_snowfall_in": 0.0,
          "overnight_low_f": 36.0,
          "humidity_pct": 80.94117647058823,
          "precipitation_in": 0.11999999918043561,
          "visibility_mi": null,
          "precipitation_probability_pct": 60
        },
        "2026-04-23": {
          "temperature_f": 42.0,
          "cloud_cover_pct": 27.0,
          "wind_speed_mph": 15.190284014400001,
          "wind_gust_mph": 27.618698208,
          "overnight_snowfall_in": 0.30000001192093,
          "overnight_low_f": 28.0,
          "humidity_pct": 63.36363636363637,
          "precipitation_in": 0.049999998882412605,
          "visibility_mi": null,
          "precipitation_probability_pct": 34
        },
        "2026-04-24": {
          "temperature_f": 44.0,
          "cloud_cover_pct": 13.666666666666666,
          "wind_speed_mph": 11.315994404666666,
          "wind_gust_mph": 26.467919115999997,
          "overnight_snowfall_in": 0.0,
          "overnight_low_f": 27.0,
          "humidity_pct": 48.388888888888886,
          "precipitation_in": 0.0,
          "visibility_mi": null,
          "precipitation_probability_pct": 3
        },
        "2026-04-25": {
          "temperature_f": 48.0,
          "cloud_cover_pct": 16.0,
          "wind_speed_mph": 7.8252978256,
          "wind_gust_mph": 18.412465472,
          "overnight_snowfall_in": 0.0,
          "overnight_low_f": 29.0,
          "humidity_pct": 48.470588235294116,
          "precipitation_in": 0.0,
          "visibility_mi": null,
          "precipitation_probability_pct": 8
        },
        "2026-04-26": {
          "temperature_f": 50.0,
          "cloud_cover_pct": 20.25,
          "wind_speed_mph": 6.329285006,
          "wind_gust_mph": 13.809349104,
          "overnight_snowfall_in": 0.0,
          "overnight_low_f": 31.0,
          "humidity_pct": 53.22222222222222,
          "precipitation_in": 0.0,
          "visibility_mi": null,
          "precipitation_probability_pct": 11
        },
        "2026-04-27": {
          "temperature_f": 48.0,
          "cloud_cover_pct": 29.5,
          "wind_speed_mph": 8.439046674666667,
          "wind_gust_mph": 17.26168638,
          "overnight_snowfall_in": 0.0,
          "overnight_low_f": 32.0,
          "humidity_pct": 63.73684210526316,
          "precipitation_in": 0.0,
          "visibility_mi": null,
          "precipitation_probability_pct": 20
        }
      },
      "forecastUrl": "https://api.weather.gov/gridpoints/OTX/45,149/forecast",
      "source": "NWS"
    },
    "48.498,-121.064": {
      "weatherByDay": {
        "2026-04-21": {
          "temperature_f": 50.0,
          "cloud_cover_pct": 58.18181818181818,
          "wind_speed_mph": 8.302049163714285,
          "wind_gust_mph": 12.658570012,
          "overnight_snowfall_in": 0.0,
          "overnight_low_f": 35.0,
          "humidity_pct": 68.5909090909091,
          "precipitation_in": 0.059999998658895,
          "visibility_mi": null,
          "precipitation_probability_pct": 50
        },
        "2026-04-22": {
          "temperature_f": 34.0,
          "cloud_cover_pct": 83.3076923076923,
          "wind_speed_mph": 15.1039755825,
          "wind_gust_mph": 18.412465472,
          "overnight_snowfall_in": 1.09999999403953,
          "overnight_low_f": 31.0,
          "humidity_pct": 90.88888888888889,
          "precipitation_in": 0.240000000223521,
          "visibility_mi": null,
          "precipitation_probability_pct": 69
        },
        "2026-04-23": {
          "temperature_f": 35.0,
          "cloud_cover_pct": 47.142857142857146,
          "wind_speed_mph": 17.097289366857144,
          "wind_gust_mph": 20.714023656,
          "overnight_snowfall_in": 1.20000004768372,
          "overnight_low_f": 26.0,
          "humidity_pct": 74.80952380952381,
          "precipitation_in": 0.11999999731779,
          "visibility_mi": null,
          "precipitation_probability_pct": 46
        },
        "2026-04-24": {
          "temperature_f": 39.0,
          "cloud_cover_pct": 13.666666666666666,
          "wind_speed_mph": 11.01459988057143,
          "wind_gust_mph": 23.01558184,
          "overnight_snowfall_in": 0.0,
          "overnight_low_f": 24.0,
          "humidity_pct": 55.7,
          "precipitation_in": 0.0,
          "visibility_mi": null,
          "precipitation_probability_pct": 3
        },
        "2026-04-25": {
          "temperature_f": 40.0,
          "cloud_cover_pct": 19.0,
          "wind_speed_mph": 11.50779092,
          "wind_gust_mph": 17.26168638,
          "overnight_snowfall_in": 0.0,
          "overnight_low_f": 26.0,
          "humidity_pct": 49.523809523809526,
          "precipitation_in": 0.0,
          "visibility_mi": null,
          "precipitation_probability_pct": 7
        },
        "2026-04-26": {
          "temperature_f": 41.0,
          "cloud_cover_pct": 30.0,
          "wind_speed_mph": 9.206232736,
          "wind_gust_mph": 18.412465472,
          "overnight_snowfall_in": 0.0,
          "overnight_low_f": 27.0,
          "humidity_pct": 54.0,
          "precipitation_in": 0.0,
          "visibility_mi": null,
          "precipitation_probability_pct": 17
        },
        "2026-04-27": {
          "temperature_f": 41.0,
          "cloud_cover_pct": 43.333333333333336,
          "wind_speed_mph": 10.357011828,
          "wind_gust_mph": 19.563244564,
          "overnight_snowfall_in": 0.0,
          "overnight_low_f": 28.0,
          "humidity_pct": 66.19047619047619,
          "precipitation_in": 0.0,
          "visibility_mi": null,
          "precipitation_probability_pct": 27
        }
      },
      "forecastUrl": "https://api.weather.gov/gridpoints/SEW/173,102/forecast",
      "source": "NWS"
    },
    "48.157,-120.907": {
      "weatherByDay": {
        "2026-04-21": {
          "temperature_f": 54.0,
          "cloud_cover_pct": 51.8,
          "wind_speed_mph": 8.055453644,
          "wind_gust_mph": 18.412465472,
          "overnight_snowfall_in": 0.0,
          "overnight_low_f": 38.0,
          "humidity_pct": 64.6,
          "precipitation_in": 0.019999999552965,
          "visibility_mi": null,
          "precipitation_probability_pct": 47
        },
        "2026-04-22": {
          "temperature_f": 41.0,
          "cloud_cover_pct": 78.23076923076923,
          "wind_speed_mph": 15.535517742,
          "wind_gust_mph": 31.071035484,
          "overnight_snowfall_in": 0.30000001192093,
          "overnight_low_f": 34.0,
          "humidity_pct": 80.53333333333333,
          "precipitation_in": 0.3800000064075051,
          "visibility_mi": null,
          "precipitation_probability_pct": 65
        },
        "2026-04-23": {
          "temperature_f": 42.0,
          "cloud_cover_pct": 47.875,
          "wind_speed_mph": 14.0395049224,
          "wind_gust_mph": 32.221814576,
          "overnight_snowfall_in": 0.6000000089406899,
          "overnight_low_f": 29.0,
          "humidity_pct": 63.529411764705884,
          "precipitation_in": 0.129999998956919,
          "visibility_mi": null,
          "precipitation_probability_pct": 38
        },
        "2026-04-24": {
          "temperature_f": 46.0,
          "cloud_cover_pct": 13.5,
          "wind_speed_mph": 11.50779092,
          "wind_gust_mph": 28.7694773,
          "overnight_snowfall_in": 0.0,
          "overnight_low_f": 27.0,
          "humidity_pct": 51.285714285714285,
          "precipitation_in": 0.0,
          "visibility_mi": null,
          "precipitation_probability_pct": 4
        },
        "2026-04-25": {
          "temperature_f": 50.0,
          "cloud_cover_pct": 14.75,
          "wind_speed_mph": 7.480064098000001,
          "wind_gust_mph": 18.412465472,
          "overnight_snowfall_in": 0.0,
          "overnight_low_f": 29.0,
          "humidity_pct": 47.31578947368421,
          "precipitation_in": 0.0,
          "visibility_mi": null,
          "precipitation_probability_pct": 10
        },
        "2026-04-26": {
          "temperature_f": 51.0,
          "cloud_cover_pct": 24.5,
          "wind_speed_mph": 8.055453644,
          "wind_gust_mph": 14.960128196000001,
          "overnight_snowfall_in": 0.0,
          "overnight_low_f": 31.0,
          "humidity_pct": 52.388888888888886,
          "precipitation_in": 0.0,
          "visibility_mi": null,
          "precipitation_probability_pct": 16
        },
        "2026-04-27": {
          "temperature_f": 49.0,
          "cloud_cover_pct": 33.0,
          "wind_speed_mph": 9.206232736,
          "wind_gust_mph": 17.26168638,
          "overnight_snowfall_in": 0.0,
          "overnight_low_f": 33.0,
          "humidity_pct": 60.78947368421053,
          "precipitation_in": 0.0,
          "visibility_mi": null,
          "precipitation_probability_pct": 24
        }
      },
      "forecastUrl": "https://api.weather.gov/gridpoints/OTX/35,133/forecast",
      "source": "NWS"
    },
    "48.127,-121.179": {
      "weatherByDay": {
        "2026-04-21": {
          "temperature_f": 61.0,
          "cloud_cover_pct": 56.56521739130435,
          "wind_speed_mph": 3.9637946502222223,
          "wind_gust_mph": 8.055453644,
          "overnight_snowfall_in": 0.0,
          "overnight_low_f": 42.0,
          "humidity_pct": 67.38095238095238,
          "precipitation_in": 0.11999999731779,
          "visibility_mi": null,
          "precipitation_probability_pct": 55
        },
        "2026-04-22": {
          "temperature_f": 42.0,
          "cloud_cover_pct": 87.16666666666667,
          "wind_speed_mph": 7.233468578285714,
          "wind_gust_mph": 14.960128196000001,
          "overnight_snowfall_in": 0.0,
          "overnight_low_f": 38.0,
          "humidity_pct": 86.8125,
          "precipitation_in": 0.490000002086162,
          "visibility_mi": null,
          "precipitation_probability_pct": 78
        },
        "2026-04-23": {
          "temperature_f": 45.0,
          "cloud_cover_pct": 60.25,
          "wind_speed_mph": 7.288267582666667,
          "wind_gust_mph": 17.26168638,
          "overnight_snowfall_in": 0.10000000149012,
          "overnight_low_f": 33.0,
          "humidity_pct": 74.61538461538461,
          "precipitation_in": 0.11999999731779,
          "visibility_mi": null,
          "precipitation_probability_pct": 51
        },
        "2026-04-24": {
          "temperature_f": 49.0,
          "cloud_cover_pct": 14.571428571428571,
          "wind_speed_mph": 6.329285006,
          "wind_gust_mph": 16.110907288,
          "overnight_snowfall_in": 0.0,
          "overnight_low_f": 31.0,
          "humidity_pct": 52.55,
          "precipitation_in": 0.0,
          "visibility_mi": null,
          "precipitation_probability_pct": 5
        },
        "2026-04-25": {
          "temperature_f": 50.0,
          "cloud_cover_pct": 15.25,
          "wind_speed_mph": 6.329285006,
          "wind_gust_mph": 17.26168638,
          "overnight_snowfall_in": 0.0,
          "overnight_low_f": 32.0,
          "humidity_pct": 47.21739130434783,
          "precipitation_in": 0.0,
          "visibility_mi": null,
          "precipitation_probability_pct": 10
        },
        "2026-04-26": {
          "temperature_f": 51.0,
          "cloud_cover_pct": 34.5,
          "wind_speed_mph": 5.75389546,
          "wind_gust_mph": 12.658570012,
          "overnight_snowfall_in": 0.0,
          "overnight_low_f": 35.0,
          "humidity_pct": 50.78947368421053,
          "precipitation_in": 0.0,
          "visibility_mi": null,
          "precipitation_probability_pct": 22
        },
        "2026-04-27": {
          "temperature_f": 50.0,
          "cloud_cover_pct": 45.75,
          "wind_speed_mph": 6.041590233000001,
          "wind_gust_mph": 14.960128196000001,
          "overnight_snowfall_in": 0.0,
          "overnight_low_f": 35.0,
          "humidity_pct": 62.611111111111114,
          "precipitation_in": 0.0,
          "visibility_mi": null,
          "precipitation_probability_pct": 32
        }
      },
      "forecastUrl": "https://api.weather.gov/gridpoints/SEW/166,85/forecast",
      "source": "NWS"
    },
    "48.125,-120.876": {
      "weatherByDay": {
        "2026-04-21": {
          "temperature_f": 63.0,
          "cloud_cover_pct": 43.266666666666666,
          "wind_speed_mph": 3.9455283154285716,
          "wind_gust_mph": 12.658570012,
          "overnight_snowfall_in": 0.0,
          "overnight_low_f": 41.0,
          "humidity_pct": 68.6875,
          "precipitation_in": 0.019999999552965,
          "visibility_mi": null,
          "precipitation_probability_pct": 46
        },
        "2026-04-22": {
          "temperature_f": 49.0,
          "cloud_cover_pct": 70.2,
          "wind_speed_mph": 8.63084319,
          "wind_gust_mph": 24.166360932000003,
          "overnight_snowfall_in": 0.0,
          "overnight_low_f": 39.0,
          "humidity_pct": 81.7,
          "precipitation_in": 0.1799999978393276,
          "visibility_mi": null,
          "precipitation_probability_pct": 64
        },
        "2026-04-23": {
          "temperature_f": 51.0,
          "cloud_cover_pct": 33.666666666666664,
          "wind_speed_mph": 8.055453644,
          "wind_gust_mph": 23.01558184,
          "overnight_snowfall_in": 0.0,
          "overnight_low_f": 35.0,
          "humidity_pct": 67.85,
          "precipitation_in": 0.059999998658896006,
          "visibility_mi": null,
          "precipitation_probability_pct": 35
        },
        "2026-04-24": {
          "temperature_f": 54.0,
          "cloud_cover_pct": 10.428571428571429,
          "wind_speed_mph": 6.4443629152,
          "wind_gust_mph": 21.864802748000002,
          "overnight_snowfall_in": 0.0,
          "overnight_low_f": 31.0,
          "humidity_pct": 53.333333333333336,
          "precipitation_in": 0.0,
          "visibility_mi": null,
          "precipitation_probability_pct": 4
        },
        "2026-04-25": {
          "temperature_f": 58.0,
          "cloud_cover_pct": 12.75,
          "wind_speed_mph": 7.288267582666667,
          "wind_gust_mph": 12.658570012,
          "overnight_snowfall_in": 0.0,
          "overnight_low_f": 33.0,
          "humidity_pct": 51.54545454545455,
          "precipitation_in": 0.0,
          "visibility_mi": null,
          "precipitation_probability_pct": 9
        },
        "2026-04-26": {
          "temperature_f": 59.0,
          "cloud_cover_pct": 20.75,
          "wind_speed_mph": 6.5210815213333335,
          "wind_gust_mph": 10.357011828,
          "overnight_snowfall_in": 0.0,
          "overnight_low_f": 35.0,
          "humidity_pct": 56.95238095238095,
          "precipitation_in": 0.0,
          "visibility_mi": null,
          "precipitation_probability_pct": 14
        },
        "2026-04-27": {
          "temperature_f": 56.0,
          "cloud_cover_pct": 29.25,
          "wind_speed_mph": 8.055453644,
          "wind_gust_mph": 11.50779092,
          "overnight_snowfall_in": 0.0,
          "overnight_low_f": 37.0,
          "humidity_pct": 63.42857142857143,
          "precipitation_in": 0.0,
          "visibility_mi": null,
          "precipitation_probability_pct": 22
        }
      },
      "forecastUrl": "https://api.weather.gov/gridpoints/OTX/35,131/forecast",
      "source": "NWS"
    },
    "48.053,-120.921": {
      "weatherByDay": {
        "2026-04-21": {
          "temperature_f": 53.0,
          "cloud_cover_pct": 50.6,
          "wind_speed_mph": 6.760827165499999,
          "wind_gust_mph": 18.412465472,
          "overnight_snowfall_in": 0.0,
          "overnight_low_f": 38.0,
          "humidity_pct": 67.28571428571429,
          "precipitation_in": 0.03999999910593,
          "visibility_mi": null,
          "precipitation_probability_pct": 47
        },
        "2026-04-22": {
          "temperature_f": 39.0,
          "cloud_cover_pct": 73.33333333333333,
          "wind_speed_mph": 14.576535165333334,
          "wind_gust_mph": 31.071035484,
          "overnight_snowfall_in": 0.0,
          "overnight_low_f": 34.0,
          "humidity_pct": 84.4090909090909,
          "precipitation_in": 0.1099999975413082,
          "visibility_mi": null,
          "precipitation_probability_pct": 67
        },
        "2026-04-23": {
          "temperature_f": 42.0,
          "cloud_cover_pct": 41.0,
          "wind_speed_mph": 12.987364038285714,
          "wind_gust_mph": 27.618698208,
          "overnight_snowfall_in": 0.30000001192093,
          "overnight_low_f": 29.0,
          "humidity_pct": 73.88888888888889,
          "precipitation_in": 0.049999998882412605,
          "visibility_mi": null,
          "precipitation_probability_pct": 37
        },
        "2026-04-24": {
          "temperature_f": 46.0,
          "cloud_cover_pct": 10.125,
          "wind_speed_mph": 9.6665443728,
          "wind_gust_mph": 25.317140024,
          "overnight_snowfall_in": 0.0,
          "overnight_low_f": 26.0,
          "humidity_pct": 51.8421052631579,
          "precipitation_in": 0.0,
          "visibility_mi": null,
          "precipitation_probability_pct": 4
        },
        "2026-04-25": {
          "temperature_f": 49.0,
          "cloud_cover_pct": 13.25,
          "wind_speed_mph": 6.904674552,
          "wind_gust_mph": 13.809349104,
          "overnight_snowfall_in": 0.0,
          "overnight_low_f": 29.0,
          "humidity_pct": 50.526315789473685,
          "precipitation_in": 0.0,
          "visibility_mi": null,
          "precipitation_probability_pct": 10
        },
        "2026-04-26": {
          "temperature_f": 50.0,
          "cloud_cover_pct": 20.25,
          "wind_speed_mph": 6.904674552,
          "wind_gust_mph": 14.960128196000001,
          "overnight_snowfall_in": 0.0,
          "overnight_low_f": 31.0,
          "humidity_pct": 55.89473684210526,
          "precipitation_in": 0.0,
          "visibility_mi": null,
          "precipitation_probability_pct": 15
        },
        "2026-04-27": {
          "temperature_f": 47.0,
          "cloud_cover_pct": 28.25,
          "wind_speed_mph": 8.055453644,
          "wind_gust_mph": 17.26168638,
          "overnight_snowfall_in": 0.0,
          "overnight_low_f": 33.0,
          "humidity_pct": 65.52631578947368,
          "precipitation_in": 0.0,
          "visibility_mi": null,
          "precipitation_probability_pct": 23
        }
      },
      "forecastUrl": "https://api.weather.gov/gridpoints/OTX/33,128/forecast",
      "source": "NWS"
    },
    "47.881,-123.127": {
      "weatherByDay": {
        "2026-04-21": {
          "temperature_f": 66.0,
          "cloud_cover_pct": 63.416666666666664,
          "wind_speed_mph": 3.0687442453333333,
          "wind_gust_mph": 11.50779092,
          "overnight_snowfall_in": 0.0,
          "overnight_low_f": 45.0,
          "humidity_pct": 60.95,
          "precipitation_in": 0.15000000596046,
          "visibility_mi": null,
          "precipitation_probability_pct": 64
        },
        "2026-04-22": {
          "temperature_f": 53.0,
          "cloud_cover_pct": 85.0,
          "wind_speed_mph": 5.178505914,
          "wind_gust_mph": 10.357011828,
          "overnight_snowfall_in": 0.0,
          "overnight_low_f": 42.0,
          "humidity_pct": 71.88888888888889,
          "precipitation_in": 0.24999999813735357,
          "visibility_mi": null,
          "precipitation_probability_pct": 70
        },
        "2026-04-23": {
          "temperature_f": 54.0,
          "cloud_cover_pct": 34.42857142857143,
          "wind_speed_mph": 6.329285006,
          "wind_gust_mph": 12.658570012,
          "overnight_snowfall_in": 0.0,
          "overnight_low_f": 38.0,
          "humidity_pct": 55.89473684210526,
          "precipitation_in": 0.0,
          "visibility_mi": null,
          "precipitation_probability_pct": 8
        },
        "2026-04-24": {
          "temperature_f": 57.0,
          "cloud_cover_pct": 9.0,
          "wind_speed_mph": 7.069071565142856,
          "wind_gust_mph": 20.714023656,
          "overnight_snowfall_in": 0.0,
          "overnight_low_f": 38.0,
          "humidity_pct": 42.2,
          "precipitation_in": 0.0,
          "visibility_mi": null,
          "precipitation_probability_pct": null
        },
        "2026-04-25": {
          "temperature_f": 59.0,
          "cloud_cover_pct": 15.333333333333334,
          "wind_speed_mph": 6.6745187336,
          "wind_gust_mph": 19.563244564,
          "overnight_snowfall_in": 0.0,
          "overnight_low_f": 40.0,
          "humidity_pct": 37.05882352941177,
          "precipitation_in": 0.0,
          "visibility_mi": null,
          "precipitation_probability_pct": null
        },
        "2026-04-26": {
          "temperature_f": 59.0,
          "cloud_cover_pct": 19.25,
          "wind_speed_mph": 5.75389546,
          "wind_gust_mph": 17.26168638,
          "overnight_snowfall_in": 0.0,
          "overnight_low_f": 41.0,
          "humidity_pct": 40.35294117647059,
          "precipitation_in": 0.0,
          "visibility_mi": null,
          "precipitation_probability_pct": 5
        },
        "2026-04-27": {
          "temperature_f": 58.0,
          "cloud_cover_pct": 32.666666666666664,
          "wind_speed_mph": 5.260704420571429,
          "wind_gust_mph": 14.960128196000001,
          "overnight_snowfall_in": 0.0,
          "overnight_low_f": 39.0,
          "humidity_pct": 52.523809523809526,
          "precipitation_in": 0.0,
          "visibility_mi": null,
          "precipitation_probability_pct": 14
        }
      },
      "forecastUrl": "https://api.weather.gov/gridpoints/SEW/102,86/forecast",
      "source": "NWS"
    },
    "47.46,-120.894": {
      "weatherByDay": {
        "2026-04-21": {
          "temperature_f": 57.0,
          "cloud_cover_pct": 59.46153846153846,
          "wind_speed_mph": 8.219850657142857,
          "wind_gust_mph": 20.714023656,
          "overnight_snowfall_in": 0.0,
          "overnight_low_f": 42.0,
          "humidity_pct": 63.916666666666664,
          "precipitation_in": 0.03999999910593,
          "visibility_mi": null,
          "precipitation_probability_pct": 48
        },
        "2026-04-22": {
          "temperature_f": 41.0,
          "cloud_cover_pct": 72.0,
          "wind_speed_mph": 16.110907288,
          "wind_gust_mph": 36.824930944,
          "overnight_snowfall_in": 0.0,
          "overnight_low_f": 36.0,
          "humidity_pct": 85.875,
          "precipitation_in": 0.34999999962746803,
          "visibility_mi": null,
          "precipitation_probability_pct": 71
        },
        "2026-04-23": {
          "temperature_f": 46.0,
          "cloud_cover_pct": 34.0,
          "wind_speed_mph": 13.425756073333332,
          "wind_gust_mph": 34.52337276,
          "overnight_snowfall_in": 0.0,
          "overnight_low_f": 31.0,
          "humidity_pct": 73.83333333333333,
          "precipitation_in": 0.0,
          "visibility_mi": null,
          "precipitation_probability_pct": 25
        },
        "2026-04-24": {
          "temperature_f": 49.0,
          "cloud_cover_pct": 12.714285714285714,
          "wind_speed_mph": 8.774690576500001,
          "wind_gust_mph": 27.618698208,
          "overnight_snowfall_in": 0.0,
          "overnight_low_f": 30.0,
          "humidity_pct": 55.22222222222222,
          "precipitation_in": 0.0,
          "visibility_mi": null,
          "precipitation_probability_pct": 4
        },
        "2026-04-25": {
          "temperature_f": 50.0,
          "cloud_cover_pct": 19.25,
          "wind_speed_mph": 6.5210815213333335,
          "wind_gust_mph": 14.960128196000001,
          "overnight_snowfall_in": 0.0,
          "overnight_low_f": 30.0,
          "humidity_pct": 53.5625,
          "precipitation_in": 0.0,
          "visibility_mi": null,
          "precipitation_probability_pct": 9
        },
        "2026-04-26": {
          "temperature_f": 51.0,
          "cloud_cover_pct": 23.5,
          "wind_speed_mph": 6.329285006,
          "wind_gust_mph": 14.960128196000001,
          "overnight_snowfall_in": 0.0,
          "overnight_low_f": 32.0,
          "humidity_pct": 56.111111111111114,
          "precipitation_in": 0.0,
          "visibility_mi": null,
          "precipitation_probability_pct": 13
        },
        "2026-04-27": {
          "temperature_f": 51.0,
          "cloud_cover_pct": 29.25,
          "wind_speed_mph": 8.055453644,
          "wind_gust_mph": 17.26168638,
          "overnight_snowfall_in": 0.0,
          "overnight_low_f": 34.0,
          "humidity_pct": 63.55555555555556,
          "precipitation_in": 0.0,
          "visibility_mi": null,
          "precipitation_probability_pct": 19
        }
      },
      "forecastUrl": "https://api.weather.gov/gridpoints/OTX/29,100/forecast",
      "source": "NWS"
    },
    "47.4274,-121.0269": {
      "weatherByDay": {
        "2026-04-21": {
          "temperature_f": 62.0,
          "cloud_cover_pct": 65.14285714285714,
          "wind_speed_mph": 5.466200687000001,
          "wind_gust_mph": 14.960128196000001,
          "overnight_snowfall_in": 0.0,
          "overnight_low_f": 43.0,
          "humidity_pct": 65.94117647058823,
          "precipitation_in": 0.03999999910593,
          "visibility_mi": null,
          "precipitation_probability_pct": 52
        },
        "2026-04-22": {
          "temperature_f": 46.0,
          "cloud_cover_pct": 78.625,
          "wind_speed_mph": 11.50779092,
          "wind_gust_mph": 26.467919115999997,
          "overnight_snowfall_in": 0.0,
          "overnight_low_f": 39.0,
          "humidity_pct": 83.11111111111111,
          "precipitation_in": 0.21999999880790302,
          "visibility_mi": null,
          "precipitation_probability_pct": 77
        },
        "2026-04-23": {
          "temperature_f": 51.0,
          "cloud_cover_pct": 49.625,
          "wind_speed_mph": 9.589825766666666,
          "wind_gust_mph": 24.166360932000003,
          "overnight_snowfall_in": 0.0,
          "overnight_low_f": 34.0,
          "humidity_pct": 71.29411764705883,
          "precipitation_in": 0.0,
          "visibility_mi": null,
          "precipitation_probability_pct": 28
        },
        "2026-04-24": {
          "temperature_f": 56.0,
          "cloud_cover_pct": 13.833333333333334,
          "wind_speed_mph": 5.178505914,
          "wind_gust_mph": 18.412465472,
          "overnight_snowfall_in": 0.0,
          "overnight_low_f": 32.0,
          "humidity_pct": 56.36842105263158,
          "precipitation_in": 0.0,
          "visibility_mi": null,
          "precipitation_probability_pct": 4
        },
        "2026-04-25": {
          "temperature_f": 56.0,
          "cloud_cover_pct": 23.0,
          "wind_speed_mph": 5.178505914,
          "wind_gust_mph": 13.809349104,
          "overnight_snowfall_in": 0.0,
          "overnight_low_f": 33.0,
          "humidity_pct": 51.333333333333336,
          "precipitation_in": 0.0,
          "visibility_mi": null,
          "precipitation_probability_pct": 7
        },
        "2026-04-26": {
          "temperature_f": 57.0,
          "cloud_cover_pct": 31.0,
          "wind_speed_mph": 5.5237396416,
          "wind_gust_mph": 12.658570012,
          "overnight_snowfall_in": 0.0,
          "overnight_low_f": 34.0,
          "humidity_pct": 52.666666666666664,
          "precipitation_in": 0.0,
          "visibility_mi": null,
          "precipitation_probability_pct": 15
        },
        "2026-04-27": {
          "temperature_f": 57.0,
          "cloud_cover_pct": 39.5,
          "wind_speed_mph": 5.75389546,
          "wind_gust_mph": 13.809349104,
          "overnight_snowfall_in": 0.0,
          "overnight_low_f": 35.0,
          "humidity_pct": 64.21052631578948,
          "precipitation_in": 0.0,
          "visibility_mi": null,
          "precipitation_probability_pct": 22
        }
      },
      "forecastUrl": "https://api.weather.gov/gridpoints/PDT/75,195/forecast",
      "source": "NWS"
    },
    "46.93,-121.657": {
      "weatherByDay": {
        "2026-04-21": {
          "temperature_f": 56.0,
          "cloud_cover_pct": 62.608695652173914,
          "wind_speed_mph": 4.219523337333333,
          "wind_gust_mph": 14.960128196000001,
          "overnight_snowfall_in": 0.0,
          "overnight_low_f": 38.0,
          "humidity_pct": 71.04545454545455,
          "precipitation_in": 0.079999998211861,
          "visibility_mi": null,
          "precipitation_probability_pct": 76
        },
        "2026-04-22": {
          "temperature_f": 37.0,
          "cloud_cover_pct": 86.92857142857143,
          "wind_speed_mph": 13.809349103999999,
          "wind_gust_mph": 24.166360932000003,
          "overnight_snowfall_in": 3.0000000745058304,
          "overnight_low_f": 31.0,
          "humidity_pct": 85.04545454545455,
          "precipitation_in": 0.449999995529643,
          "visibility_mi": null,
          "precipitation_probability_pct": 92
        },
        "2026-04-23": {
          "temperature_f": 40.0,
          "cloud_cover_pct": 45.714285714285715,
          "wind_speed_mph": 10.932401374,
          "wind_gust_mph": 25.317140024,
          "overnight_snowfall_in": 0.10000000149012,
          "overnight_low_f": 27.0,
          "humidity_pct": 71.2,
          "precipitation_in": 0.0099999997764826,
          "visibility_mi": null,
          "precipitation_probability_pct": 47
        },
        "2026-04-24": {
          "temperature_f": 46.0,
          "cloud_cover_pct": 8.875,
          "wind_speed_mph": 9.4363885544,
          "wind_gust_mph": 19.563244564,
          "overnight_snowfall_in": 0.0,
          "overnight_low_f": 27.0,
          "humidity_pct": 50.3,
          "precipitation_in": 0.0,
          "visibility_mi": null,
          "precipitation_probability_pct": 6
        },
        "2026-04-25": {
          "temperature_f": 46.0,
          "cloud_cover_pct": 21.25,
          "wind_speed_mph": 8.976076917600002,
          "wind_gust_mph": 23.01558184,
          "overnight_snowfall_in": 0.0,
          "overnight_low_f": 29.0,
          "humidity_pct": 47.68181818181818,
          "precipitation_in": 0.0,
          "visibility_mi": null,
          "precipitation_probability_pct": 10
        },
        "2026-04-26": {
          "temperature_f": 46.0,
          "cloud_cover_pct": 24.75,
          "wind_speed_mph": 8.055453644,
          "wind_gust_mph": 18.412465472,
          "overnight_snowfall_in": 0.0,
          "overnight_low_f": 30.0,
          "humidity_pct": 48.78260869565217,
          "precipitation_in": 0.0,
          "visibility_mi": null,
          "precipitation_probability_pct": 21
        },
        "2026-04-27": {
          "temperature_f": 46.0,
          "cloud_cover_pct": 40.75,
          "wind_speed_mph": 8.055453644,
          "wind_gust_mph": 20.714023656,
          "overnight_snowfall_in": 0.0,
          "overnight_low_f": 32.0,
          "humidity_pct": 57.36363636363637,
          "precipitation_in": 0.0,
          "visibility_mi": null,
          "precipitation_probability_pct": 30
        }
      },
      "forecastUrl": "https://api.weather.gov/gridpoints/SEW/140,32/forecast",
      "source": "NWS"
    },
    "46.803,-121.737": {
      "weatherByDay": {
        "2026-04-21": {
          "temperature_f": 55.0,
          "cloud_cover_pct": 65.0,
          "wind_speed_mph": 6.0735563188888895,
          "wind_gust_mph": 18.412465472,
          "overnight_snowfall_in": 0.0,
          "overnight_low_f": 38.0,
          "humidity_pct": 64.36842105263158,
          "precipitation_in": 0.12999999895691522,
          "visibility_mi": null,
          "precipitation_probability_pct": 79
        },
        "2026-04-22": {
          "temperature_f": 33.0,
          "cloud_cover_pct": 84.38461538461539,
          "wind_speed_mph": 16.996121974153844,
          "wind_gust_mph": 26.467919115999997,
          "overnight_snowfall_in": 7.9000000730156215,
          "overnight_low_f": 30.0,
          "humidity_pct": 78.23809523809524,
          "precipitation_in": 0.8100000005215481,
          "visibility_mi": null,
          "precipitation_probability_pct": 94
        },
        "2026-04-23": {
          "temperature_f": 39.0,
          "cloud_cover_pct": 46.285714285714285,
          "wind_speed_mph": 22.02919976114286,
          "wind_gust_mph": 24.166360932000003,
          "overnight_snowfall_in": 0.30000000447035,
          "overnight_low_f": 27.0,
          "humidity_pct": 65.05263157894737,
          "precipitation_in": 0.0399999991059306,
          "visibility_mi": null,
          "precipitation_probability_pct": 50
        },
        "2026-04-24": {
          "temperature_f": 45.0,
          "cloud_cover_pct": 8.666666666666666,
          "wind_speed_mph": 14.8162808095,
          "wind_gust_mph": 24.166360932000003,
          "overnight_snowfall_in": 0.0,
          "overnight_low_f": 27.0,
          "humidity_pct": 44.85,
          "precipitation_in": 0.0,
          "visibility_mi": null,
          "precipitation_probability_pct": 6
        },
        "2026-04-25": {
          "temperature_f": 45.0,
          "cloud_cover_pct": 20.5,
          "wind_speed_mph": 12.329775985714287,
          "wind_gust_mph": 24.166360932000003,
          "overnight_snowfall_in": 0.0,
          "overnight_low_f": 28.0,
          "humidity_pct": 41.54545454545455,
          "precipitation_in": 0.0,
          "visibility_mi": null,
          "precipitation_probability_pct": 10
        },
        "2026-04-26": {
          "temperature_f": 45.0,
          "cloud_cover_pct": 25.0,
          "wind_speed_mph": 11.50779092,
          "wind_gust_mph": 20.714023656,
          "overnight_snowfall_in": 0.0,
          "overnight_low_f": 29.0,
          "humidity_pct": 41.27272727272727,
          "precipitation_in": 0.0,
          "visibility_mi": null,
          "precipitation_probability_pct": 22
        },
        "2026-04-27": {
          "temperature_f": 45.0,
          "cloud_cover_pct": 41.25,
          "wind_speed_mph": 11.891383950666667,
          "wind_gust_mph": 21.864802748000002,
          "overnight_snowfall_in": 0.10000000149012,
          "overnight_low_f": 31.0,
          "humidity_pct": 49.666666666666664,
          "precipitation_in": 0.029999999329447604,
          "visibility_mi": null,
          "precipitation_probability_pct": 29
        }
      },
      "forecastUrl": "https://api.weather.gov/gridpoints/SEW/136,27/forecast",
      "source": "NWS"
    },
    "46.186,-121.492": {
      "weatherByDay": {
        "2026-04-21": {
          "temperature_f": 31.0,
          "cloud_cover_pct": 76.28571428571429,
          "wind_speed_mph": 17.837075926,
          "wind_gust_mph": 36.824930944,
          "overnight_snowfall_in": 1.90000005066399,
          "overnight_low_f": 32.0,
          "humidity_pct": 68.0,
          "precipitation_in": 0.19999999925493803,
          "visibility_mi": null,
          "precipitation_probability_pct": 69
        },
        "2026-04-22": {
          "temperature_f": 22.0,
          "cloud_cover_pct": 87.0,
          "wind_speed_mph": 41.428047312,
          "wind_gust_mph": 58.689733692,
          "overnight_snowfall_in": 15.500000119209362,
          "overnight_low_f": 19.0,
          "humidity_pct": 75.86363636363636,
          "precipitation_in": 1.120000023394828,
          "visibility_mi": null,
          "precipitation_probability_pct": 88
        },
        "2026-04-23": {
          "temperature_f": 29.0,
          "cloud_cover_pct": 48.285714285714285,
          "wind_speed_mph": 27.618698207999998,
          "wind_gust_mph": 51.78505914,
          "overnight_snowfall_in": 0.40000000596046004,
          "overnight_low_f": 18.0,
          "humidity_pct": 60.94444444444444,
          "precipitation_in": 0.03999999910593,
          "visibility_mi": null,
          "precipitation_probability_pct": 32
        },
        "2026-04-24": {
          "temperature_f": 34.0,
          "cloud_cover_pct": 13.375,
          "wind_speed_mph": 18.576862485142858,
          "wind_gust_mph": 35.674151852,
          "overnight_snowfall_in": 0.0,
          "overnight_low_f": 18.0,
          "humidity_pct": 39.388888888888886,
          "precipitation_in": 0.0,
          "visibility_mi": null,
          "precipitation_probability_pct": 6
        },
        "2026-04-25": {
          "temperature_f": 33.0,
          "cloud_cover_pct": 27.75,
          "wind_speed_mph": 19.563244563999998,
          "wind_gust_mph": 28.7694773,
          "overnight_snowfall_in": 0.0,
          "overnight_low_f": 19.0,
          "humidity_pct": 34.705882352941174,
          "precipitation_in": 0.0,
          "visibility_mi": null,
          "precipitation_probability_pct": 9
        },
        "2026-04-26": {
          "temperature_f": 34.0,
          "cloud_cover_pct": 27.25,
          "wind_speed_mph": 17.837075926,
          "wind_gust_mph": 28.7694773,
          "overnight_snowfall_in": 0.0,
          "overnight_low_f": 20.0,
          "humidity_pct": 33.3,
          "precipitation_in": 0.0,
          "visibility_mi": null,
          "precipitation_probability_pct": 18
        },
        "2026-04-27": {
          "temperature_f": 35.0,
          "cloud_cover_pct": 40.75,
          "wind_speed_mph": 19.892038590285715,
          "wind_gust_mph": 31.071035484,
          "overnight_snowfall_in": 0.0,
          "overnight_low_f": 21.0,
          "humidity_pct": 44.0,
          "precipitation_in": 0.0,
          "visibility_mi": null,
          "precipitation_probability_pct": 26
        }
      },
      "forecastUrl": "https://api.weather.gov/gridpoints/PDT/49,140/forecast",
      "source": "NWS"
    },
    "46.184,-122.197": {
      "weatherByDay": {
        "2026-04-21": {
          "temperature_f": 40.0,
          "cloud_cover_pct": 81.85714285714286,
          "wind_speed_mph": 8.877438709714285,
          "wind_gust_mph": 18.412465472,
          "overnight_snowfall_in": 0.0,
          "overnight_low_f": 37.0,
          "humidity_pct": 80.85714285714286,
          "precipitation_in": 0.28999999165535,
          "visibility_mi": 8.06216285329169,
          "precipitation_probability_pct": 82
        },
        "2026-04-22": {
          "temperature_f": 33.0,
          "cloud_cover_pct": 90.23809523809524,
          "wind_speed_mph": 16.932892353714287,
          "wind_gust_mph": 29.920256392000002,
          "overnight_snowfall_in": 13.500000096857523,
          "overnight_low_f": 30.0,
          "humidity_pct": 89.75,
          "precipitation_in": 1.7999999821186001,
          "visibility_mi": 2.9309596805672635,
          "precipitation_probability_pct": 97
        },
        "2026-04-23": {
          "temperature_f": 39.0,
          "cloud_cover_pct": 68.5,
          "wind_speed_mph": 10.685805854285714,
          "wind_gust_mph": 27.618698208,
          "overnight_snowfall_in": 0.80000001192093,
          "overnight_low_f": 28.0,
          "humidity_pct": 78.83333333333333,
          "precipitation_in": 0.11999999731779101,
          "visibility_mi": 8.46716396754475,
          "precipitation_probability_pct": 62
        },
        "2026-04-24": {
          "temperature_f": 47.0,
          "cloud_cover_pct": 15.0,
          "wind_speed_mph": 9.863820788571429,
          "wind_gust_mph": 23.01558184,
          "overnight_snowfall_in": 0.0,
          "overnight_low_f": 28.0,
          "humidity_pct": 56.78947368421053,
          "precipitation_in": 0.0,
          "visibility_mi": null,
          "precipitation_probability_pct": 13
        },
        "2026-04-25": {
          "temperature_f": 47.0,
          "cloud_cover_pct": 21.5,
          "wind_speed_mph": 11.836584946285715,
          "wind_gust_mph": 24.166360932000003,
          "overnight_snowfall_in": 0.0,
          "overnight_low_f": 31.0,
          "humidity_pct": 43.54545454545455,
          "precipitation_in": 0.0,
          "visibility_mi": null,
          "precipitation_probability_pct": 13
        },
        "2026-04-26": {
          "temperature_f": 43.0,
          "cloud_cover_pct": 32.714285714285715,
          "wind_speed_mph": 10.357011828,
          "wind_gust_mph": 18.412465472,
          "overnight_snowfall_in": 0.0,
          "overnight_low_f": 30.0,
          "humidity_pct": 43.34782608695652,
          "precipitation_in": 0.019999999552965,
          "visibility_mi": null,
          "precipitation_probability_pct": 26
        },
        "2026-04-27": {
          "temperature_f": 44.0,
          "cloud_cover_pct": 41.4,
          "wind_speed_mph": 9.206232736,
          "wind_gust_mph": 19.563244564,
          "overnight_snowfall_in": 0.0,
          "overnight_low_f": 31.0,
          "humidity_pct": 56.72222222222222,
          "precipitation_in": 0.0099999997764826,
          "visibility_mi": null,
          "precipitation_probability_pct": 34
        }
      },
      "forecastUrl": "https://api.weather.gov/gridpoints/PQR/134,131/forecast",
      "source": "NWS"
    },
    "48.828,-121.689": {
      "weatherByDay": {
        "2026-04-21": {
          "temperature_f": 64.0,
          "cloud_cover_pct": 59.77272727272727,
          "wind_speed_mph": 4.5072181103333335,
          "wind_gust_mph": 9.206232736,
          "overnight_snowfall_in": 0.0,
          "overnight_low_f": 43.0,
          "humidity_pct": 68.9,
          "precipitation_in": 0.070000000298023,
          "visibility_mi": null,
          "precipitation_probability_pct": 49
        },
        "2026-04-22": {
          "temperature_f": 47.0,
          "cloud_cover_pct": 87.64285714285714,
          "wind_speed_mph": 4.393883805818183,
          "wind_gust_mph": 10.357011828,
          "overnight_snowfall_in": 0.0,
          "overnight_low_f": 40.0,
          "humidity_pct": 87.0,
          "precipitation_in": 0.229999996721744,
          "visibility_mi": null,
          "precipitation_probability_pct": 78
        },
        "2026-04-23": {
          "temperature_f": 49.0,
          "cloud_cover_pct": 46.0,
          "wind_speed_mph": 7.8252978256,
          "wind_gust_mph": 14.960128196000001,
          "overnight_snowfall_in": 0.0,
          "overnight_low_f": 35.0,
          "humidity_pct": 71.52941176470588,
          "precipitation_in": 0.05999999865889501,
          "visibility_mi": null,
          "precipitation_probability_pct": 42
        },
        "2026-04-24": {
          "temperature_f": 54.0,
          "cloud_cover_pct": 9.375,
          "wind_speed_mph": 7.8252978256,
          "wind_gust_mph": 18.412465472,
          "overnight_snowfall_in": 0.0,
          "overnight_low_f": 34.0,
          "humidity_pct": 50.55,
          "precipitation_in": 0.0,
          "visibility_mi": null,
          "precipitation_probability_pct": 2
        },
        "2026-04-25": {
          "temperature_f": 55.0,
          "cloud_cover_pct": 13.0,
          "wind_speed_mph": 7.8252978256,
          "wind_gust_mph": 19.563244564,
          "overnight_snowfall_in": 0.0,
          "overnight_low_f": 35.0,
          "humidity_pct": 46.0,
          "precipitation_in": 0.0,
          "visibility_mi": null,
          "precipitation_probability_pct": 5
        },
        "2026-04-26": {
          "temperature_f": 55.0,
          "cloud_cover_pct": 25.75,
          "wind_speed_mph": 6.041590233000001,
          "wind_gust_mph": 14.960128196000001,
          "overnight_snowfall_in": 0.0,
          "overnight_low_f": 37.0,
          "humidity_pct": 50.333333333333336,
          "precipitation_in": 0.0,
          "visibility_mi": null,
          "precipitation_probability_pct": 15
        },
        "2026-04-27": {
          "temperature_f": 53.0,
          "cloud_cover_pct": 41.0,
          "wind_speed_mph": 6.041590233000001,
          "wind_gust_mph": 14.960128196000001,
          "overnight_snowfall_in": 0.0,
          "overnight_low_f": 37.0,
          "humidity_pct": 63.27272727272727,
          "precipitation_in": 0.0099999997764826,
          "visibility_mi": null,
          "precipitation_probability_pct": 30
        }
      },
      "forecastUrl": "https://api.weather.gov/gridpoints/SEW/156,121/forecast",
      "source": "NWS"
    },
    "48.4748,-121.075": {
      "weatherByDay": {
        "2026-04-21": {
          "temperature_f": 60.0,
          "cloud_cover_pct": 57.25,
          "wind_speed_mph": 6.041590233000001,
          "wind_gust_mph": 10.357011828,
          "overnight_snowfall_in": 0.0,
          "overnight_low_f": 40.0,
          "humidity_pct": 72.38888888888889,
          "precipitation_in": 0.050000000745058,
          "visibility_mi": null,
          "precipitation_probability_pct": 50
        },
        "2026-04-22": {
          "temperature_f": 43.0,
          "cloud_cover_pct": 82.81818181818181,
          "wind_speed_mph": 9.717690110222224,
          "wind_gust_mph": 14.960128196000001,
          "overnight_snowfall_in": 0.0,
          "overnight_low_f": 39.0,
          "humidity_pct": 92.05882352941177,
          "precipitation_in": 0.279999995604157,
          "visibility_mi": null,
          "precipitation_probability_pct": 71
        },
        "2026-04-23": {
          "temperature_f": 45.0,
          "cloud_cover_pct": 50.375,
          "wind_speed_mph": 12.16537897257143,
          "wind_gust_mph": 18.412465472,
          "overnight_snowfall_in": 0.0,
          "overnight_low_f": 33.0,
          "humidity_pct": 72.63157894736842,
          "precipitation_in": 0.109999999403953,
          "visibility_mi": null,
          "precipitation_probability_pct": 45
        },
        "2026-04-24": {
          "temperature_f": 49.0,
          "cloud_cover_pct": 13.571428571428571,
          "wind_speed_mph": 8.439046674666667,
          "wind_gust_mph": 19.563244564,
          "overnight_snowfall_in": 0.0,
          "overnight_low_f": 31.0,
          "humidity_pct": 56.31578947368421,
          "precipitation_in": 0.0,
          "visibility_mi": null,
          "precipitation_probability_pct": 3
        },
        "2026-04-25": {
          "temperature_f": 51.0,
          "cloud_cover_pct": 18.75,
          "wind_speed_mph": 8.439046674666667,
          "wind_gust_mph": 18.412465472,
          "overnight_snowfall_in": 0.0,
          "overnight_low_f": 31.0,
          "humidity_pct": 51.5,
          "precipitation_in": 0.0,
          "visibility_mi": null,
          "precipitation_probability_pct": 7
        },
        "2026-04-26": {
          "temperature_f": 51.0,
          "cloud_cover_pct": 30.75,
          "wind_speed_mph": 6.904674552,
          "wind_gust_mph": 16.110907288,
          "overnight_snowfall_in": 0.0,
          "overnight_low_f": 34.0,
          "humidity_pct": 54.94444444444444,
          "precipitation_in": 0.0,
          "visibility_mi": null,
          "precipitation_probability_pct": 17
        },
        "2026-04-27": {
          "temperature_f": 51.0,
          "cloud_cover_pct": 44.0,
          "wind_speed_mph": 7.671860613333333,
          "wind_gust_mph": 16.110907288,
          "overnight_snowfall_in": 0.0,
          "overnight_low_f": 35.0,
          "humidity_pct": 67.8125,
          "precipitation_in": 0.0,
          "visibility_mi": null,
          "precipitation_probability_pct": 27
        }
      },
      "forecastUrl": "https://api.weather.gov/gridpoints/SEW/172,101/forecast",
      "source": "NWS"
    },
    "47.942,-123.699": {
      "weatherByDay": {
        "2026-04-21": {
          "temperature_f": 57.0,
          "cloud_cover_pct": 61.65217391304348,
          "wind_speed_mph": 6.285024271692308,
          "wind_gust_mph": 16.110907288,
          "overnight_snowfall_in": 0.0,
          "overnight_low_f": 39.0,
          "humidity_pct": 72.8695652173913,
          "precipitation_in": 0.12999999895691802,
          "visibility_mi": null,
          "precipitation_probability_pct": 72
        },
        "2026-04-22": {
          "temperature_f": 46.0,
          "cloud_cover_pct": 80.57142857142857,
          "wind_speed_mph": 10.357011828,
          "wind_gust_mph": 14.960128196000001,
          "overnight_snowfall_in": 0.0,
          "overnight_low_f": 37.0,
          "humidity_pct": 85.23809523809524,
          "precipitation_in": 0.310000002384189,
          "visibility_mi": null,
          "precipitation_probability_pct": 76
        },
        "2026-04-23": {
          "temperature_f": 47.0,
          "cloud_cover_pct": 32.75,
          "wind_speed_mph": 7.1348303704000005,
          "wind_gust_mph": 13.809349104,
          "overnight_snowfall_in": 0.0,
          "overnight_low_f": 33.0,
          "humidity_pct": 71.4,
          "precipitation_in": 0.0,
          "visibility_mi": null,
          "precipitation_probability_pct": 7
        },
        "2026-04-24": {
          "temperature_f": 50.0,
          "cloud_cover_pct": 9.5,
          "wind_speed_mph": 8.5157652808,
          "wind_gust_mph": 21.864802748000002,
          "overnight_snowfall_in": 0.0,
          "overnight_low_f": 34.0,
          "humidity_pct": 55.95238095238095,
          "precipitation_in": 0.0,
          "visibility_mi": null,
          "precipitation_probability_pct": 1
        },
        "2026-04-25": {
          "temperature_f": 51.0,
          "cloud_cover_pct": 14.0,
          "wind_speed_mph": 8.2856094624,
          "wind_gust_mph": 21.864802748000002,
          "overnight_snowfall_in": 0.0,
          "overnight_low_f": 36.0,
          "humidity_pct": 45.75,
          "precipitation_in": 0.0,
          "visibility_mi": null,
          "precipitation_probability_pct": 1
        },
        "2026-04-26": {
          "temperature_f": 51.0,
          "cloud_cover_pct": 15.25,
          "wind_speed_mph": 8.2856094624,
          "wind_gust_mph": 20.714023656,
          "overnight_snowfall_in": 0.0,
          "overnight_low_f": 37.0,
          "humidity_pct": 49.57142857142857,
          "precipitation_in": 0.0,
          "visibility_mi": null,
          "precipitation_probability_pct": 6
        },
        "2026-04-27": {
          "temperature_f": 49.0,
          "cloud_cover_pct": 27.0,
          "wind_speed_mph": 9.973418797333334,
          "wind_gust_mph": 20.714023656,
          "overnight_snowfall_in": 0.0,
          "overnight_low_f": 36.0,
          "humidity_pct": 61.18181818181818,
          "precipitation_in": 0.0,
          "visibility_mi": null,
          "precipitation_probability_pct": 15
        }
      },
      "forecastUrl": "https://api.weather.gov/gridpoints/SEW/85,93/forecast",
      "source": "NWS"
    },
    "47.5282,-120.8253": {
      "weatherByDay": {
        "2026-04-21": {
          "temperature_f": 54.0,
          "cloud_cover_pct": 60.42857142857143,
          "wind_speed_mph": 7.233468578285714,
          "wind_gust_mph": 20.714023656,
          "overnight_snowfall_in": 0.0,
          "overnight_low_f": 42.0,
          "humidity_pct": 64.71428571428571,
          "precipitation_in": 0.059999998658895,
          "visibility_mi": null,
          "precipitation_probability_pct": 46
        },
        "2026-04-22": {
          "temperature_f": 40.0,
          "cloud_cover_pct": 74.6,
          "wind_speed_mph": 16.275304301142857,
          "wind_gust_mph": 39.126489128,
          "overnight_snowfall_in": 0.0,
          "overnight_low_f": 36.0,
          "humidity_pct": 84.0,
          "precipitation_in": 0.30999999307095905,
          "visibility_mi": null,
          "precipitation_probability_pct": 68
        },
        "2026-04-23": {
          "temperature_f": 44.0,
          "cloud_cover_pct": 36.57142857142857,
          "wind_speed_mph": 14.76833168066667,
          "wind_gust_mph": 40.277268219999996,
          "overnight_snowfall_in": 0.0,
          "overnight_low_f": 31.0,
          "humidity_pct": 73.04545454545455,
          "precipitation_in": 0.0,
          "visibility_mi": null,
          "precipitation_probability_pct": 25
        },
        "2026-04-24": {
          "temperature_f": 47.0,
          "cloud_cover_pct": 12.571428571428571,
          "wind_speed_mph": 9.041835722857144,
          "wind_gust_mph": 28.7694773,
          "overnight_snowfall_in": 0.0,
          "overnight_low_f": 30.0,
          "humidity_pct": 54.31578947368421,
          "precipitation_in": 0.0,
          "visibility_mi": null,
          "precipitation_probability_pct": 5
        },
        "2026-04-25": {
          "temperature_f": 48.0,
          "cloud_cover_pct": 18.0,
          "wind_speed_mph": 9.781622281999999,
          "wind_gust_mph": 16.110907288,
          "overnight_snowfall_in": 0.0,
          "overnight_low_f": 31.0,
          "humidity_pct": 51.68421052631579,
          "precipitation_in": 0.0,
          "visibility_mi": null,
          "precipitation_probability_pct": 9
        },
        "2026-04-26": {
          "temperature_f": 50.0,
          "cloud_cover_pct": 23.25,
          "wind_speed_mph": 8.63084319,
          "wind_gust_mph": 14.960128196000001,
          "overnight_snowfall_in": 0.0,
          "overnight_low_f": 32.0,
          "humidity_pct": 56.95238095238095,
          "precipitation_in": 0.0,
          "visibility_mi": null,
          "precipitation_probability_pct": 12
        },
        "2026-04-27": {
          "temperature_f": 50.0,
          "cloud_cover_pct": 27.0,
          "wind_speed_mph": 11.50779092,
          "wind_gust_mph": 18.412465472,
          "overnight_snowfall_in": 0.0,
          "overnight_low_f": 35.0,
          "humidity_pct": 62.05555555555556,
          "precipitation_in": 0.0,
          "visibility_mi": null,
          "precipitation_probability_pct": 17
        }
      },
      "forecastUrl": "https://api.weather.gov/gridpoints/OTX/31,103/forecast",
      "source": "NWS"
    },
    "46.9145,-121.6415": {
      "weatherByDay": {
        "2026-04-21": {
          "temperature_f": 62.0,
          "cloud_cover_pct": 63.166666666666664,
          "wind_speed_mph": 3.3084898895,
          "wind_gust_mph": 13.809349104,
          "overnight_snowfall_in": 0.0,
          "overnight_low_f": 39.0,
          "humidity_pct": 71.75,
          "precipitation_in": 0.11000000312924402,
          "visibility_mi": null,
          "precipitation_probability_pct": 77
        },
        "2026-04-22": {
          "temperature_f": 42.0,
          "cloud_cover_pct": 86.0,
          "wind_speed_mph": 13.600116541818181,
          "wind_gust_mph": 23.01558184,
          "overnight_snowfall_in": 0.40000000596046004,
          "overnight_low_f": 33.0,
          "humidity_pct": 86.7,
          "precipitation_in": 0.430000014603143,
          "visibility_mi": null,
          "precipitation_probability_pct": 92
        },
        "2026-04-23": {
          "temperature_f": 45.0,
          "cloud_cover_pct": 44.714285714285715,
          "wind_speed_mph": 9.666544372799999,
          "wind_gust_mph": 18.412465472,
          "overnight_snowfall_in": 0.0,
          "overnight_low_f": 29.0,
          "humidity_pct": 70.46666666666667,
          "precipitation_in": 0.0099999997764826,
          "visibility_mi": null,
          "precipitation_probability_pct": 47
        },
        "2026-04-24": {
          "temperature_f": 51.0,
          "cloud_cover_pct": 7.571428571428571,
          "wind_speed_mph": 9.206232735999999,
          "wind_gust_mph": 18.412465472,
          "overnight_snowfall_in": 0.0,
          "overnight_low_f": 28.0,
          "humidity_pct": 52.77777777777778,
          "precipitation_in": 0.0,
          "visibility_mi": null,
          "precipitation_probability_pct": 7
        },
        "2026-04-25": {
          "temperature_f": 51.0,
          "cloud_cover_pct": 20.75,
          "wind_speed_mph": 7.671860613333333,
          "wind_gust_mph": 20.714023656,
          "overnight_snowfall_in": 0.0,
          "overnight_low_f": 30.0,
          "humidity_pct": 51.34782608695652,
          "precipitation_in": 0.0,
          "visibility_mi": null,
          "precipitation_probability_pct": 10
        },
        "2026-04-26": {
          "temperature_f": 52.0,
          "cloud_cover_pct": 24.5,
          "wind_speed_mph": 7.288267582666667,
          "wind_gust_mph": 17.26168638,
          "overnight_snowfall_in": 0.0,
          "overnight_low_f": 31.0,
          "humidity_pct": 50.5,
          "precipitation_in": 0.0,
          "visibility_mi": null,
          "precipitation_probability_pct": 21
        },
        "2026-04-27": {
          "temperature_f": 52.0,
          "cloud_cover_pct": 40.75,
          "wind_speed_mph": 6.6745187336,
          "wind_gust_mph": 18.412465472,
          "overnight_snowfall_in": 0.0,
          "overnight_low_f": 33.0,
          "humidity_pct": 60.18181818181818,
          "precipitation_in": 0.0,
          "visibility_mi": null,
          "precipitation_probability_pct": 30
        }
      },
      "forecastUrl": "https://api.weather.gov/gridpoints/SEW/140,31/forecast",
      "source": "NWS"
    },
    "46.4675,-121.5025": {
      "weatherByDay": {
        "2026-04-21": {
          "temperature_f": 60.0,
          "cloud_cover_pct": 66.34782608695652,
          "wind_speed_mph": 4.080034962545454,
          "wind_gust_mph": 12.658570012,
          "overnight_snowfall_in": 0.0,
          "overnight_low_f": 41.0,
          "humidity_pct": 74.3,
          "precipitation_in": 0.07000000029802321,
          "visibility_mi": null,
          "precipitation_probability_pct": 74
        },
        "2026-04-22": {
          "temperature_f": 35.0,
          "cloud_cover_pct": 86.3,
          "wind_speed_mph": 10.5008592145,
          "wind_gust_mph": 19.563244564,
          "overnight_snowfall_in": 4.2000000029802305,
          "overnight_low_f": 33.0,
          "humidity_pct": 93.7,
          "precipitation_in": 0.96999998390674,
          "visibility_mi": null,
          "precipitation_probability_pct": 88
        },
        "2026-04-23": {
          "temperature_f": 44.0,
          "cloud_cover_pct": 57.714285714285715,
          "wind_speed_mph": 7.8636571286666666,
          "wind_gust_mph": 16.110907288,
          "overnight_snowfall_in": 0.0,
          "overnight_low_f": 30.0,
          "humidity_pct": 79.38095238095238,
          "precipitation_in": 0.0099999997764826,
          "visibility_mi": null,
          "precipitation_probability_pct": 37
        },
        "2026-04-24": {
          "temperature_f": 49.0,
          "cloud_cover_pct": 14.333333333333334,
          "wind_speed_mph": 4.1428047312,
          "wind_gust_mph": 13.809349104,
          "overnight_snowfall_in": 0.0,
          "overnight_low_f": 29.0,
          "humidity_pct": 56.4,
          "precipitation_in": 0.0,
          "visibility_mi": null,
          "precipitation_probability_pct": 6
        },
        "2026-04-25": {
          "temperature_f": 47.0,
          "cloud_cover_pct": 29.0,
          "wind_speed_mph": 4.027726822,
          "wind_gust_mph": 13.809349104,
          "overnight_snowfall_in": 0.0,
          "overnight_low_f": 31.0,
          "humidity_pct": 51.833333333333336,
          "precipitation_in": 0.0,
          "visibility_mi": null,
          "precipitation_probability_pct": 9
        },
        "2026-04-26": {
          "temperature_f": 48.0,
          "cloud_cover_pct": 26.25,
          "wind_speed_mph": 4.219523337333333,
          "wind_gust_mph": 12.658570012,
          "overnight_snowfall_in": 0.0,
          "overnight_low_f": 32.0,
          "humidity_pct": 51.523809523809526,
          "precipitation_in": 0.0,
          "visibility_mi": null,
          "precipitation_probability_pct": 17
        },
        "2026-04-27": {
          "temperature_f": 49.0,
          "cloud_cover_pct": 43.75,
          "wind_speed_mph": 4.603116368,
          "wind_gust_mph": 13.809349104,
          "overnight_snowfall_in": 0.0,
          "overnight_low_f": 34.0,
          "humidity_pct": 64.26315789473684,
          "precipitation_in": 0.0,
          "visibility_mi": null,
          "precipitation_probability_pct": 24
        }
      },
      "forecastUrl": "https://api.weather.gov/gridpoints/SEW/140,10/forecast",
      "source": "NWS"
    },
    "48.483,-121.053": {
      "weatherByDay": {
        "2026-04-21": {
          "temperature_f": 51.0,
          "cloud_cover_pct": 57.47826086956522,
          "wind_speed_mph": 7.966932175384616,
          "wind_gust_mph": 11.50779092,
          "overnight_snowfall_in": 0.0,
          "overnight_low_f": 37.0,
          "humidity_pct": 68.71428571428571,
          "precipitation_in": 0.050000000745058,
          "visibility_mi": null,
          "precipitation_probability_pct": 50
        },
        "2026-04-22": {
          "temperature_f": 35.0,
          "cloud_cover_pct": 81.27272727272727,
          "wind_speed_mph": 14.795731182857143,
          "wind_gust_mph": 17.26168638,
          "overnight_snowfall_in": 0.80000002682209,
          "overnight_low_f": 33.0,
          "humidity_pct": 91.75,
          "precipitation_in": 0.279999997466799,
          "visibility_mi": null,
          "precipitation_probability_pct": 69
        },
        "2026-04-23": {
          "temperature_f": 36.0,
          "cloud_cover_pct": 48.875,
          "wind_speed_mph": 17.069889864666667,
          "wind_gust_mph": 20.714023656,
          "overnight_snowfall_in": 1.00000002980232,
          "overnight_low_f": 27.0,
          "humidity_pct": 74.81818181818181,
          "precipitation_in": 0.109999999403953,
          "visibility_mi": null,
          "precipitation_probability_pct": 45
        },
        "2026-04-24": {
          "temperature_f": 40.0,
          "cloud_cover_pct": 12.333333333333334,
          "wind_speed_mph": 11.124197889333333,
          "wind_gust_mph": 20.714023656,
          "overnight_snowfall_in": 0.0,
          "overnight_low_f": 25.0,
          "humidity_pct": 55.86363636363637,
          "precipitation_in": 0.0,
          "visibility_mi": null,
          "precipitation_probability_pct": 3
        },
        "2026-04-25": {
          "temperature_f": 41.0,
          "cloud_cover_pct": 18.666666666666668,
          "wind_speed_mph": 9.781622281999999,
          "wind_gust_mph": 21.864802748000002,
          "overnight_snowfall_in": 0.0,
          "overnight_low_f": 27.0,
          "humidity_pct": 50.76190476190476,
          "precipitation_in": 0.0,
          "visibility_mi": null,
          "precipitation_probability_pct": 7
        },
        "2026-04-26": {
          "temperature_f": 42.0,
          "cloud_cover_pct": 30.0,
          "wind_speed_mph": 8.343148417,
          "wind_gust_mph": 17.26168638,
          "overnight_snowfall_in": 0.0,
          "overnight_low_f": 29.0,
          "humidity_pct": 55.7,
          "precipitation_in": 0.0,
          "visibility_mi": null,
          "precipitation_probability_pct": 17
        },
        "2026-04-27": {
          "temperature_f": 42.0,
          "cloud_cover_pct": 43.333333333333336,
          "wind_speed_mph": 8.7459210992,
          "wind_gust_mph": 17.26168638,
          "overnight_snowfall_in": 0.0,
          "overnight_low_f": 30.0,
          "humidity_pct": 67.2,
          "precipitation_in": 0.0,
          "visibility_mi": null,
          "precipitation_probability_pct": 27
        }
      },
      "forecastUrl": "https://api.weather.gov/gridpoints/SEW/173,101/forecast",
      "source": "NWS"
    },
    "47.515,-120.81": {
      "weatherByDay": {
        "2026-04-21": {
          "temperature_f": 44.0,
          "cloud_cover_pct": 65.92307692307692,
          "wind_speed_mph": 15.797058444727273,
          "wind_gust_mph": 25.317140024,
          "overnight_snowfall_in": 0.0,
          "overnight_low_f": 37.0,
          "humidity_pct": 66.375,
          "precipitation_in": 0.03999999910593,
          "visibility_mi": null,
          "precipitation_probability_pct": 43
        },
        "2026-04-22": {
          "temperature_f": 33.0,
          "cloud_cover_pct": 77.73333333333333,
          "wind_speed_mph": 34.941837884363636,
          "wind_gust_mph": 44.880384588,
          "overnight_snowfall_in": 1.7000000476837602,
          "overnight_low_f": 30.0,
          "humidity_pct": 84.38888888888889,
          "precipitation_in": 0.330000007525089,
          "visibility_mi": null,
          "precipitation_probability_pct": 66
        },
        "2026-04-23": {
          "temperature_f": 35.0,
          "cloud_cover_pct": 39.57142857142857,
          "wind_speed_mph": 30.3517985515,
          "wind_gust_mph": 46.03116368,
          "overnight_snowfall_in": 0.0,
          "overnight_low_f": 26.0,
          "humidity_pct": 69.47058823529412,
          "precipitation_in": 0.0,
          "visibility_mi": null,
          "precipitation_probability_pct": 23
        },
        "2026-04-24": {
          "temperature_f": 38.0,
          "cloud_cover_pct": 14.666666666666666,
          "wind_speed_mph": 19.563244564,
          "wind_gust_mph": 34.52337276,
          "overnight_snowfall_in": 0.0,
          "overnight_low_f": 25.0,
          "humidity_pct": 51.388888888888886,
          "precipitation_in": 0.0,
          "visibility_mi": null,
          "precipitation_probability_pct": 4
        },
        "2026-04-25": {
          "temperature_f": 41.0,
          "cloud_cover_pct": 20.25,
          "wind_speed_mph": 14.384738650000001,
          "wind_gust_mph": 20.714023656,
          "overnight_snowfall_in": 0.0,
          "overnight_low_f": 26.0,
          "humidity_pct": 53.1764705882353,
          "precipitation_in": 0.0,
          "visibility_mi": null,
          "precipitation_probability_pct": 8
        },
        "2026-04-26": {
          "temperature_f": 43.0,
          "cloud_cover_pct": 26.5,
          "wind_speed_mph": 12.850366527333334,
          "wind_gust_mph": 18.412465472,
          "overnight_snowfall_in": 0.0,
          "overnight_low_f": 28.0,
          "humidity_pct": 56.285714285714285,
          "precipitation_in": 0.0,
          "visibility_mi": null,
          "precipitation_probability_pct": 11
        },
        "2026-04-27": {
          "temperature_f": 42.0,
          "cloud_cover_pct": 29.5,
          "wind_speed_mph": 16.5712189248,
          "wind_gust_mph": 21.864802748000002,
          "overnight_snowfall_in": 0.0,
          "overnight_low_f": 30.0,
          "humidity_pct": 62.5,
          "precipitation_in": 0.0,
          "visibility_mi": null,
          "precipitation_probability_pct": 15
        }
      },
      "forecastUrl": "https://api.weather.gov/gridpoints/OTX/32,102/forecast",
      "source": "NWS"
    },
    "46.92,-121.805": {
      "weatherByDay": {
        "2026-04-21": {
          "temperature_f": 57.0,
          "cloud_cover_pct": 64.375,
          "wind_speed_mph": 8.1993010305,
          "wind_gust_mph": 19.563244564,
          "overnight_snowfall_in": 0.0,
          "overnight_low_f": 38.0,
          "humidity_pct": 72.0952380952381,
          "precipitation_in": 0.18999999575316762,
          "visibility_mi": null,
          "precipitation_probability_pct": 77
        },
        "2026-04-22": {
          "temperature_f": 35.0,
          "cloud_cover_pct": 87.61538461538461,
          "wind_speed_mph": 14.672433423,
          "wind_gust_mph": 25.317140024,
          "overnight_snowfall_in": 10.60000026226044,
          "overnight_low_f": 32.0,
          "humidity_pct": 85.6,
          "precipitation_in": 1.360000014305121,
          "visibility_mi": null,
          "precipitation_probability_pct": 94
        },
        "2026-04-23": {
          "temperature_f": 41.0,
          "cloud_cover_pct": 49.42857142857143,
          "wind_speed_mph": 10.932401374000001,
          "wind_gust_mph": 23.01558184,
          "overnight_snowfall_in": 0.20000000298024,
          "overnight_low_f": 29.0,
          "humidity_pct": 71.7,
          "precipitation_in": 0.0199999995529652,
          "visibility_mi": null,
          "precipitation_probability_pct": 46
        },
        "2026-04-24": {
          "temperature_f": 46.0,
          "cloud_cover_pct": 8.5,
          "wind_speed_mph": 8.4869958035,
          "wind_gust_mph": 23.01558184,
          "overnight_snowfall_in": 0.0,
          "overnight_low_f": 30.0,
          "humidity_pct": 50.68181818181818,
          "precipitation_in": 0.0,
          "visibility_mi": null,
          "precipitation_probability_pct": 6
        },
        "2026-04-25": {
          "temperature_f": 47.0,
          "cloud_cover_pct": 19.0,
          "wind_speed_mph": 11.672187933142858,
          "wind_gust_mph": 26.467919115999997,
          "overnight_snowfall_in": 0.0,
          "overnight_low_f": 32.0,
          "humidity_pct": 47.75,
          "precipitation_in": 0.0,
          "visibility_mi": null,
          "precipitation_probability_pct": 8
        },
        "2026-04-26": {
          "temperature_f": 48.0,
          "cloud_cover_pct": 24.25,
          "wind_speed_mph": 10.850202867428573,
          "wind_gust_mph": 21.864802748000002,
          "overnight_snowfall_in": 0.0,
          "overnight_low_f": 32.0,
          "humidity_pct": 46.17391304347826,
          "precipitation_in": 0.0,
          "visibility_mi": null,
          "precipitation_probability_pct": 21
        },
        "2026-04-27": {
          "temperature_f": 47.0,
          "cloud_cover_pct": 40.75,
          "wind_speed_mph": 10.8173234648,
          "wind_gust_mph": 23.01558184,
          "overnight_snowfall_in": 0.0,
          "overnight_low_f": 34.0,
          "humidity_pct": 55.19047619047619,
          "precipitation_in": 0.0099999997764826,
          "visibility_mi": null,
          "precipitation_probability_pct": 30
        }
      },
      "forecastUrl": "https://api.weather.gov/gridpoints/SEW/135,33/forecast",
      "source": "NWS"
    },
    "46.458,-121.442": {
      "weatherByDay": {
        "2026-04-21": {
          "temperature_f": 60.0,
          "cloud_cover_pct": 65.95652173913044,
          "wind_speed_mph": 5.2935838232,
          "wind_gust_mph": 16.110907288,
          "overnight_snowfall_in": 0.0,
          "overnight_low_f": 40.0,
          "humidity_pct": 76.25,
          "precipitation_in": 0.0899999979883436,
          "visibility_mi": null,
          "precipitation_probability_pct": 71
        },
        "2026-04-22": {
          "temperature_f": 36.0,
          "cloud_cover_pct": 85.61538461538461,
          "wind_speed_mph": 14.074913509846155,
          "wind_gust_mph": 24.166360932000003,
          "overnight_snowfall_in": 5.700000122189531,
          "overnight_low_f": 32.0,
          "humidity_pct": 94.38461538461539,
          "precipitation_in": 1.000000007450573,
          "visibility_mi": null,
          "precipitation_probability_pct": 86
        },
        "2026-04-23": {
          "temperature_f": 45.0,
          "cloud_cover_pct": 57.0,
          "wind_speed_mph": 10.644706601000001,
          "wind_gust_mph": 21.864802748000002,
          "overnight_snowfall_in": 0.20000000298023002,
          "overnight_low_f": 30.0,
          "humidity_pct": 82.43478260869566,
          "precipitation_in": 0.050000000745058,
          "visibility_mi": null,
          "precipitation_probability_pct": 35
        },
        "2026-04-24": {
          "temperature_f": 48.0,
          "cloud_cover_pct": 14.714285714285714,
          "wind_speed_mph": 7.3649861888000006,
          "wind_gust_mph": 16.110907288,
          "overnight_snowfall_in": 0.0,
          "overnight_low_f": 28.0,
          "humidity_pct": 60.35,
          "precipitation_in": 0.0,
          "visibility_mi": null,
          "precipitation_probability_pct": 6
        },
        "2026-04-25": {
          "temperature_f": 47.0,
          "cloud_cover_pct": 30.5,
          "wind_speed_mph": 7.3649861888000006,
          "wind_gust_mph": 18.412465472,
          "overnight_snowfall_in": 0.0,
          "overnight_low_f": 30.0,
          "humidity_pct": 55.21739130434783,
          "precipitation_in": 0.0,
          "visibility_mi": null,
          "precipitation_probability_pct": 10
        },
        "2026-04-26": {
          "temperature_f": 48.0,
          "cloud_cover_pct": 27.75,
          "wind_speed_mph": 5.75389546,
          "wind_gust_mph": 17.26168638,
          "overnight_snowfall_in": 0.0,
          "overnight_low_f": 30.0,
          "humidity_pct": 52.8,
          "precipitation_in": 0.0099999997764826,
          "visibility_mi": null,
          "precipitation_probability_pct": 17
        },
        "2026-04-27": {
          "temperature_f": 49.0,
          "cloud_cover_pct": 44.75,
          "wind_speed_mph": 7.192369325,
          "wind_gust_mph": 17.26168638,
          "overnight_snowfall_in": 0.0,
          "overnight_low_f": 33.0,
          "humidity_pct": 65.8125,
          "precipitation_in": 0.0,
          "visibility_mi": null,
          "precipitation_probability_pct": 25
        }
      },
      "forecastUrl": "https://api.weather.gov/gridpoints/SEW/142,9/forecast",
      "source": "NWS"
    },
    "48.8566,-121.6644": {
      "weatherByDay": {
        "2026-04-21": {
          "temperature_f": 62.0,
          "cloud_cover_pct": 57.833333333333336,
          "wind_speed_mph": 5.014108900857144,
          "wind_gust_mph": 10.357011828,
          "overnight_snowfall_in": 0.0,
          "overnight_low_f": 43.0,
          "humidity_pct": 63.72727272727273,
          "precipitation_in": 0.070000000298023,
          "visibility_mi": null,
          "precipitation_probability_pct": 49
        },
        "2026-04-22": {
          "temperature_f": 44.0,
          "cloud_cover_pct": 88.16666666666667,
          "wind_speed_mph": 5.021581492363637,
          "wind_gust_mph": 12.658570012,
          "overnight_snowfall_in": 0.0,
          "overnight_low_f": 39.0,
          "humidity_pct": 82.63157894736842,
          "precipitation_in": 0.240000002086166,
          "visibility_mi": null,
          "precipitation_probability_pct": 80
        },
        "2026-04-23": {
          "temperature_f": 47.0,
          "cloud_cover_pct": 45.25,
          "wind_speed_mph": 6.575880525714285,
          "wind_gust_mph": 17.26168638,
          "overnight_snowfall_in": 0.0,
          "overnight_low_f": 34.0,
          "humidity_pct": 67.55,
          "precipitation_in": 0.069999998435378,
          "visibility_mi": null,
          "precipitation_probability_pct": 44
        },
        "2026-04-24": {
          "temperature_f": 52.0,
          "cloud_cover_pct": 9.571428571428571,
          "wind_speed_mph": 8.055453644,
          "wind_gust_mph": 25.317140024,
          "overnight_snowfall_in": 0.0,
          "overnight_low_f": 34.0,
          "humidity_pct": 48.8,
          "precipitation_in": 0.0,
          "visibility_mi": null,
          "precipitation_probability_pct": 2
        },
        "2026-04-25": {
          "temperature_f": 54.0,
          "cloud_cover_pct": 12.75,
          "wind_speed_mph": 8.199301030500001,
          "wind_gust_mph": 26.467919115999997,
          "overnight_snowfall_in": 0.0,
          "overnight_low_f": 35.0,
          "humidity_pct": 41.94736842105263,
          "precipitation_in": 0.0,
          "visibility_mi": null,
          "precipitation_probability_pct": 5
        },
        "2026-04-26": {
          "temperature_f": 54.0,
          "cloud_cover_pct": 26.25,
          "wind_speed_mph": 6.6745187336,
          "wind_gust_mph": 19.563244564,
          "overnight_snowfall_in": 0.0,
          "overnight_low_f": 37.0,
          "humidity_pct": 48.0,
          "precipitation_in": 0.0,
          "visibility_mi": null,
          "precipitation_probability_pct": 16
        },
        "2026-04-27": {
          "temperature_f": 52.0,
          "cloud_cover_pct": 41.5,
          "wind_speed_mph": 6.740277538857143,
          "wind_gust_mph": 19.563244564,
          "overnight_snowfall_in": 0.0,
          "overnight_low_f": 37.0,
          "humidity_pct": 59.44444444444444,
          "precipitation_in": 0.0099999997764826,
          "visibility_mi": null,
          "precipitation_probability_pct": 30
        }
      },
      "forecastUrl": "https://api.weather.gov/gridpoints/SEW/157,123/forecast",
      "source": "NWS"
    },
    "47.7448,-121.089": {
      "weatherByDay": {
        "2026-04-21": {
          "temperature_f": 63.0,
          "cloud_cover_pct": 57.333333333333336,
          "wind_speed_mph": 3.5674151852000002,
          "wind_gust_mph": 10.357011828,
          "overnight_snowfall_in": 0.0,
          "overnight_low_f": 42.0,
          "humidity_pct": 72.4,
          "precipitation_in": 0.03999999910593,
          "visibility_mi": null,
          "precipitation_probability_pct": 54
        },
        "2026-04-22": {
          "temperature_f": 42.0,
          "cloud_cover_pct": 85.3125,
          "wind_speed_mph": 8.4006873716,
          "wind_gust_mph": 17.26168638,
          "overnight_snowfall_in": 0.0,
          "overnight_low_f": 38.0,
          "humidity_pct": 89.33333333333333,
          "precipitation_in": 0.490000002086169,
          "visibility_mi": null,
          "precipitation_probability_pct": 80
        },
        "2026-04-23": {
          "temperature_f": 46.0,
          "cloud_cover_pct": 61.0,
          "wind_speed_mph": 8.63084319,
          "wind_gust_mph": 19.563244564,
          "overnight_snowfall_in": 0.0,
          "overnight_low_f": 35.0,
          "humidity_pct": 76.3076923076923,
          "precipitation_in": 0.069999998435378,
          "visibility_mi": null,
          "precipitation_probability_pct": 44
        },
        "2026-04-24": {
          "temperature_f": 51.0,
          "cloud_cover_pct": 12.571428571428571,
          "wind_speed_mph": 3.452337276,
          "wind_gust_mph": 14.960128196000001,
          "overnight_snowfall_in": 0.0,
          "overnight_low_f": 31.0,
          "humidity_pct": 62.285714285714285,
          "precipitation_in": 0.0,
          "visibility_mi": null,
          "precipitation_probability_pct": 6
        },
        "2026-04-25": {
          "temperature_f": 52.0,
          "cloud_cover_pct": 19.25,
          "wind_speed_mph": 4.219523337333333,
          "wind_gust_mph": 16.110907288,
          "overnight_snowfall_in": 0.0,
          "overnight_low_f": 32.0,
          "humidity_pct": 55.095238095238095,
          "precipitation_in": 0.0,
          "visibility_mi": null,
          "precipitation_probability_pct": 11
        },
        "2026-04-26": {
          "temperature_f": 52.0,
          "cloud_cover_pct": 35.25,
          "wind_speed_mph": 4.027726822,
          "wind_gust_mph": 12.658570012,
          "overnight_snowfall_in": 0.0,
          "overnight_low_f": 33.0,
          "humidity_pct": 58.333333333333336,
          "precipitation_in": 0.0,
          "visibility_mi": null,
          "precipitation_probability_pct": 21
        },
        "2026-04-27": {
          "temperature_f": 51.0,
          "cloud_cover_pct": 44.0,
          "wind_speed_mph": 4.603116368,
          "wind_gust_mph": 14.960128196000001,
          "overnight_snowfall_in": 0.0,
          "overnight_low_f": 35.0,
          "humidity_pct": 68.3157894736842,
          "precipitation_in": 0.0,
          "visibility_mi": null,
          "precipitation_probability_pct": 30
        }
      },
      "forecastUrl": "https://api.weather.gov/gridpoints/SEW/165,67/forecast",
      "source": "NWS"
    },
    "47.4281,-121.4138": {
      "weatherByDay": {
        "2026-04-21": {
          "temperature_f": 66.0,
          "cloud_cover_pct": 59.27272727272727,
          "wind_speed_mph": 3.356439018333334,
          "wind_gust_mph": 11.50779092,
          "overnight_snowfall_in": 0.0,
          "overnight_low_f": 42.0,
          "humidity_pct": 80.28571428571429,
          "precipitation_in": 0.10000000149012,
          "visibility_mi": null,
          "precipitation_probability_pct": 64
        },
        "2026-04-22": {
          "temperature_f": 43.0,
          "cloud_cover_pct": 84.86666666666666,
          "wind_speed_mph": 6.904674552,
          "wind_gust_mph": 16.110907288,
          "overnight_snowfall_in": 0.0,
          "overnight_low_f": 39.0,
          "humidity_pct": 95.92857142857143,
          "precipitation_in": 0.81000000983477,
          "visibility_mi": null,
          "precipitation_probability_pct": 90
        },
        "2026-04-23": {
          "temperature_f": 48.0,
          "cloud_cover_pct": 61.0,
          "wind_speed_mph": 7.671860613333333,
          "wind_gust_mph": 17.26168638,
          "overnight_snowfall_in": 0.0,
          "overnight_low_f": 35.0,
          "humidity_pct": 86.0,
          "precipitation_in": 0.099999999627471,
          "visibility_mi": null,
          "precipitation_probability_pct": 51
        },
        "2026-04-24": {
          "temperature_f": 55.0,
          "cloud_cover_pct": 9.125,
          "wind_speed_mph": 3.5961846625000002,
          "wind_gust_mph": 13.809349104,
          "overnight_snowfall_in": 0.0,
          "overnight_low_f": 31.0,
          "humidity_pct": 69.75,
          "precipitation_in": 0.0,
          "visibility_mi": null,
          "precipitation_probability_pct": 6
        },
        "2026-04-25": {
          "temperature_f": 55.0,
          "cloud_cover_pct": 16.5,
          "wind_speed_mph": 2.87694773,
          "wind_gust_mph": 16.110907288,
          "overnight_snowfall_in": 0.0,
          "overnight_low_f": 34.0,
          "humidity_pct": 59.857142857142854,
          "precipitation_in": 0.0,
          "visibility_mi": null,
          "precipitation_probability_pct": 11
        },
        "2026-04-26": {
          "temperature_f": 55.0,
          "cloud_cover_pct": 33.0,
          "wind_speed_mph": 3.452337276,
          "wind_gust_mph": 14.960128196000001,
          "overnight_snowfall_in": 0.0,
          "overnight_low_f": 35.0,
          "humidity_pct": 61.38095238095238,
          "precipitation_in": 0.0,
          "visibility_mi": null,
          "precipitation_probability_pct": 23
        },
        "2026-04-27": {
          "temperature_f": 54.0,
          "cloud_cover_pct": 45.75,
          "wind_speed_mph": 3.8359303066666666,
          "wind_gust_mph": 14.960128196000001,
          "overnight_snowfall_in": 0.0,
          "overnight_low_f": 37.0,
          "humidity_pct": 69.36363636363636,
          "precipitation_in": 0.0,
          "visibility_mi": null,
          "precipitation_probability_pct": 33
        }
      },
      "forecastUrl": "https://api.weather.gov/gridpoints/SEW/152,54/forecast",
      "source": "NWS"
    },
    "46.9354,-121.5045": {
      "weatherByDay": {
        "2026-04-21": {
          "temperature_f": 61.0,
          "cloud_cover_pct": 64.31818181818181,
          "wind_speed_mph": 4.5072181103333335,
          "wind_gust_mph": 17.26168638,
          "overnight_snowfall_in": 0.0,
          "overnight_low_f": 40.0,
          "humidity_pct": 74.63636363636364,
          "precipitation_in": 0.1100000012666026,
          "visibility_mi": null,
          "precipitation_probability_pct": 73
        },
        "2026-04-22": {
          "temperature_f": 40.0,
          "cloud_cover_pct": 86.3125,
          "wind_speed_mph": 12.466773496666667,
          "wind_gust_mph": 24.166360932000003,
          "overnight_snowfall_in": 0.0,
          "overnight_low_f": 34.0,
          "humidity_pct": 90.57142857142857,
          "precipitation_in": 0.38000000081956803,
          "visibility_mi": null,
          "precipitation_probability_pct": 89
        },
        "2026-04-23": {
          "temperature_f": 44.0,
          "cloud_cover_pct": 45.285714285714285,
          "wind_speed_mph": 10.192614814857142,
          "wind_gust_mph": 21.864802748000002,
          "overnight_snowfall_in": 0.0,
          "overnight_low_f": 30.0,
          "humidity_pct": 77.8695652173913,
          "precipitation_in": 0.0099999997764826,
          "visibility_mi": null,
          "precipitation_probability_pct": 40
        },
        "2026-04-24": {
          "temperature_f": 49.0,
          "cloud_cover_pct": 10.166666666666666,
          "wind_speed_mph": 7.288267582666667,
          "wind_gust_mph": 21.864802748000002,
          "overnight_snowfall_in": 0.0,
          "overnight_low_f": 30.0,
          "humidity_pct": 56.0,
          "precipitation_in": 0.0,
          "visibility_mi": null,
          "precipitation_probability_pct": 6
        },
        "2026-04-25": {
          "temperature_f": 49.0,
          "cloud_cover_pct": 24.0,
          "wind_speed_mph": 8.63084319,
          "wind_gust_mph": 25.317140024,
          "overnight_snowfall_in": 0.0,
          "overnight_low_f": 31.0,
          "humidity_pct": 53.25,
          "precipitation_in": 0.0,
          "visibility_mi": null,
          "precipitation_probability_pct": 10
        },
        "2026-04-26": {
          "temperature_f": 50.0,
          "cloud_cover_pct": 27.25,
          "wind_speed_mph": 7.595142007200001,
          "wind_gust_mph": 21.864802748000002,
          "overnight_snowfall_in": 0.0,
          "overnight_low_f": 32.0,
          "humidity_pct": 53.55,
          "precipitation_in": 0.0,
          "visibility_mi": null,
          "precipitation_probability_pct": 19
        },
        "2026-04-27": {
          "temperature_f": 50.0,
          "cloud_cover_pct": 39.5,
          "wind_speed_mph": 8.247250159333333,
          "wind_gust_mph": 23.01558184,
          "overnight_snowfall_in": 0.0,
          "overnight_low_f": 33.0,
          "humidity_pct": 62.666666666666664,
          "precipitation_in": 0.0,
          "visibility_mi": null,
          "precipitation_probability_pct": 27
        }
      },
      "forecastUrl": "https://api.weather.gov/gridpoints/SEW/145,31/forecast",
      "source": "NWS"
    }
  }
}