{
  "lastUpdated": "2026-04-28T09:40:05.560293+00:00",
  "locationCount": 31,
  "errors": [],
  "weatherCache": {
    "48.9162,-121.608": {
      "weatherByDay": {
        "2026-04-28": {
          "temperature_f": 49.0,
          "cloud_cover_pct": 83.31818181818181,
          "wind_speed_mph": 6.0991291876,
          "wind_gust_mph": 17.26168638,
          "overnight_snowfall_in": 0.0,
          "overnight_low_f": 37.0,
          "humidity_pct": 88.5,
          "precipitation_in": 0.0499999988824132,
          "visibility_mi": null,
          "precipitation_probability_pct": 51
        },
        "2026-04-29": {
          "temperature_f": 58.0,
          "cloud_cover_pct": 52.86666666666667,
          "wind_speed_mph": 3.9455283154285716,
          "wind_gust_mph": 11.50779092,
          "overnight_snowfall_in": 0.0,
          "overnight_low_f": 34.0,
          "humidity_pct": 75.61111111111111,
          "precipitation_in": 0.0,
          "visibility_mi": null,
          "precipitation_probability_pct": 13
        },
        "2026-04-30": {
          "temperature_f": 59.0,
          "cloud_cover_pct": 30.75,
          "wind_speed_mph": 5.75389546,
          "wind_gust_mph": 13.809349104,
          "overnight_snowfall_in": 0.0,
          "overnight_low_f": 41.0,
          "humidity_pct": 64.29411764705883,
          "precipitation_in": 0.0,
          "visibility_mi": null,
          "precipitation_probability_pct": 3
        },
        "2026-05-01": {
          "temperature_f": 57.0,
          "cloud_cover_pct": 50.75,
          "wind_speed_mph": 4.603116367999999,
          "wind_gust_mph": 12.658570012,
          "overnight_snowfall_in": 0.0,
          "overnight_low_f": 39.0,
          "humidity_pct": 64.95,
          "precipitation_in": 0.0,
          "visibility_mi": null,
          "precipitation_probability_pct": 6
        },
        "2026-05-02": {
          "temperature_f": 62.0,
          "cloud_cover_pct": 57.5,
          "wind_speed_mph": 7.288267582666667,
          "wind_gust_mph": 13.809349104,
          "overnight_snowfall_in": 0.0,
          "overnight_low_f": 40.0,
          "humidity_pct": 60.5,
          "precipitation_in": 0.0,
          "visibility_mi": null,
          "precipitation_probability_pct": 10
        },
        "2026-05-03": {
          "temperature_f": 69.0,
          "cloud_cover_pct": 22.75,
          "wind_speed_mph": 9.206232736,
          "wind_gust_mph": 16.110907288,
          "overnight_snowfall_in": 0.0,
          "overnight_low_f": 43.0,
          "humidity_pct": 51.55,
          "precipitation_in": 0.0,
          "visibility_mi": null,
          "precipitation_probability_pct": 8
        },
        "2026-05-04": {
          "temperature_f": 71.0,
          "cloud_cover_pct": 19.75,
          "wind_speed_mph": 8.63084319,
          "wind_gust_mph": 13.809349104,
          "overnight_snowfall_in": 0.0,
          "overnight_low_f": 47.0,
          "humidity_pct": 44.2,
          "precipitation_in": 0.0,
          "visibility_mi": null,
          "precipitation_probability_pct": 4
        }
      },
      "forecastUrl": "https://api.weather.gov/gridpoints/SEW/160,125/forecast",
      "source": "NWS"
    },
    "48.821,-121.601": {
      "weatherByDay": {
        "2026-04-28": {
          "temperature_f": 34.0,
          "cloud_cover_pct": 80.5,
          "wind_speed_mph": 10.252395546909092,
          "wind_gust_mph": 19.563244564,
          "overnight_snowfall_in": 0.80000000447035,
          "overnight_low_f": 27.0,
          "humidity_pct": 90.0,
          "precipitation_in": 0.0800000000745056,
          "visibility_mi": null,
          "precipitation_probability_pct": 46
        },
        "2026-04-29": {
          "temperature_f": 44.0,
          "cloud_cover_pct": 47.875,
          "wind_speed_mph": 7.927589300444445,
          "wind_gust_mph": 12.658570012,
          "overnight_snowfall_in": 0.0,
          "overnight_low_f": 25.0,
          "humidity_pct": 77.04545454545455,
          "precipitation_in": 0.0,
          "visibility_mi": null,
          "precipitation_probability_pct": 11
        },
        "2026-04-30": {
          "temperature_f": 46.0,
          "cloud_cover_pct": 26.714285714285715,
          "wind_speed_mph": 10.644706601000001,
          "wind_gust_mph": 16.110907288,
          "overnight_snowfall_in": 0.0,
          "overnight_low_f": 31.0,
          "humidity_pct": 62.94117647058823,
          "precipitation_in": 0.0,
          "visibility_mi": null,
          "precipitation_probability_pct": 2
        },
        "2026-05-01": {
          "temperature_f": 43.0,
          "cloud_cover_pct": 48.42857142857143,
          "wind_speed_mph": 8.918537963,
          "wind_gust_mph": 17.26168638,
          "overnight_snowfall_in": 0.0,
          "overnight_low_f": 31.0,
          "humidity_pct": 64.5909090909091,
          "precipitation_in": 0.0,
          "visibility_mi": null,
          "precipitation_probability_pct": 5
        },
        "2026-05-02": {
          "temperature_f": 49.0,
          "cloud_cover_pct": 51.0,
          "wind_speed_mph": 5.562098944666666,
          "wind_gust_mph": 14.960128196000001,
          "overnight_snowfall_in": 0.0,
          "overnight_low_f": 32.0,
          "humidity_pct": 62.23809523809524,
          "precipitation_in": 0.0,
          "visibility_mi": null,
          "precipitation_probability_pct": 10
        },
        "2026-05-03": {
          "temperature_f": 55.0,
          "cloud_cover_pct": 20.5,
          "wind_speed_mph": 7.562262604571429,
          "wind_gust_mph": 19.563244564,
          "overnight_snowfall_in": 0.0,
          "overnight_low_f": 35.0,
          "humidity_pct": 48.75,
          "precipitation_in": 0.0,
          "visibility_mi": null,
          "precipitation_probability_pct": 7
        },
        "2026-05-04": {
          "temperature_f": 58.0,
          "cloud_cover_pct": 18.25,
          "wind_speed_mph": 6.247086499428573,
          "wind_gust_mph": 18.412465472,
          "overnight_snowfall_in": 0.0,
          "overnight_low_f": 38.0,
          "humidity_pct": 43.7,
          "precipitation_in": 0.0,
          "visibility_mi": null,
          "precipitation_probability_pct": 3
        }
      },
      "forecastUrl": "https://api.weather.gov/gridpoints/SEW/159,121/forecast",
      "source": "NWS"
    },
    "48.72,-121.815": {
      "weatherByDay": {
        "2026-04-28": {
          "temperature_f": 46.0,
          "cloud_cover_pct": 77.1,
          "wind_speed_mph": 5.562098944666666,
          "wind_gust_mph": 14.960128196000001,
          "overnight_snowfall_in": 0.0,
          "overnight_low_f": 36.0,
          "humidity_pct": 85.23529411764706,
          "precipitation_in": 0.0899999998509882,
          "visibility_mi": null,
          "precipitation_probability_pct": 46
        },
        "2026-04-29": {
          "temperature_f": 55.0,
          "cloud_cover_pct": 33.333333333333336,
          "wind_speed_mph": 4.027726822,
          "wind_gust_mph": 9.206232736,
          "overnight_snowfall_in": 0.0,
          "overnight_low_f": 34.0,
          "humidity_pct": 74.14285714285714,
          "precipitation_in": 0.0,
          "visibility_mi": null,
          "precipitation_probability_pct": 10
        },
        "2026-04-30": {
          "temperature_f": 57.0,
          "cloud_cover_pct": 36.2,
          "wind_speed_mph": 5.370302429333334,
          "wind_gust_mph": 10.357011828,
          "overnight_snowfall_in": 0.0,
          "overnight_low_f": 41.0,
          "humidity_pct": 61.5625,
          "precipitation_in": 0.0,
          "visibility_mi": null,
          "precipitation_probability_pct": 1
        },
        "2026-05-01": {
          "temperature_f": 54.0,
          "cloud_cover_pct": 47.166666666666664,
          "wind_speed_mph": 5.178505914,
          "wind_gust_mph": 12.658570012,
          "overnight_snowfall_in": 0.0,
          "overnight_low_f": 40.0,
          "humidity_pct": 60.35294117647059,
          "precipitation_in": 0.0,
          "visibility_mi": null,
          "precipitation_probability_pct": 3
        },
        "2026-05-02": {
          "temperature_f": 60.0,
          "cloud_cover_pct": 47.333333333333336,
          "wind_speed_mph": 5.0346585275,
          "wind_gust_mph": 11.50779092,
          "overnight_snowfall_in": 0.0,
          "overnight_low_f": 40.0,
          "humidity_pct": 58.26315789473684,
          "precipitation_in": 0.0,
          "visibility_mi": null,
          "precipitation_probability_pct": 7
        },
        "2026-05-03": {
          "temperature_f": 67.0,
          "cloud_cover_pct": 16.333333333333332,
          "wind_speed_mph": 6.575880525714285,
          "wind_gust_mph": 13.809349104,
          "overnight_snowfall_in": 0.0,
          "overnight_low_f": 44.0,
          "humidity_pct": 47.1578947368421,
          "precipitation_in": 0.0,
          "visibility_mi": null,
          "precipitation_probability_pct": 5
        },
        "2026-05-04": {
          "temperature_f": 69.0,
          "cloud_cover_pct": 15.75,
          "wind_speed_mph": 6.712878036666668,
          "wind_gust_mph": 12.658570012,
          "overnight_snowfall_in": 0.0,
          "overnight_low_f": 48.0,
          "humidity_pct": 40.2,
          "precipitation_in": 0.0,
          "visibility_mi": null,
          "precipitation_probability_pct": 3
        }
      },
      "forecastUrl": "https://api.weather.gov/gridpoints/SEW/151,117/forecast",
      "source": "NWS"
    },
    "48.689,-121.139": {
      "weatherByDay": {
        "2026-04-28": {
          "temperature_f": 45.0,
          "cloud_cover_pct": 68.79166666666667,
          "wind_speed_mph": 8.439046674666667,
          "wind_gust_mph": 21.864802748000002,
          "overnight_snowfall_in": 0.0,
          "overnight_low_f": 35.0,
          "humidity_pct": 83.5,
          "precipitation_in": 0.0,
          "visibility_mi": null,
          "precipitation_probability_pct": 27
        },
        "2026-04-29": {
          "temperature_f": 55.0,
          "cloud_cover_pct": 45.8,
          "wind_speed_mph": 5.75389546,
          "wind_gust_mph": 14.960128196000001,
          "overnight_snowfall_in": 0.0,
          "overnight_low_f": 35.0,
          "humidity_pct": 71.79166666666667,
          "precipitation_in": 0.0,
          "visibility_mi": null,
          "precipitation_probability_pct": 8
        },
        "2026-04-30": {
          "temperature_f": 57.0,
          "cloud_cover_pct": 22.625,
          "wind_speed_mph": 6.6745187336,
          "wind_gust_mph": 13.809349104,
          "overnight_snowfall_in": 0.0,
          "overnight_low_f": 40.0,
          "humidity_pct": 55.833333333333336,
          "precipitation_in": 0.0,
          "visibility_mi": null,
          "precipitation_probability_pct": 4
        },
        "2026-05-01": {
          "temperature_f": 55.0,
          "cloud_cover_pct": 39.0,
          "wind_speed_mph": 5.9182924731428574,
          "wind_gust_mph": 16.110907288,
          "overnight_snowfall_in": 0.0,
          "overnight_low_f": 39.0,
          "humidity_pct": 61.333333333333336,
          "precipitation_in": 0.0,
          "visibility_mi": null,
          "precipitation_probability_pct": 8
        },
        "2026-05-02": {
          "temperature_f": 57.0,
          "cloud_cover_pct": 51.0,
          "wind_speed_mph": 5.75389546,
          "wind_gust_mph": 12.658570012,
          "overnight_snowfall_in": 0.0,
          "overnight_low_f": 40.0,
          "humidity_pct": 59.5,
          "precipitation_in": 0.0,
          "visibility_mi": null,
          "precipitation_probability_pct": 14
        },
        "2026-05-03": {
          "temperature_f": 65.0,
          "cloud_cover_pct": 16.0,
          "wind_speed_mph": 6.712878036666668,
          "wind_gust_mph": 13.809349104,
          "overnight_snowfall_in": 0.0,
          "overnight_low_f": 41.0,
          "humidity_pct": 48.95,
          "precipitation_in": 0.0,
          "visibility_mi": null,
          "precipitation_probability_pct": 10
        },
        "2026-05-04": {
          "temperature_f": 67.0,
          "cloud_cover_pct": 13.0,
          "wind_speed_mph": 5.75389546,
          "wind_gust_mph": 12.658570012,
          "overnight_snowfall_in": 0.0,
          "overnight_low_f": 45.0,
          "humidity_pct": 44.10526315789474,
          "precipitation_in": 0.0,
          "visibility_mi": null,
          "precipitation_probability_pct": 4
        }
      },
      "forecastUrl": "https://api.weather.gov/gridpoints/SEW/172,111/forecast",
      "source": "NWS"
    },
    "48.5175,-120.679": {
      "weatherByDay": {
        "2026-04-28": {
          "temperature_f": 43.0,
          "cloud_cover_pct": 59.388888888888886,
          "wind_speed_mph": 9.863820788571429,
          "wind_gust_mph": 17.26168638,
          "overnight_snowfall_in": 0.0,
          "overnight_low_f": 31.0,
          "humidity_pct": 80.625,
          "precipitation_in": 0.0,
          "visibility_mi": null,
          "precipitation_probability_pct": 15
        },
        "2026-04-29": {
          "temperature_f": 51.0,
          "cloud_cover_pct": 35.733333333333334,
          "wind_speed_mph": 6.712878036666668,
          "wind_gust_mph": 16.110907288,
          "overnight_snowfall_in": 0.0,
          "overnight_low_f": 29.0,
          "humidity_pct": 72.63636363636364,
          "precipitation_in": 0.0,
          "visibility_mi": null,
          "precipitation_probability_pct": 11
        },
        "2026-04-30": {
          "temperature_f": 53.0,
          "cloud_cover_pct": 24.375,
          "wind_speed_mph": 6.137488490666668,
          "wind_gust_mph": 12.658570012,
          "overnight_snowfall_in": 0.0,
          "overnight_low_f": 34.0,
          "humidity_pct": 61.31578947368421,
          "precipitation_in": 0.0,
          "visibility_mi": null,
          "precipitation_probability_pct": 3
        },
        "2026-05-01": {
          "temperature_f": 53.0,
          "cloud_cover_pct": 39.285714285714285,
          "wind_speed_mph": 6.904674552,
          "wind_gust_mph": 13.809349104,
          "overnight_snowfall_in": 0.0,
          "overnight_low_f": 34.0,
          "humidity_pct": 63.72222222222222,
          "precipitation_in": 0.0,
          "visibility_mi": null,
          "precipitation_probability_pct": 5
        },
        "2026-05-02": {
          "temperature_f": 54.0,
          "cloud_cover_pct": 51.0,
          "wind_speed_mph": 7.192369325,
          "wind_gust_mph": 14.960128196000001,
          "overnight_snowfall_in": 0.0,
          "overnight_low_f": 36.0,
          "humidity_pct": 61.94117647058823,
          "precipitation_in": 0.0,
          "visibility_mi": null,
          "precipitation_probability_pct": 13
        },
        "2026-05-03": {
          "temperature_f": 60.0,
          "cloud_cover_pct": 18.75,
          "wind_speed_mph": 6.6745187336,
          "wind_gust_mph": 13.809349104,
          "overnight_snowfall_in": 0.0,
          "overnight_low_f": 37.0,
          "humidity_pct": 53.0,
          "precipitation_in": 0.0,
          "visibility_mi": null,
          "precipitation_probability_pct": 8
        },
        "2026-05-04": {
          "temperature_f": 63.0,
          "cloud_cover_pct": 13.0,
          "wind_speed_mph": 6.5210815213333335,
          "wind_gust_mph": 13.809349104,
          "overnight_snowfall_in": 0.0,
          "overnight_low_f": 40.0,
          "humidity_pct": 45.421052631578945,
          "precipitation_in": 0.0,
          "visibility_mi": null,
          "precipitation_probability_pct": 4
        }
      },
      "forecastUrl": "https://api.weather.gov/gridpoints/OTX/45,149/forecast",
      "source": "NWS"
    },
    "48.498,-121.064": {
      "weatherByDay": {
        "2026-04-28": {
          "temperature_f": 34.0,
          "cloud_cover_pct": 80.0952380952381,
          "wind_speed_mph": 10.548808343333333,
          "wind_gust_mph": 21.864802748000002,
          "overnight_snowfall_in": 0.0,
          "overnight_low_f": 29.0,
          "humidity_pct": 92.6470588235294,
          "precipitation_in": 0.0,
          "visibility_mi": null,
          "precipitation_probability_pct": 19
        },
        "2026-04-29": {
          "temperature_f": 44.0,
          "cloud_cover_pct": 50.6,
          "wind_speed_mph": 6.904674552,
          "wind_gust_mph": 14.960128196000001,
          "overnight_snowfall_in": 0.0,
          "overnight_low_f": 28.0,
          "humidity_pct": 78.54545454545455,
          "precipitation_in": 0.0,
          "visibility_mi": null,
          "precipitation_probability_pct": 7
        },
        "2026-04-30": {
          "temperature_f": 47.0,
          "cloud_cover_pct": 26.5,
          "wind_speed_mph": 8.2856094624,
          "wind_gust_mph": 13.809349104,
          "overnight_snowfall_in": 0.0,
          "overnight_low_f": 32.0,
          "humidity_pct": 63.94444444444444,
          "precipitation_in": 0.0,
          "visibility_mi": null,
          "precipitation_probability_pct": 3
        },
        "2026-05-01": {
          "temperature_f": 45.0,
          "cloud_cover_pct": 44.5,
          "wind_speed_mph": 8.63084319,
          "wind_gust_mph": 14.960128196000001,
          "overnight_snowfall_in": 0.0,
          "overnight_low_f": 32.0,
          "humidity_pct": 66.73333333333333,
          "precipitation_in": 0.0,
          "visibility_mi": null,
          "precipitation_probability_pct": 6
        },
        "2026-05-02": {
          "temperature_f": 47.0,
          "cloud_cover_pct": 55.25,
          "wind_speed_mph": 6.329285006,
          "wind_gust_mph": 14.960128196000001,
          "overnight_snowfall_in": 0.0,
          "overnight_low_f": 33.0,
          "humidity_pct": 64.57894736842105,
          "precipitation_in": 0.0,
          "visibility_mi": null,
          "precipitation_probability_pct": 14
        },
        "2026-05-03": {
          "temperature_f": 54.0,
          "cloud_cover_pct": 20.5,
          "wind_speed_mph": 7.288267582666667,
          "wind_gust_mph": 14.960128196000001,
          "overnight_snowfall_in": 0.0,
          "overnight_low_f": 33.0,
          "humidity_pct": 54.63157894736842,
          "precipitation_in": 0.0,
          "visibility_mi": null,
          "precipitation_probability_pct": 11
        },
        "2026-05-04": {
          "temperature_f": 56.0,
          "cloud_cover_pct": 16.5,
          "wind_speed_mph": 6.329285006,
          "wind_gust_mph": 13.809349104,
          "overnight_snowfall_in": 0.0,
          "overnight_low_f": 38.0,
          "humidity_pct": 46.9,
          "precipitation_in": 0.0,
          "visibility_mi": null,
          "precipitation_probability_pct": 3
        }
      },
      "forecastUrl": "https://api.weather.gov/gridpoints/SEW/173,102/forecast",
      "source": "NWS"
    },
    "48.157,-120.907": {
      "weatherByDay": {
        "2026-04-28": {
          "temperature_f": 43.0,
          "cloud_cover_pct": 64.89473684210526,
          "wind_speed_mph": 11.178996893714285,
          "wind_gust_mph": 20.714023656,
          "overnight_snowfall_in": 0.0,
          "overnight_low_f": 32.0,
          "humidity_pct": 78.84210526315789,
          "precipitation_in": 0.0,
          "visibility_mi": null,
          "precipitation_probability_pct": 10
        },
        "2026-04-29": {
          "temperature_f": 52.0,
          "cloud_cover_pct": 43.0,
          "wind_speed_mph": 8.055453644,
          "wind_gust_mph": 20.714023656,
          "overnight_snowfall_in": 0.0,
          "overnight_low_f": 30.0,
          "humidity_pct": 69.91304347826087,
          "precipitation_in": 0.0,
          "visibility_mi": null,
          "precipitation_probability_pct": 6
        },
        "2026-04-30": {
          "temperature_f": 54.0,
          "cloud_cover_pct": 26.0,
          "wind_speed_mph": 6.329285006,
          "wind_gust_mph": 12.658570012,
          "overnight_snowfall_in": 0.0,
          "overnight_low_f": 35.0,
          "humidity_pct": 57.857142857142854,
          "precipitation_in": 0.0,
          "visibility_mi": null,
          "precipitation_probability_pct": 3
        },
        "2026-05-01": {
          "temperature_f": 54.0,
          "cloud_cover_pct": 42.0,
          "wind_speed_mph": 8.055453644,
          "wind_gust_mph": 13.809349104,
          "overnight_snowfall_in": 0.0,
          "overnight_low_f": 34.0,
          "humidity_pct": 60.285714285714285,
          "precipitation_in": 0.0,
          "visibility_mi": null,
          "precipitation_probability_pct": 6
        },
        "2026-05-02": {
          "temperature_f": 56.0,
          "cloud_cover_pct": 55.5,
          "wind_speed_mph": 6.4443629152,
          "wind_gust_mph": 14.960128196000001,
          "overnight_snowfall_in": 0.0,
          "overnight_low_f": 36.0,
          "humidity_pct": 58.73913043478261,
          "precipitation_in": 0.0,
          "visibility_mi": null,
          "precipitation_probability_pct": 17
        },
        "2026-05-03": {
          "temperature_f": 62.0,
          "cloud_cover_pct": 16.333333333333332,
          "wind_speed_mph": 5.9840512784,
          "wind_gust_mph": 11.50779092,
          "overnight_snowfall_in": 0.0,
          "overnight_low_f": 38.0,
          "humidity_pct": 53.8421052631579,
          "precipitation_in": 0.0,
          "visibility_mi": null,
          "precipitation_probability_pct": 10
        },
        "2026-05-04": {
          "temperature_f": 64.0,
          "cloud_cover_pct": 15.0,
          "wind_speed_mph": 5.370302429333334,
          "wind_gust_mph": 12.658570012,
          "overnight_snowfall_in": 0.0,
          "overnight_low_f": 41.0,
          "humidity_pct": 43.8,
          "precipitation_in": 0.0,
          "visibility_mi": null,
          "precipitation_probability_pct": 3
        }
      },
      "forecastUrl": "https://api.weather.gov/gridpoints/OTX/35,133/forecast",
      "source": "NWS"
    },
    "48.127,-121.179": {
      "weatherByDay": {
        "2026-04-28": {
          "temperature_f": 45.0,
          "cloud_cover_pct": 81.17391304347827,
          "wind_speed_mph": 6.137488490666667,
          "wind_gust_mph": 18.412465472,
          "overnight_snowfall_in": 0.0,
          "overnight_low_f": 35.0,
          "humidity_pct": 86.3529411764706,
          "precipitation_in": 0.029999999329447604,
          "visibility_mi": null,
          "precipitation_probability_pct": 16
        },
        "2026-04-29": {
          "temperature_f": 55.0,
          "cloud_cover_pct": 50.0,
          "wind_speed_mph": 3.6441337913333336,
          "wind_gust_mph": 11.50779092,
          "overnight_snowfall_in": 0.0,
          "overnight_low_f": 34.0,
          "humidity_pct": 75.8,
          "precipitation_in": 0.0,
          "visibility_mi": null,
          "precipitation_probability_pct": 9
        },
        "2026-04-30": {
          "temperature_f": 58.0,
          "cloud_cover_pct": 25.75,
          "wind_speed_mph": 3.6824930944000003,
          "wind_gust_mph": 9.206232736,
          "overnight_snowfall_in": 0.0,
          "overnight_low_f": 41.0,
          "humidity_pct": 57.111111111111114,
          "precipitation_in": 0.0,
          "visibility_mi": null,
          "precipitation_probability_pct": 3
        },
        "2026-05-01": {
          "temperature_f": 55.0,
          "cloud_cover_pct": 42.875,
          "wind_speed_mph": 4.986709398666667,
          "wind_gust_mph": 10.357011828,
          "overnight_snowfall_in": 0.0,
          "overnight_low_f": 39.0,
          "humidity_pct": 61.266666666666666,
          "precipitation_in": 0.0,
          "visibility_mi": null,
          "precipitation_probability_pct": 7
        },
        "2026-05-02": {
          "temperature_f": 58.0,
          "cloud_cover_pct": 58.666666666666664,
          "wind_speed_mph": 3.6824930944000003,
          "wind_gust_mph": 11.50779092,
          "overnight_snowfall_in": 0.0,
          "overnight_low_f": 40.0,
          "humidity_pct": 61.26315789473684,
          "precipitation_in": 0.0,
          "visibility_mi": null,
          "precipitation_probability_pct": 17
        },
        "2026-05-03": {
          "temperature_f": 65.0,
          "cloud_cover_pct": 17.0,
          "wind_speed_mph": 3.8359303066666666,
          "wind_gust_mph": 10.357011828,
          "overnight_snowfall_in": 0.0,
          "overnight_low_f": 42.0,
          "humidity_pct": 52.0,
          "precipitation_in": 0.0,
          "visibility_mi": null,
          "precipitation_probability_pct": 10
        },
        "2026-05-04": {
          "temperature_f": 67.0,
          "cloud_cover_pct": 17.0,
          "wind_speed_mph": 4.109925328571429,
          "wind_gust_mph": 10.357011828,
          "overnight_snowfall_in": 0.0,
          "overnight_low_f": 46.0,
          "humidity_pct": 45.21739130434783,
          "precipitation_in": 0.0,
          "visibility_mi": null,
          "precipitation_probability_pct": 4
        }
      },
      "forecastUrl": "https://api.weather.gov/gridpoints/SEW/166,85/forecast",
      "source": "NWS"
    },
    "48.125,-120.876": {
      "weatherByDay": {
        "2026-04-28": {
          "temperature_f": 53.0,
          "cloud_cover_pct": 47.2,
          "wind_speed_mph": 6.5210815213333335,
          "wind_gust_mph": 16.110907288,
          "overnight_snowfall_in": 0.0,
          "overnight_low_f": 36.0,
          "humidity_pct": 78.25,
          "precipitation_in": 0.0,
          "visibility_mi": null,
          "precipitation_probability_pct": 9
        },
        "2026-04-29": {
          "temperature_f": 61.0,
          "cloud_cover_pct": 29.3125,
          "wind_speed_mph": 4.027726822,
          "wind_gust_mph": 14.960128196000001,
          "overnight_snowfall_in": 0.0,
          "overnight_low_f": 33.0,
          "humidity_pct": 71.19047619047619,
          "precipitation_in": 0.0,
          "visibility_mi": null,
          "precipitation_probability_pct": 5
        },
        "2026-04-30": {
          "temperature_f": 64.0,
          "cloud_cover_pct": 18.625,
          "wind_speed_mph": 2.87694773,
          "wind_gust_mph": 6.904674552,
          "overnight_snowfall_in": 0.0,
          "overnight_low_f": 38.0,
          "humidity_pct": 62.2,
          "precipitation_in": 0.0,
          "visibility_mi": null,
          "precipitation_probability_pct": 2
        },
        "2026-05-01": {
          "temperature_f": 63.0,
          "cloud_cover_pct": 31.0,
          "wind_speed_mph": 3.8359303066666666,
          "wind_gust_mph": 9.206232736,
          "overnight_snowfall_in": 0.0,
          "overnight_low_f": 38.0,
          "humidity_pct": 64.19047619047619,
          "precipitation_in": 0.0,
          "visibility_mi": null,
          "precipitation_probability_pct": 6
        },
        "2026-05-02": {
          "temperature_f": 64.0,
          "cloud_cover_pct": 52.25,
          "wind_speed_mph": 6.247086499428573,
          "wind_gust_mph": 9.206232736,
          "overnight_snowfall_in": 0.0,
          "overnight_low_f": 40.0,
          "humidity_pct": 62.9,
          "precipitation_in": 0.0,
          "visibility_mi": null,
          "precipitation_probability_pct": 15
        },
        "2026-05-03": {
          "temperature_f": 71.0,
          "cloud_cover_pct": 22.0,
          "wind_speed_mph": 5.178505914,
          "wind_gust_mph": 6.904674552,
          "overnight_snowfall_in": 0.0,
          "overnight_low_f": 41.0,
          "humidity_pct": 56.458333333333336,
          "precipitation_in": 0.0,
          "visibility_mi": null,
          "precipitation_probability_pct": 9
        },
        "2026-05-04": {
          "temperature_f": 73.0,
          "cloud_cover_pct": 12.5,
          "wind_speed_mph": 5.260704420571429,
          "wind_gust_mph": 8.055453644,
          "overnight_snowfall_in": 0.0,
          "overnight_low_f": 44.0,
          "humidity_pct": 47.523809523809526,
          "precipitation_in": 0.0,
          "visibility_mi": null,
          "precipitation_probability_pct": 4
        }
      },
      "forecastUrl": "https://api.weather.gov/gridpoints/OTX/35,131/forecast",
      "source": "NWS"
    },
    "48.053,-120.921": {
      "weatherByDay": {
        "2026-04-28": {
          "temperature_f": 42.0,
          "cloud_cover_pct": 54.27777777777778,
          "wind_speed_mph": 9.206232736,
          "wind_gust_mph": 19.563244564,
          "overnight_snowfall_in": 0.0,
          "overnight_low_f": 30.0,
          "humidity_pct": 82.3529411764706,
          "precipitation_in": 0.0,
          "visibility_mi": null,
          "precipitation_probability_pct": 8
        },
        "2026-04-29": {
          "temperature_f": 51.0,
          "cloud_cover_pct": 29.3125,
          "wind_speed_mph": 7.288267582666667,
          "wind_gust_mph": 19.563244564,
          "overnight_snowfall_in": 0.0,
          "overnight_low_f": 29.0,
          "humidity_pct": 72.65,
          "precipitation_in": 0.0,
          "visibility_mi": null,
          "precipitation_probability_pct": 5
        },
        "2026-04-30": {
          "temperature_f": 53.0,
          "cloud_cover_pct": 23.428571428571427,
          "wind_speed_mph": 5.178505914,
          "wind_gust_mph": 11.50779092,
          "overnight_snowfall_in": 0.0,
          "overnight_low_f": 35.0,
          "humidity_pct": 60.904761904761905,
          "precipitation_in": 0.0,
          "visibility_mi": null,
          "precipitation_probability_pct": 2
        },
        "2026-05-01": {
          "temperature_f": 53.0,
          "cloud_cover_pct": 37.285714285714285,
          "wind_speed_mph": 6.904674552,
          "wind_gust_mph": 12.658570012,
          "overnight_snowfall_in": 0.0,
          "overnight_low_f": 34.0,
          "humidity_pct": 62.07142857142857,
          "precipitation_in": 0.0,
          "visibility_mi": null,
          "precipitation_probability_pct": 5
        },
        "2026-05-02": {
          "temperature_f": 55.0,
          "cloud_cover_pct": 51.75,
          "wind_speed_mph": 7.397865591428571,
          "wind_gust_mph": 14.960128196000001,
          "overnight_snowfall_in": 0.0,
          "overnight_low_f": 36.0,
          "humidity_pct": 61.8,
          "precipitation_in": 0.0,
          "visibility_mi": null,
          "precipitation_probability_pct": 15
        },
        "2026-05-03": {
          "temperature_f": 61.0,
          "cloud_cover_pct": 21.75,
          "wind_speed_mph": 6.329285006,
          "wind_gust_mph": 12.658570012,
          "overnight_snowfall_in": 0.0,
          "overnight_low_f": 37.0,
          "humidity_pct": 53.90909090909091,
          "precipitation_in": 0.0,
          "visibility_mi": null,
          "precipitation_probability_pct": 9
        },
        "2026-05-04": {
          "temperature_f": 63.0,
          "cloud_cover_pct": 10.333333333333334,
          "wind_speed_mph": 6.137488490666668,
          "wind_gust_mph": 12.658570012,
          "overnight_snowfall_in": 0.0,
          "overnight_low_f": 41.0,
          "humidity_pct": 47.80952380952381,
          "precipitation_in": 0.0,
          "visibility_mi": null,
          "precipitation_probability_pct": 3
        }
      },
      "forecastUrl": "https://api.weather.gov/gridpoints/OTX/33,128/forecast",
      "source": "NWS"
    },
    "47.881,-123.127": {
      "weatherByDay": {
        "2026-04-28": {
          "temperature_f": 54.0,
          "cloud_cover_pct": 81.19047619047619,
          "wind_speed_mph": 3.452337276,
          "wind_gust_mph": 13.809349104,
          "overnight_snowfall_in": 0.0,
          "overnight_low_f": 39.0,
          "humidity_pct": 75.47368421052632,
          "precipitation_in": 0.0099999997764826,
          "visibility_mi": null,
          "precipitation_probability_pct": 30
        },
        "2026-04-29": {
          "temperature_f": 59.0,
          "cloud_cover_pct": 50.0,
          "wind_speed_mph": 4.274322341714286,
          "wind_gust_mph": 16.110907288,
          "overnight_snowfall_in": 0.0,
          "overnight_low_f": 36.0,
          "humidity_pct": 68.61111111111111,
          "precipitation_in": 0.0,
          "visibility_mi": null,
          "precipitation_probability_pct": 9
        },
        "2026-04-30": {
          "temperature_f": 62.0,
          "cloud_cover_pct": 36.857142857142854,
          "wind_speed_mph": 4.219523337333333,
          "wind_gust_mph": 14.960128196000001,
          "overnight_snowfall_in": 0.0,
          "overnight_low_f": 43.0,
          "humidity_pct": 56.05263157894737,
          "precipitation_in": 0.0,
          "visibility_mi": null,
          "precipitation_probability_pct": 1
        },
        "2026-05-01": {
          "temperature_f": 57.0,
          "cloud_cover_pct": 44.875,
          "wind_speed_mph": 4.3729605496,
          "wind_gust_mph": 12.658570012,
          "overnight_snowfall_in": 0.0,
          "overnight_low_f": 42.0,
          "humidity_pct": 60.09090909090909,
          "precipitation_in": 0.0,
          "visibility_mi": null,
          "precipitation_probability_pct": 2
        },
        "2026-05-02": {
          "temperature_f": 63.0,
          "cloud_cover_pct": 49.0,
          "wind_speed_mph": 5.1785059140000005,
          "wind_gust_mph": 18.412465472,
          "overnight_snowfall_in": 0.0,
          "overnight_low_f": 42.0,
          "humidity_pct": 55.2,
          "precipitation_in": 0.0,
          "visibility_mi": null,
          "precipitation_probability_pct": 1
        },
        "2026-05-03": {
          "temperature_f": 69.0,
          "cloud_cover_pct": 13.5,
          "wind_speed_mph": 5.562098944666666,
          "wind_gust_mph": 16.110907288,
          "overnight_snowfall_in": 0.0,
          "overnight_low_f": 48.0,
          "humidity_pct": 41.888888888888886,
          "precipitation_in": 0.0,
          "visibility_mi": null,
          "precipitation_probability_pct": 0
        },
        "2026-05-04": {
          "temperature_f": 72.0,
          "cloud_cover_pct": 16.5,
          "wind_speed_mph": 4.411319852666667,
          "wind_gust_mph": 10.357011828,
          "overnight_snowfall_in": 0.0,
          "overnight_low_f": 51.0,
          "humidity_pct": 37.69230769230769,
          "precipitation_in": 0.0,
          "visibility_mi": null,
          "precipitation_probability_pct": 2
        }
      },
      "forecastUrl": "https://api.weather.gov/gridpoints/SEW/102,86/forecast",
      "source": "NWS"
    },
    "47.46,-120.894": {
      "weatherByDay": {
        "2026-04-28": {
          "temperature_f": 47.0,
          "cloud_cover_pct": 48.25,
          "wind_speed_mph": 10.932401374,
          "wind_gust_mph": 25.317140024,
          "overnight_snowfall_in": 0.0,
          "overnight_low_f": 32.0,
          "humidity_pct": 79.58823529411765,
          "precipitation_in": 0.0,
          "visibility_mi": null,
          "precipitation_probability_pct": 5
        },
        "2026-04-29": {
          "temperature_f": 55.0,
          "cloud_cover_pct": 30.375,
          "wind_speed_mph": 7.8252978256,
          "wind_gust_mph": 20.714023656,
          "overnight_snowfall_in": 0.0,
          "overnight_low_f": 31.0,
          "humidity_pct": 70.86363636363636,
          "precipitation_in": 0.0,
          "visibility_mi": null,
          "precipitation_probability_pct": 4
        },
        "2026-04-30": {
          "temperature_f": 58.0,
          "cloud_cover_pct": 25.5,
          "wind_speed_mph": 5.75389546,
          "wind_gust_mph": 12.658570012,
          "overnight_snowfall_in": 0.0,
          "overnight_low_f": 37.0,
          "humidity_pct": 55.4375,
          "precipitation_in": 0.0,
          "visibility_mi": null,
          "precipitation_probability_pct": 3
        },
        "2026-05-01": {
          "temperature_f": 58.0,
          "cloud_cover_pct": 37.625,
          "wind_speed_mph": 7.671860613333333,
          "wind_gust_mph": 13.809349104,
          "overnight_snowfall_in": 0.0,
          "overnight_low_f": 37.0,
          "humidity_pct": 58.22727272727273,
          "precipitation_in": 0.0,
          "visibility_mi": null,
          "precipitation_probability_pct": 3
        },
        "2026-05-02": {
          "temperature_f": 58.0,
          "cloud_cover_pct": 60.75,
          "wind_speed_mph": 7.8252978256,
          "wind_gust_mph": 17.26168638,
          "overnight_snowfall_in": 0.0,
          "overnight_low_f": 39.0,
          "humidity_pct": 62.0,
          "precipitation_in": 0.0,
          "visibility_mi": null,
          "precipitation_probability_pct": 14
        },
        "2026-05-03": {
          "temperature_f": 64.0,
          "cloud_cover_pct": 24.75,
          "wind_speed_mph": 6.4443629152,
          "wind_gust_mph": 17.26168638,
          "overnight_snowfall_in": 0.0,
          "overnight_low_f": 40.0,
          "humidity_pct": 54.611111111111114,
          "precipitation_in": 0.0,
          "visibility_mi": null,
          "precipitation_probability_pct": 11
        },
        "2026-05-04": {
          "temperature_f": 67.0,
          "cloud_cover_pct": 19.666666666666668,
          "wind_speed_mph": 7.671860613333333,
          "wind_gust_mph": 17.26168638,
          "overnight_snowfall_in": 0.0,
          "overnight_low_f": 44.0,
          "humidity_pct": 46.95,
          "precipitation_in": 0.0,
          "visibility_mi": null,
          "precipitation_probability_pct": 3
        }
      },
      "forecastUrl": "https://api.weather.gov/gridpoints/OTX/29,100/forecast",
      "source": "NWS"
    },
    "47.4274,-121.0269": {
      "weatherByDay": {
        "2026-04-28": {
          "temperature_f": 54.0,
          "cloud_cover_pct": 62.5,
          "wind_speed_mph": 7.4800640980000015,
          "wind_gust_mph": 19.563244564,
          "overnight_snowfall_in": 0.0,
          "overnight_low_f": 35.0,
          "humidity_pct": 77.04761904761905,
          "precipitation_in": 0.0,
          "visibility_mi": null,
          "precipitation_probability_pct": 7
        },
        "2026-04-29": {
          "temperature_f": 62.0,
          "cloud_cover_pct": 30.375,
          "wind_speed_mph": 4.603116367999999,
          "wind_gust_mph": 16.110907288,
          "overnight_snowfall_in": 0.0,
          "overnight_low_f": 34.0,
          "humidity_pct": 68.72727272727273,
          "precipitation_in": 0.0,
          "visibility_mi": null,
          "precipitation_probability_pct": 4
        },
        "2026-04-30": {
          "temperature_f": 65.0,
          "cloud_cover_pct": 29.375,
          "wind_speed_mph": 3.6824930944000003,
          "wind_gust_mph": 10.357011828,
          "overnight_snowfall_in": 0.0,
          "overnight_low_f": 41.0,
          "humidity_pct": 55.76190476190476,
          "precipitation_in": 0.0,
          "visibility_mi": null,
          "precipitation_probability_pct": 3
        },
        "2026-05-01": {
          "temperature_f": 64.0,
          "cloud_cover_pct": 40.0,
          "wind_speed_mph": 4.890811141,
          "wind_gust_mph": 11.50779092,
          "overnight_snowfall_in": 0.0,
          "overnight_low_f": 41.0,
          "humidity_pct": 59.36363636363637,
          "precipitation_in": 0.0,
          "visibility_mi": null,
          "precipitation_probability_pct": 4
        },
        "2026-05-02": {
          "temperature_f": 65.0,
          "cloud_cover_pct": 63.75,
          "wind_speed_mph": 5.2935838232000005,
          "wind_gust_mph": 13.809349104,
          "overnight_snowfall_in": 0.0,
          "overnight_low_f": 42.0,
          "humidity_pct": 60.72222222222222,
          "precipitation_in": 0.0,
          "visibility_mi": null,
          "precipitation_probability_pct": 13
        },
        "2026-05-03": {
          "temperature_f": 72.0,
          "cloud_cover_pct": 24.75,
          "wind_speed_mph": 4.3729605496,
          "wind_gust_mph": 11.50779092,
          "overnight_snowfall_in": 0.0,
          "overnight_low_f": 44.0,
          "humidity_pct": 54.17391304347826,
          "precipitation_in": 0.0,
          "visibility_mi": null,
          "precipitation_probability_pct": 10
        },
        "2026-05-04": {
          "temperature_f": 74.0,
          "cloud_cover_pct": 18.5,
          "wind_speed_mph": 4.890811141,
          "wind_gust_mph": 13.809349104,
          "overnight_snowfall_in": 0.0,
          "overnight_low_f": 48.0,
          "humidity_pct": 43.75,
          "precipitation_in": 0.0,
          "visibility_mi": null,
          "precipitation_probability_pct": 5
        }
      },
      "forecastUrl": "https://api.weather.gov/gridpoints/PDT/75,195/forecast",
      "source": "NWS"
    },
    "46.93,-121.657": {
      "weatherByDay": {
        "2026-04-28": {
          "temperature_f": 41.0,
          "cloud_cover_pct": 52.130434782608695,
          "wind_speed_mph": 9.973418797333334,
          "wind_gust_mph": 28.7694773,
          "overnight_snowfall_in": 0.0,
          "overnight_low_f": 28.0,
          "humidity_pct": 74.61111111111111,
          "precipitation_in": 0.0,
          "visibility_mi": null,
          "precipitation_probability_pct": 18
        },
        "2026-04-29": {
          "temperature_f": 50.0,
          "cloud_cover_pct": 44.06666666666667,
          "wind_speed_mph": 5.75389546,
          "wind_gust_mph": 18.412465472,
          "overnight_snowfall_in": 0.0,
          "overnight_low_f": 28.0,
          "humidity_pct": 67.625,
          "precipitation_in": 0.0,
          "visibility_mi": null,
          "precipitation_probability_pct": 6
        },
        "2026-04-30": {
          "temperature_f": 54.0,
          "cloud_cover_pct": 28.625,
          "wind_speed_mph": 6.740277538857143,
          "wind_gust_mph": 12.658570012,
          "overnight_snowfall_in": 0.0,
          "overnight_low_f": 36.0,
          "humidity_pct": 52.714285714285715,
          "precipitation_in": 0.0,
          "visibility_mi": null,
          "precipitation_probability_pct": 3
        },
        "2026-05-01": {
          "temperature_f": 50.0,
          "cloud_cover_pct": 36.75,
          "wind_speed_mph": 6.5210815213333335,
          "wind_gust_mph": 16.110907288,
          "overnight_snowfall_in": 0.0,
          "overnight_low_f": 35.0,
          "humidity_pct": 58.36842105263158,
          "precipitation_in": 0.0,
          "visibility_mi": null,
          "precipitation_probability_pct": 6
        },
        "2026-05-02": {
          "temperature_f": 53.0,
          "cloud_cover_pct": 60.25,
          "wind_speed_mph": 6.137488490666667,
          "wind_gust_mph": 17.26168638,
          "overnight_snowfall_in": 0.0,
          "overnight_low_f": 35.0,
          "humidity_pct": 63.285714285714285,
          "precipitation_in": 0.0,
          "visibility_mi": null,
          "precipitation_probability_pct": 15
        },
        "2026-05-03": {
          "temperature_f": 60.0,
          "cloud_cover_pct": 23.5,
          "wind_speed_mph": 7.096471067333334,
          "wind_gust_mph": 14.960128196000001,
          "overnight_snowfall_in": 0.0,
          "overnight_low_f": 39.0,
          "humidity_pct": 54.1578947368421,
          "precipitation_in": 0.0,
          "visibility_mi": null,
          "precipitation_probability_pct": 10
        },
        "2026-05-04": {
          "temperature_f": 62.0,
          "cloud_cover_pct": 18.25,
          "wind_speed_mph": 6.904674552,
          "wind_gust_mph": 14.960128196000001,
          "overnight_snowfall_in": 0.0,
          "overnight_low_f": 44.0,
          "humidity_pct": 43.083333333333336,
          "precipitation_in": 0.0,
          "visibility_mi": null,
          "precipitation_probability_pct": 4
        }
      },
      "forecastUrl": "https://api.weather.gov/gridpoints/SEW/140,32/forecast",
      "source": "NWS"
    },
    "46.803,-121.737": {
      "weatherByDay": {
        "2026-04-28": {
          "temperature_f": 39.0,
          "cloud_cover_pct": 52.7,
          "wind_speed_mph": 10.357011828,
          "wind_gust_mph": 27.618698208,
          "overnight_snowfall_in": 0.0,
          "overnight_low_f": 28.0,
          "humidity_pct": 68.42857142857143,
          "precipitation_in": 0.0,
          "visibility_mi": null,
          "precipitation_probability_pct": 22
        },
        "2026-04-29": {
          "temperature_f": 49.0,
          "cloud_cover_pct": 31.0,
          "wind_speed_mph": 7.927589300444445,
          "wind_gust_mph": 19.563244564,
          "overnight_snowfall_in": 0.0,
          "overnight_low_f": 28.0,
          "humidity_pct": 58.94736842105263,
          "precipitation_in": 0.0,
          "visibility_mi": null,
          "precipitation_probability_pct": 8
        },
        "2026-04-30": {
          "temperature_f": 53.0,
          "cloud_cover_pct": 21.833333333333332,
          "wind_speed_mph": 8.055453644,
          "wind_gust_mph": 14.960128196000001,
          "overnight_snowfall_in": 0.0,
          "overnight_low_f": 36.0,
          "humidity_pct": 46.05882352941177,
          "precipitation_in": 0.0,
          "visibility_mi": null,
          "precipitation_probability_pct": 3
        },
        "2026-05-01": {
          "temperature_f": 49.0,
          "cloud_cover_pct": 34.714285714285715,
          "wind_speed_mph": 7.069071565142856,
          "wind_gust_mph": 18.412465472,
          "overnight_snowfall_in": 0.0,
          "overnight_low_f": 35.0,
          "humidity_pct": 51.916666666666664,
          "precipitation_in": 0.0,
          "visibility_mi": null,
          "precipitation_probability_pct": 5
        },
        "2026-05-02": {
          "temperature_f": 52.0,
          "cloud_cover_pct": 57.5,
          "wind_speed_mph": 9.206232735999999,
          "wind_gust_mph": 16.110907288,
          "overnight_snowfall_in": 0.0,
          "overnight_low_f": 34.0,
          "humidity_pct": 53.0,
          "precipitation_in": 0.0,
          "visibility_mi": null,
          "precipitation_probability_pct": 15
        },
        "2026-05-03": {
          "temperature_f": 59.0,
          "cloud_cover_pct": 27.5,
          "wind_speed_mph": 8.976076917599999,
          "wind_gust_mph": 14.960128196000001,
          "overnight_snowfall_in": 0.0,
          "overnight_low_f": 38.0,
          "humidity_pct": 45.63157894736842,
          "precipitation_in": 0.0,
          "visibility_mi": null,
          "precipitation_probability_pct": 11
        },
        "2026-05-04": {
          "temperature_f": 61.0,
          "cloud_cover_pct": 20.666666666666668,
          "wind_speed_mph": 9.041835722857144,
          "wind_gust_mph": 16.110907288,
          "overnight_snowfall_in": 0.0,
          "overnight_low_f": 43.0,
          "humidity_pct": 38.10526315789474,
          "precipitation_in": 0.0,
          "visibility_mi": null,
          "precipitation_probability_pct": 5
        }
      },
      "forecastUrl": "https://api.weather.gov/gridpoints/SEW/136,27/forecast",
      "source": "NWS"
    },
    "46.186,-121.492": {
      "weatherByDay": {
        "2026-04-28": {
          "temperature_f": 27.0,
          "cloud_cover_pct": 48.25,
          "wind_speed_mph": 25.086984205599997,
          "wind_gust_mph": 39.126489128,
          "overnight_snowfall_in": 0.0,
          "overnight_low_f": 19.0,
          "humidity_pct": 55.05,
          "precipitation_in": 0.0,
          "visibility_mi": null,
          "precipitation_probability_pct": 7
        },
        "2026-04-29": {
          "temperature_f": 36.0,
          "cloud_cover_pct": 23.625,
          "wind_speed_mph": 13.316158064571427,
          "wind_gust_mph": 27.618698208,
          "overnight_snowfall_in": 0.0,
          "overnight_low_f": 18.0,
          "humidity_pct": 50.26086956521739,
          "precipitation_in": 0.0,
          "visibility_mi": null,
          "precipitation_probability_pct": 3
        },
        "2026-04-30": {
          "temperature_f": 42.0,
          "cloud_cover_pct": 32.625,
          "wind_speed_mph": 14.240891263500002,
          "wind_gust_mph": 21.864802748000002,
          "overnight_snowfall_in": 0.0,
          "overnight_low_f": 26.0,
          "humidity_pct": 37.36363636363637,
          "precipitation_in": 0.0,
          "visibility_mi": null,
          "precipitation_probability_pct": 1
        },
        "2026-05-01": {
          "temperature_f": 41.0,
          "cloud_cover_pct": 41.625,
          "wind_speed_mph": 15.288922222285713,
          "wind_gust_mph": 24.166360932000003,
          "overnight_snowfall_in": 0.0,
          "overnight_low_f": 26.0,
          "humidity_pct": 42.166666666666664,
          "precipitation_in": 0.0,
          "visibility_mi": null,
          "precipitation_probability_pct": 4
        },
        "2026-05-02": {
          "temperature_f": 43.0,
          "cloud_cover_pct": 64.5,
          "wind_speed_mph": 15.453319235428571,
          "wind_gust_mph": 24.166360932000003,
          "overnight_snowfall_in": 0.0,
          "overnight_low_f": 27.0,
          "humidity_pct": 45.65,
          "precipitation_in": 0.0,
          "visibility_mi": null,
          "precipitation_probability_pct": 14
        },
        "2026-05-03": {
          "temperature_f": 49.0,
          "cloud_cover_pct": 29.0,
          "wind_speed_mph": 17.1178389935,
          "wind_gust_mph": 27.618698208,
          "overnight_snowfall_in": 0.0,
          "overnight_low_f": 31.0,
          "humidity_pct": 37.63636363636363,
          "precipitation_in": 0.0,
          "visibility_mi": null,
          "precipitation_probability_pct": 10
        },
        "2026-05-04": {
          "temperature_f": 51.0,
          "cloud_cover_pct": 19.25,
          "wind_speed_mph": 14.466937156571428,
          "wind_gust_mph": 23.01558184,
          "overnight_snowfall_in": 0.0,
          "overnight_low_f": 35.0,
          "humidity_pct": 30.5,
          "precipitation_in": 0.0,
          "visibility_mi": null,
          "precipitation_probability_pct": 7
        }
      },
      "forecastUrl": "https://api.weather.gov/gridpoints/PDT/49,140/forecast",
      "source": "NWS"
    },
    "46.184,-122.197": {
      "weatherByDay": {
        "2026-04-28": {
          "temperature_f": 38.0,
          "cloud_cover_pct": 65.0,
          "wind_speed_mph": 8.40953951846154,
          "wind_gust_mph": 18.412465472,
          "overnight_snowfall_in": 0.0,
          "overnight_low_f": 29.0,
          "humidity_pct": 79.9375,
          "precipitation_in": 0.0,
          "visibility_mi": 8.047162938170768,
          "precipitation_probability_pct": 22
        },
        "2026-04-29": {
          "temperature_f": 49.0,
          "cloud_cover_pct": 26.333333333333332,
          "wind_speed_mph": 8.997000173818181,
          "wind_gust_mph": 19.563244564,
          "overnight_snowfall_in": 0.0,
          "overnight_low_f": 29.0,
          "humidity_pct": 66.6086956521739,
          "precipitation_in": 0.0,
          "visibility_mi": 9.368773321706183,
          "precipitation_probability_pct": 4
        },
        "2026-04-30": {
          "temperature_f": 54.0,
          "cloud_cover_pct": 29.375,
          "wind_speed_mph": 9.6665443728,
          "wind_gust_mph": 16.110907288,
          "overnight_snowfall_in": 0.0,
          "overnight_low_f": 37.0,
          "humidity_pct": 51.27777777777778,
          "precipitation_in": 0.0,
          "visibility_mi": null,
          "precipitation_probability_pct": 2
        },
        "2026-05-01": {
          "temperature_f": 48.0,
          "cloud_cover_pct": 40.125,
          "wind_speed_mph": 9.699423775428572,
          "wind_gust_mph": 18.412465472,
          "overnight_snowfall_in": 0.0,
          "overnight_low_f": 35.0,
          "humidity_pct": 57.73684210526316,
          "precipitation_in": 0.0,
          "visibility_mi": null,
          "precipitation_probability_pct": 4
        },
        "2026-05-02": {
          "temperature_f": 53.0,
          "cloud_cover_pct": 60.333333333333336,
          "wind_speed_mph": 8.384247670285713,
          "wind_gust_mph": 21.864802748000002,
          "overnight_snowfall_in": 0.0,
          "overnight_low_f": 34.0,
          "humidity_pct": 60.63157894736842,
          "precipitation_in": 0.0,
          "visibility_mi": null,
          "precipitation_probability_pct": 13
        },
        "2026-05-03": {
          "temperature_f": 62.0,
          "cloud_cover_pct": 21.0,
          "wind_speed_mph": 7.8252978256,
          "wind_gust_mph": 17.26168638,
          "overnight_snowfall_in": 0.0,
          "overnight_low_f": 40.0,
          "humidity_pct": 51.5,
          "precipitation_in": 0.0,
          "visibility_mi": null,
          "precipitation_probability_pct": 10
        },
        "2026-05-04": {
          "temperature_f": 60.0,
          "cloud_cover_pct": 18.25,
          "wind_speed_mph": 6.904674552,
          "wind_gust_mph": 18.412465472,
          "overnight_snowfall_in": 0.0,
          "overnight_low_f": 46.0,
          "humidity_pct": 44.94736842105263,
          "precipitation_in": 0.0,
          "visibility_mi": null,
          "precipitation_probability_pct": 6
        }
      },
      "forecastUrl": "https://api.weather.gov/gridpoints/PQR/134,131/forecast",
      "source": "NWS"
    },
    "48.828,-121.689": {
      "weatherByDay": {
        "2026-04-28": {
          "temperature_f": 49.0,
          "cloud_cover_pct": 81.52380952380952,
          "wind_speed_mph": 5.466200687000001,
          "wind_gust_mph": 14.960128196000001,
          "overnight_snowfall_in": 0.0,
          "overnight_low_f": 37.0,
          "humidity_pct": 88.8,
          "precipitation_in": 0.0800000000745056,
          "visibility_mi": null,
          "precipitation_probability_pct": 49
        },
        "2026-04-29": {
          "temperature_f": 58.0,
          "cloud_cover_pct": 46.2,
          "wind_speed_mph": 3.6441337913333336,
          "wind_gust_mph": 10.357011828,
          "overnight_snowfall_in": 0.0,
          "overnight_low_f": 35.0,
          "humidity_pct": 76.42857142857143,
          "precipitation_in": 0.0,
          "visibility_mi": null,
          "precipitation_probability_pct": 11
        },
        "2026-04-30": {
          "temperature_f": 59.0,
          "cloud_cover_pct": 27.875,
          "wind_speed_mph": 4.986709398666667,
          "wind_gust_mph": 11.50779092,
          "overnight_snowfall_in": 0.0,
          "overnight_low_f": 42.0,
          "humidity_pct": 65.0,
          "precipitation_in": 0.0,
          "visibility_mi": null,
          "precipitation_probability_pct": 2
        },
        "2026-05-01": {
          "temperature_f": 57.0,
          "cloud_cover_pct": 48.5,
          "wind_speed_mph": 4.3729605496,
          "wind_gust_mph": 12.658570012,
          "overnight_snowfall_in": 0.0,
          "overnight_low_f": 40.0,
          "humidity_pct": 64.05263157894737,
          "precipitation_in": 0.0,
          "visibility_mi": null,
          "precipitation_probability_pct": 4
        },
        "2026-05-02": {
          "temperature_f": 63.0,
          "cloud_cover_pct": 55.75,
          "wind_speed_mph": 4.8332721864,
          "wind_gust_mph": 11.50779092,
          "overnight_snowfall_in": 0.0,
          "overnight_low_f": 41.0,
          "humidity_pct": 63.05,
          "precipitation_in": 0.0,
          "visibility_mi": null,
          "precipitation_probability_pct": 9
        },
        "2026-05-03": {
          "temperature_f": 69.0,
          "cloud_cover_pct": 21.666666666666668,
          "wind_speed_mph": 6.616979779,
          "wind_gust_mph": 12.658570012,
          "overnight_snowfall_in": 0.0,
          "overnight_low_f": 44.0,
          "humidity_pct": 51.80952380952381,
          "precipitation_in": 0.0,
          "visibility_mi": null,
          "precipitation_probability_pct": 7
        },
        "2026-05-04": {
          "temperature_f": 71.0,
          "cloud_cover_pct": 18.5,
          "wind_speed_mph": 5.589498446857143,
          "wind_gust_mph": 10.357011828,
          "overnight_snowfall_in": 0.0,
          "overnight_low_f": 48.0,
          "humidity_pct": 44.80952380952381,
          "precipitation_in": 0.0,
          "visibility_mi": null,
          "precipitation_probability_pct": 3
        }
      },
      "forecastUrl": "https://api.weather.gov/gridpoints/SEW/156,121/forecast",
      "source": "NWS"
    },
    "48.4748,-121.075": {
      "weatherByDay": {
        "2026-04-28": {
          "temperature_f": 46.0,
          "cloud_cover_pct": 79.91304347826087,
          "wind_speed_mph": 7.288267582666667,
          "wind_gust_mph": 18.412465472,
          "overnight_snowfall_in": 0.0,
          "overnight_low_f": 36.0,
          "humidity_pct": 91.17647058823529,
          "precipitation_in": 0.0,
          "visibility_mi": null,
          "precipitation_probability_pct": 18
        },
        "2026-04-29": {
          "temperature_f": 55.0,
          "cloud_cover_pct": 47.8,
          "wind_speed_mph": 4.4592689815,
          "wind_gust_mph": 12.658570012,
          "overnight_snowfall_in": 0.0,
          "overnight_low_f": 34.0,
          "humidity_pct": 78.7,
          "precipitation_in": 0.0,
          "visibility_mi": null,
          "precipitation_probability_pct": 7
        },
        "2026-04-30": {
          "temperature_f": 57.0,
          "cloud_cover_pct": 25.75,
          "wind_speed_mph": 6.329285006,
          "wind_gust_mph": 11.50779092,
          "overnight_snowfall_in": 0.0,
          "overnight_low_f": 39.0,
          "humidity_pct": 64.38888888888889,
          "precipitation_in": 0.0,
          "visibility_mi": null,
          "precipitation_probability_pct": 3
        },
        "2026-05-01": {
          "temperature_f": 55.0,
          "cloud_cover_pct": 43.5,
          "wind_speed_mph": 5.75389546,
          "wind_gust_mph": 12.658570012,
          "overnight_snowfall_in": 0.0,
          "overnight_low_f": 38.0,
          "humidity_pct": 68.29411764705883,
          "precipitation_in": 0.0,
          "visibility_mi": null,
          "precipitation_probability_pct": 6
        },
        "2026-05-02": {
          "temperature_f": 57.0,
          "cloud_cover_pct": 56.5,
          "wind_speed_mph": 4.603116368,
          "wind_gust_mph": 12.658570012,
          "overnight_snowfall_in": 0.0,
          "overnight_low_f": 39.0,
          "humidity_pct": 66.95,
          "precipitation_in": 0.0,
          "visibility_mi": null,
          "precipitation_probability_pct": 13
        },
        "2026-05-03": {
          "temperature_f": 65.0,
          "cloud_cover_pct": 23.333333333333332,
          "wind_speed_mph": 5.9182924731428574,
          "wind_gust_mph": 12.658570012,
          "overnight_snowfall_in": 0.0,
          "overnight_low_f": 40.0,
          "humidity_pct": 55.36363636363637,
          "precipitation_in": 0.0,
          "visibility_mi": null,
          "precipitation_probability_pct": 10
        },
        "2026-05-04": {
          "temperature_f": 67.0,
          "cloud_cover_pct": 17.333333333333332,
          "wind_speed_mph": 5.178505914,
          "wind_gust_mph": 11.50779092,
          "overnight_snowfall_in": 0.0,
          "overnight_low_f": 44.0,
          "humidity_pct": 48.27777777777778,
          "precipitation_in": 0.0,
          "visibility_mi": null,
          "precipitation_probability_pct": 3
        }
      },
      "forecastUrl": "https://api.weather.gov/gridpoints/SEW/172,101/forecast",
      "source": "NWS"
    },
    "47.942,-123.699": {
      "weatherByDay": {
        "2026-04-28": {
          "temperature_f": 46.0,
          "cloud_cover_pct": 61.13636363636363,
          "wind_speed_mph": 8.69477536177778,
          "wind_gust_mph": 20.714023656,
          "overnight_snowfall_in": 0.0,
          "overnight_low_f": 34.0,
          "humidity_pct": 84.80952380952381,
          "precipitation_in": 0.0099999997764826,
          "visibility_mi": null,
          "precipitation_probability_pct": 42
        },
        "2026-04-29": {
          "temperature_f": 50.0,
          "cloud_cover_pct": 26.642857142857142,
          "wind_speed_mph": 5.6388175508,
          "wind_gust_mph": 14.960128196000001,
          "overnight_snowfall_in": 0.0,
          "overnight_low_f": 32.0,
          "humidity_pct": 77.8,
          "precipitation_in": 0.0,
          "visibility_mi": null,
          "precipitation_probability_pct": 9
        },
        "2026-04-30": {
          "temperature_f": 54.0,
          "cloud_cover_pct": 38.0,
          "wind_speed_mph": 6.712878036666666,
          "wind_gust_mph": 16.110907288,
          "overnight_snowfall_in": 0.0,
          "overnight_low_f": 38.0,
          "humidity_pct": 68.6,
          "precipitation_in": 0.0,
          "visibility_mi": null,
          "precipitation_probability_pct": 1
        },
        "2026-05-01": {
          "temperature_f": 49.0,
          "cloud_cover_pct": 50.375,
          "wind_speed_mph": 9.6665443728,
          "wind_gust_mph": 18.412465472,
          "overnight_snowfall_in": 0.0,
          "overnight_low_f": 36.0,
          "humidity_pct": 68.85714285714286,
          "precipitation_in": 0.0,
          "visibility_mi": null,
          "precipitation_probability_pct": 4
        },
        "2026-05-02": {
          "temperature_f": 56.0,
          "cloud_cover_pct": 42.5,
          "wind_speed_mph": 6.329285006,
          "wind_gust_mph": 21.864802748000002,
          "overnight_snowfall_in": 0.0,
          "overnight_low_f": 37.0,
          "humidity_pct": 66.95238095238095,
          "precipitation_in": 0.0,
          "visibility_mi": null,
          "precipitation_probability_pct": 2
        },
        "2026-05-03": {
          "temperature_f": 62.0,
          "cloud_cover_pct": 11.25,
          "wind_speed_mph": 7.671860613333333,
          "wind_gust_mph": 18.412465472,
          "overnight_snowfall_in": 0.0,
          "overnight_low_f": 43.0,
          "humidity_pct": 51.4,
          "precipitation_in": 0.0,
          "visibility_mi": null,
          "precipitation_probability_pct": 1
        },
        "2026-05-04": {
          "temperature_f": 64.0,
          "cloud_cover_pct": 13.0,
          "wind_speed_mph": 5.9840512784,
          "wind_gust_mph": 14.960128196000001,
          "overnight_snowfall_in": 0.0,
          "overnight_low_f": 48.0,
          "humidity_pct": 41.6,
          "precipitation_in": 0.0,
          "visibility_mi": null,
          "precipitation_probability_pct": 3
        }
      },
      "forecastUrl": "https://api.weather.gov/gridpoints/SEW/85,93/forecast",
      "source": "NWS"
    },
    "47.5282,-120.8253": {
      "weatherByDay": {
        "2026-04-28": {
          "temperature_f": 44.0,
          "cloud_cover_pct": 51.0,
          "wind_speed_mph": 10.192614814857142,
          "wind_gust_mph": 25.317140024,
          "overnight_snowfall_in": 0.0,
          "overnight_low_f": 32.0,
          "humidity_pct": 77.86666666666666,
          "precipitation_in": 0.0,
          "visibility_mi": null,
          "precipitation_probability_pct": 5
        },
        "2026-04-29": {
          "temperature_f": 52.0,
          "cloud_cover_pct": 33.375,
          "wind_speed_mph": 6.329285006,
          "wind_gust_mph": 21.864802748000002,
          "overnight_snowfall_in": 0.0,
          "overnight_low_f": 31.0,
          "humidity_pct": 69.68181818181819,
          "precipitation_in": 0.0,
          "visibility_mi": null,
          "precipitation_probability_pct": 4
        },
        "2026-04-30": {
          "temperature_f": 56.0,
          "cloud_cover_pct": 25.25,
          "wind_speed_mph": 4.794912883333333,
          "wind_gust_mph": 12.658570012,
          "overnight_snowfall_in": 0.0,
          "overnight_low_f": 37.0,
          "humidity_pct": 54.6875,
          "precipitation_in": 0.0,
          "visibility_mi": null,
          "precipitation_probability_pct": 3
        },
        "2026-05-01": {
          "temperature_f": 56.0,
          "cloud_cover_pct": 38.0,
          "wind_speed_mph": 6.5210815213333335,
          "wind_gust_mph": 13.809349104,
          "overnight_snowfall_in": 0.0,
          "overnight_low_f": 37.0,
          "humidity_pct": 56.95238095238095,
          "precipitation_in": 0.0,
          "visibility_mi": null,
          "precipitation_probability_pct": 3
        },
        "2026-05-02": {
          "temperature_f": 56.0,
          "cloud_cover_pct": 60.0,
          "wind_speed_mph": 10.8173234648,
          "wind_gust_mph": 18.412465472,
          "overnight_snowfall_in": 0.0,
          "overnight_low_f": 39.0,
          "humidity_pct": 61.21052631578947,
          "precipitation_in": 0.0,
          "visibility_mi": null,
          "precipitation_probability_pct": 13
        },
        "2026-05-03": {
          "temperature_f": 62.0,
          "cloud_cover_pct": 25.0,
          "wind_speed_mph": 8.822639705333334,
          "wind_gust_mph": 18.412465472,
          "overnight_snowfall_in": 0.0,
          "overnight_low_f": 40.0,
          "humidity_pct": 56.476190476190474,
          "precipitation_in": 0.0,
          "visibility_mi": null,
          "precipitation_probability_pct": 10
        },
        "2026-05-04": {
          "temperature_f": 65.0,
          "cloud_cover_pct": 19.0,
          "wind_speed_mph": 8.5157652808,
          "wind_gust_mph": 18.412465472,
          "overnight_snowfall_in": 0.0,
          "overnight_low_f": 45.0,
          "humidity_pct": 45.40909090909091,
          "precipitation_in": 0.0,
          "visibility_mi": null,
          "precipitation_probability_pct": 3
        }
      },
      "forecastUrl": "https://api.weather.gov/gridpoints/OTX/31,103/forecast",
      "source": "NWS"
    },
    "46.9145,-121.6415": {
      "weatherByDay": {
        "2026-04-28": {
          "temperature_f": 48.0,
          "cloud_cover_pct": 54.869565217391305,
          "wind_speed_mph": 7.710219916400001,
          "wind_gust_mph": 26.467919115999997,
          "overnight_snowfall_in": 0.0,
          "overnight_low_f": 29.0,
          "humidity_pct": 75.5,
          "precipitation_in": 0.0,
          "visibility_mi": null,
          "precipitation_probability_pct": 18
        },
        "2026-04-29": {
          "temperature_f": 56.0,
          "cloud_cover_pct": 39.8,
          "wind_speed_mph": 3.9126489128,
          "wind_gust_mph": 17.26168638,
          "overnight_snowfall_in": 0.0,
          "overnight_low_f": 29.0,
          "humidity_pct": 66.68181818181819,
          "precipitation_in": 0.0,
          "visibility_mi": null,
          "precipitation_probability_pct": 7
        },
        "2026-04-30": {
          "temperature_f": 60.0,
          "cloud_cover_pct": 28.5,
          "wind_speed_mph": 4.794912883333333,
          "wind_gust_mph": 12.658570012,
          "overnight_snowfall_in": 0.0,
          "overnight_low_f": 37.0,
          "humidity_pct": 53.56521739130435,
          "precipitation_in": 0.0,
          "visibility_mi": null,
          "precipitation_probability_pct": 3
        },
        "2026-05-01": {
          "temperature_f": 55.0,
          "cloud_cover_pct": 36.375,
          "wind_speed_mph": 4.603116368,
          "wind_gust_mph": 14.960128196000001,
          "overnight_snowfall_in": 0.0,
          "overnight_low_f": 36.0,
          "humidity_pct": 61.142857142857146,
          "precipitation_in": 0.0,
          "visibility_mi": null,
          "precipitation_probability_pct": 6
        },
        "2026-05-02": {
          "temperature_f": 59.0,
          "cloud_cover_pct": 59.25,
          "wind_speed_mph": 4.794912883333334,
          "wind_gust_mph": 12.658570012,
          "overnight_snowfall_in": 0.0,
          "overnight_low_f": 36.0,
          "humidity_pct": 63.45454545454545,
          "precipitation_in": 0.0,
          "visibility_mi": null,
          "precipitation_probability_pct": 15
        },
        "2026-05-03": {
          "temperature_f": 66.0,
          "cloud_cover_pct": 23.0,
          "wind_speed_mph": 5.9182924731428574,
          "wind_gust_mph": 13.809349104,
          "overnight_snowfall_in": 0.0,
          "overnight_low_f": 41.0,
          "humidity_pct": 55.142857142857146,
          "precipitation_in": 0.0,
          "visibility_mi": null,
          "precipitation_probability_pct": 10
        },
        "2026-05-04": {
          "temperature_f": 68.0,
          "cloud_cover_pct": 17.5,
          "wind_speed_mph": 5.75389546,
          "wind_gust_mph": 12.658570012,
          "overnight_snowfall_in": 0.0,
          "overnight_low_f": 45.0,
          "humidity_pct": 45.21739130434783,
          "precipitation_in": 0.0,
          "visibility_mi": null,
          "precipitation_probability_pct": 4
        }
      },
      "forecastUrl": "https://api.weather.gov/gridpoints/SEW/140,31/forecast",
      "source": "NWS"
    },
    "46.4675,-121.5025": {
      "weatherByDay": {
        "2026-04-28": {
          "temperature_f": 45.0,
          "cloud_cover_pct": 66.72727272727273,
          "wind_speed_mph": 5.589498446857143,
          "wind_gust_mph": 18.412465472,
          "overnight_snowfall_in": 0.0,
          "overnight_low_f": 32.0,
          "humidity_pct": 81.23529411764706,
          "precipitation_in": 0.0,
          "visibility_mi": null,
          "precipitation_probability_pct": 8
        },
        "2026-04-29": {
          "temperature_f": 54.0,
          "cloud_cover_pct": 34.0,
          "wind_speed_mph": 2.589252957,
          "wind_gust_mph": 13.809349104,
          "overnight_snowfall_in": 0.0,
          "overnight_low_f": 31.0,
          "humidity_pct": 71.04761904761905,
          "precipitation_in": 0.0,
          "visibility_mi": null,
          "precipitation_probability_pct": 3
        },
        "2026-04-30": {
          "temperature_f": 57.0,
          "cloud_cover_pct": 32.5,
          "wind_speed_mph": 3.2605407606666668,
          "wind_gust_mph": 10.357011828,
          "overnight_snowfall_in": 0.0,
          "overnight_low_f": 38.0,
          "humidity_pct": 52.05555555555556,
          "precipitation_in": 0.0,
          "visibility_mi": null,
          "precipitation_probability_pct": 2
        },
        "2026-05-01": {
          "temperature_f": 55.0,
          "cloud_cover_pct": 42.75,
          "wind_speed_mph": 3.452337276,
          "wind_gust_mph": 11.50779092,
          "overnight_snowfall_in": 0.0,
          "overnight_low_f": 39.0,
          "humidity_pct": 60.72727272727273,
          "precipitation_in": 0.0,
          "visibility_mi": null,
          "precipitation_probability_pct": 4
        },
        "2026-05-02": {
          "temperature_f": 57.0,
          "cloud_cover_pct": 66.25,
          "wind_speed_mph": 2.3015581839999997,
          "wind_gust_mph": 12.658570012,
          "overnight_snowfall_in": 0.0,
          "overnight_low_f": 39.0,
          "humidity_pct": 64.1,
          "precipitation_in": 0.0,
          "visibility_mi": null,
          "precipitation_probability_pct": 15
        },
        "2026-05-03": {
          "temperature_f": 63.0,
          "cloud_cover_pct": 29.75,
          "wind_speed_mph": 3.8359303066666666,
          "wind_gust_mph": 12.658570012,
          "overnight_snowfall_in": 0.0,
          "overnight_low_f": 42.0,
          "humidity_pct": 55.8125,
          "precipitation_in": 0.0,
          "visibility_mi": null,
          "precipitation_probability_pct": 10
        },
        "2026-05-04": {
          "temperature_f": 65.0,
          "cloud_cover_pct": 21.0,
          "wind_speed_mph": 3.164642503,
          "wind_gust_mph": 12.658570012,
          "overnight_snowfall_in": 0.0,
          "overnight_low_f": 46.0,
          "humidity_pct": 44.95238095238095,
          "precipitation_in": 0.0,
          "visibility_mi": null,
          "precipitation_probability_pct": 4
        }
      },
      "forecastUrl": "https://api.weather.gov/gridpoints/SEW/140,10/forecast",
      "source": "NWS"
    },
    "48.483,-121.053": {
      "weatherByDay": {
        "2026-04-28": {
          "temperature_f": 35.0,
          "cloud_cover_pct": 78.38888888888889,
          "wind_speed_mph": 10.603607347714286,
          "wind_gust_mph": 19.563244564,
          "overnight_snowfall_in": 0.0,
          "overnight_low_f": 30.0,
          "humidity_pct": 92.61904761904762,
          "precipitation_in": 0.0,
          "visibility_mi": null,
          "precipitation_probability_pct": 18
        },
        "2026-04-29": {
          "temperature_f": 46.0,
          "cloud_cover_pct": 48.06666666666667,
          "wind_speed_mph": 7.032538895555556,
          "wind_gust_mph": 14.960128196000001,
          "overnight_snowfall_in": 0.0,
          "overnight_low_f": 29.0,
          "humidity_pct": 79.15,
          "precipitation_in": 0.0,
          "visibility_mi": null,
          "precipitation_probability_pct": 7
        },
        "2026-04-30": {
          "temperature_f": 48.0,
          "cloud_cover_pct": 28.428571428571427,
          "wind_speed_mph": 8.2856094624,
          "wind_gust_mph": 13.809349104,
          "overnight_snowfall_in": 0.0,
          "overnight_low_f": 34.0,
          "humidity_pct": 63.8,
          "precipitation_in": 0.0,
          "visibility_mi": null,
          "precipitation_probability_pct": 3
        },
        "2026-05-01": {
          "temperature_f": 46.0,
          "cloud_cover_pct": 42.75,
          "wind_speed_mph": 7.8636571286666666,
          "wind_gust_mph": 12.658570012,
          "overnight_snowfall_in": 0.0,
          "overnight_low_f": 33.0,
          "humidity_pct": 68.5,
          "precipitation_in": 0.0,
          "visibility_mi": null,
          "precipitation_probability_pct": 6
        },
        "2026-05-02": {
          "temperature_f": 49.0,
          "cloud_cover_pct": 55.25,
          "wind_speed_mph": 6.2142070968,
          "wind_gust_mph": 13.809349104,
          "overnight_snowfall_in": 0.0,
          "overnight_low_f": 34.0,
          "humidity_pct": 66.52631578947368,
          "precipitation_in": 0.0,
          "visibility_mi": null,
          "precipitation_probability_pct": 13
        },
        "2026-05-03": {
          "temperature_f": 56.0,
          "cloud_cover_pct": 23.0,
          "wind_speed_mph": 6.5210815213333335,
          "wind_gust_mph": 13.809349104,
          "overnight_snowfall_in": 0.0,
          "overnight_low_f": 35.0,
          "humidity_pct": 54.63636363636363,
          "precipitation_in": 0.0,
          "visibility_mi": null,
          "precipitation_probability_pct": 10
        },
        "2026-05-04": {
          "temperature_f": 57.0,
          "cloud_cover_pct": 16.0,
          "wind_speed_mph": 5.9840512784,
          "wind_gust_mph": 12.658570012,
          "overnight_snowfall_in": 0.0,
          "overnight_low_f": 40.0,
          "humidity_pct": 47.4375,
          "precipitation_in": 0.0,
          "visibility_mi": null,
          "precipitation_probability_pct": 3
        }
      },
      "forecastUrl": "https://api.weather.gov/gridpoints/SEW/173,101/forecast",
      "source": "NWS"
    },
    "47.515,-120.81": {
      "weatherByDay": {
        "2026-04-28": {
          "temperature_f": 34.0,
          "cloud_cover_pct": 57.76470588235294,
          "wind_speed_mph": 22.572974496923077,
          "wind_gust_mph": 29.920256392000002,
          "overnight_snowfall_in": 0.0,
          "overnight_low_f": 25.0,
          "humidity_pct": 80.7,
          "precipitation_in": 0.0,
          "visibility_mi": null,
          "precipitation_probability_pct": 5
        },
        "2026-04-29": {
          "temperature_f": 43.0,
          "cloud_cover_pct": 37.75,
          "wind_speed_mph": 15.7656735604,
          "wind_gust_mph": 27.618698208,
          "overnight_snowfall_in": 0.0,
          "overnight_low_f": 26.0,
          "humidity_pct": 69.72727272727273,
          "precipitation_in": 0.0,
          "visibility_mi": null,
          "precipitation_probability_pct": 4
        },
        "2026-04-30": {
          "temperature_f": 48.0,
          "cloud_cover_pct": 29.125,
          "wind_speed_mph": 11.220096147,
          "wind_gust_mph": 14.960128196000001,
          "overnight_snowfall_in": 0.0,
          "overnight_low_f": 32.0,
          "humidity_pct": 53.5,
          "precipitation_in": 0.0,
          "visibility_mi": null,
          "precipitation_probability_pct": 2
        },
        "2026-05-01": {
          "temperature_f": 48.0,
          "cloud_cover_pct": 42.75,
          "wind_speed_mph": 14.960128196000001,
          "wind_gust_mph": 18.412465472,
          "overnight_snowfall_in": 0.0,
          "overnight_low_f": 32.0,
          "humidity_pct": 56.1578947368421,
          "precipitation_in": 0.0,
          "visibility_mi": null,
          "precipitation_probability_pct": 3
        },
        "2026-05-02": {
          "temperature_f": 48.0,
          "cloud_cover_pct": 63.0,
          "wind_speed_mph": 17.26168638,
          "wind_gust_mph": 24.166360932000003,
          "overnight_snowfall_in": 0.0,
          "overnight_low_f": 34.0,
          "humidity_pct": 60.5,
          "precipitation_in": 0.0,
          "visibility_mi": null,
          "precipitation_probability_pct": 12
        },
        "2026-05-03": {
          "temperature_f": 53.0,
          "cloud_cover_pct": 27.0,
          "wind_speed_mph": 15.190284014400001,
          "wind_gust_mph": 23.01558184,
          "overnight_snowfall_in": 0.0,
          "overnight_low_f": 35.0,
          "humidity_pct": 56.63636363636363,
          "precipitation_in": 0.0,
          "visibility_mi": null,
          "precipitation_probability_pct": 10
        },
        "2026-05-04": {
          "temperature_f": 57.0,
          "cloud_cover_pct": 19.25,
          "wind_speed_mph": 14.269660740800001,
          "wind_gust_mph": 24.166360932000003,
          "overnight_snowfall_in": 0.0,
          "overnight_low_f": 40.0,
          "humidity_pct": 46.6,
          "precipitation_in": 0.0,
          "visibility_mi": null,
          "precipitation_probability_pct": 3
        }
      },
      "forecastUrl": "https://api.weather.gov/gridpoints/OTX/32,102/forecast",
      "source": "NWS"
    },
    "46.92,-121.805": {
      "weatherByDay": {
        "2026-04-28": {
          "temperature_f": 41.0,
          "cloud_cover_pct": 54.791666666666664,
          "wind_speed_mph": 12.83561294923077,
          "wind_gust_mph": 29.920256392000002,
          "overnight_snowfall_in": 0.0,
          "overnight_low_f": 31.0,
          "humidity_pct": 76.76190476190476,
          "precipitation_in": 0.0,
          "visibility_mi": null,
          "precipitation_probability_pct": 22
        },
        "2026-04-29": {
          "temperature_f": 50.0,
          "cloud_cover_pct": 40.666666666666664,
          "wind_speed_mph": 6.904674552,
          "wind_gust_mph": 19.563244564,
          "overnight_snowfall_in": 0.0,
          "overnight_low_f": 30.0,
          "humidity_pct": 68.13636363636364,
          "precipitation_in": 0.0,
          "visibility_mi": null,
          "precipitation_probability_pct": 8
        },
        "2026-04-30": {
          "temperature_f": 54.0,
          "cloud_cover_pct": 29.25,
          "wind_speed_mph": 9.206232735999999,
          "wind_gust_mph": 18.412465472,
          "overnight_snowfall_in": 0.0,
          "overnight_low_f": 38.0,
          "humidity_pct": 50.666666666666664,
          "precipitation_in": 0.0,
          "visibility_mi": null,
          "precipitation_probability_pct": 3
        },
        "2026-05-01": {
          "temperature_f": 50.0,
          "cloud_cover_pct": 38.5,
          "wind_speed_mph": 9.4363885544,
          "wind_gust_mph": 19.563244564,
          "overnight_snowfall_in": 0.0,
          "overnight_low_f": 37.0,
          "humidity_pct": 58.578947368421055,
          "precipitation_in": 0.0,
          "visibility_mi": null,
          "precipitation_probability_pct": 6
        },
        "2026-05-02": {
          "temperature_f": 54.0,
          "cloud_cover_pct": 60.0,
          "wind_speed_mph": 6.247086499428573,
          "wind_gust_mph": 16.110907288,
          "overnight_snowfall_in": 0.0,
          "overnight_low_f": 37.0,
          "humidity_pct": 60.19047619047619,
          "precipitation_in": 0.0,
          "visibility_mi": null,
          "precipitation_probability_pct": 14
        },
        "2026-05-03": {
          "temperature_f": 62.0,
          "cloud_cover_pct": 23.666666666666668,
          "wind_speed_mph": 8.055453644,
          "wind_gust_mph": 17.26168638,
          "overnight_snowfall_in": 0.0,
          "overnight_low_f": 41.0,
          "humidity_pct": 51.869565217391305,
          "precipitation_in": 0.0,
          "visibility_mi": null,
          "precipitation_probability_pct": 10
        },
        "2026-05-04": {
          "temperature_f": 63.0,
          "cloud_cover_pct": 18.25,
          "wind_speed_mph": 9.041835722857144,
          "wind_gust_mph": 19.563244564,
          "overnight_snowfall_in": 0.0,
          "overnight_low_f": 46.0,
          "humidity_pct": 43.166666666666664,
          "precipitation_in": 0.0,
          "visibility_mi": null,
          "precipitation_probability_pct": 5
        }
      },
      "forecastUrl": "https://api.weather.gov/gridpoints/SEW/135,33/forecast",
      "source": "NWS"
    },
    "46.458,-121.442": {
      "weatherByDay": {
        "2026-04-28": {
          "temperature_f": 46.0,
          "cloud_cover_pct": 67.08695652173913,
          "wind_speed_mph": 8.055453644,
          "wind_gust_mph": 23.01558184,
          "overnight_snowfall_in": 0.0,
          "overnight_low_f": 31.0,
          "humidity_pct": 83.72222222222223,
          "precipitation_in": 0.0,
          "visibility_mi": null,
          "precipitation_probability_pct": 7
        },
        "2026-04-29": {
          "temperature_f": 54.0,
          "cloud_cover_pct": 35.86666666666667,
          "wind_speed_mph": 5.589498446857143,
          "wind_gust_mph": 17.26168638,
          "overnight_snowfall_in": 0.0,
          "overnight_low_f": 29.0,
          "humidity_pct": 72.85714285714286,
          "precipitation_in": 0.0,
          "visibility_mi": null,
          "precipitation_probability_pct": 3
        },
        "2026-04-30": {
          "temperature_f": 58.0,
          "cloud_cover_pct": 33.75,
          "wind_speed_mph": 4.603116368,
          "wind_gust_mph": 12.658570012,
          "overnight_snowfall_in": 0.0,
          "overnight_low_f": 36.0,
          "humidity_pct": 57.0,
          "precipitation_in": 0.0,
          "visibility_mi": null,
          "precipitation_probability_pct": 2
        },
        "2026-05-01": {
          "temperature_f": 56.0,
          "cloud_cover_pct": 47.0,
          "wind_speed_mph": 5.75389546,
          "wind_gust_mph": 14.960128196000001,
          "overnight_snowfall_in": 0.0,
          "overnight_low_f": 38.0,
          "humidity_pct": 62.61904761904762,
          "precipitation_in": 0.0,
          "visibility_mi": null,
          "precipitation_probability_pct": 4
        },
        "2026-05-02": {
          "temperature_f": 57.0,
          "cloud_cover_pct": 68.0,
          "wind_speed_mph": 3.9126489128,
          "wind_gust_mph": 16.110907288,
          "overnight_snowfall_in": 0.0,
          "overnight_low_f": 38.0,
          "humidity_pct": 67.38888888888889,
          "precipitation_in": 0.0,
          "visibility_mi": null,
          "precipitation_probability_pct": 15
        },
        "2026-05-03": {
          "temperature_f": 62.0,
          "cloud_cover_pct": 30.25,
          "wind_speed_mph": 5.2935838232000005,
          "wind_gust_mph": 17.26168638,
          "overnight_snowfall_in": 0.0,
          "overnight_low_f": 41.0,
          "humidity_pct": 59.388888888888886,
          "precipitation_in": 0.0,
          "visibility_mi": null,
          "precipitation_probability_pct": 11
        },
        "2026-05-04": {
          "temperature_f": 66.0,
          "cloud_cover_pct": 21.75,
          "wind_speed_mph": 5.0634280047999995,
          "wind_gust_mph": 14.960128196000001,
          "overnight_snowfall_in": 0.0,
          "overnight_low_f": 45.0,
          "humidity_pct": 49.57142857142857,
          "precipitation_in": 0.0,
          "visibility_mi": null,
          "precipitation_probability_pct": 4
        }
      },
      "forecastUrl": "https://api.weather.gov/gridpoints/SEW/142,9/forecast",
      "source": "NWS"
    },
    "48.8566,-121.6644": {
      "weatherByDay": {
        "2026-04-28": {
          "temperature_f": 48.0,
          "cloud_cover_pct": 78.95238095238095,
          "wind_speed_mph": 5.75389546,
          "wind_gust_mph": 19.563244564,
          "overnight_snowfall_in": 0.0,
          "overnight_low_f": 37.0,
          "humidity_pct": 83.86363636363636,
          "precipitation_in": 0.0499999988824132,
          "visibility_mi": null,
          "precipitation_probability_pct": 51
        },
        "2026-04-29": {
          "temperature_f": 56.0,
          "cloud_cover_pct": 48.5,
          "wind_speed_mph": 3.835930306666667,
          "wind_gust_mph": 12.658570012,
          "overnight_snowfall_in": 0.0,
          "overnight_low_f": 35.0,
          "humidity_pct": 69.88235294117646,
          "precipitation_in": 0.0,
          "visibility_mi": null,
          "precipitation_probability_pct": 12
        },
        "2026-04-30": {
          "temperature_f": 58.0,
          "cloud_cover_pct": 28.375,
          "wind_speed_mph": 5.75389546,
          "wind_gust_mph": 14.960128196000001,
          "overnight_snowfall_in": 0.0,
          "overnight_low_f": 42.0,
          "humidity_pct": 59.588235294117645,
          "precipitation_in": 0.0,
          "visibility_mi": null,
          "precipitation_probability_pct": 2
        },
        "2026-05-01": {
          "temperature_f": 55.0,
          "cloud_cover_pct": 48.75,
          "wind_speed_mph": 4.411319852666667,
          "wind_gust_mph": 16.110907288,
          "overnight_snowfall_in": 0.0,
          "overnight_low_f": 40.0,
          "humidity_pct": 60.611111111111114,
          "precipitation_in": 0.0,
          "visibility_mi": null,
          "precipitation_probability_pct": 5
        },
        "2026-05-02": {
          "temperature_f": 61.0,
          "cloud_cover_pct": 56.0,
          "wind_speed_mph": 5.370302429333334,
          "wind_gust_mph": 14.960128196000001,
          "overnight_snowfall_in": 0.0,
          "overnight_low_f": 41.0,
          "humidity_pct": 59.6,
          "precipitation_in": 0.0,
          "visibility_mi": null,
          "precipitation_probability_pct": 9
        },
        "2026-05-03": {
          "temperature_f": 68.0,
          "cloud_cover_pct": 20.75,
          "wind_speed_mph": 6.904674552,
          "wind_gust_mph": 17.26168638,
          "overnight_snowfall_in": 0.0,
          "overnight_low_f": 45.0,
          "humidity_pct": 44.89473684210526,
          "precipitation_in": 0.0,
          "visibility_mi": null,
          "precipitation_probability_pct": 7
        },
        "2026-05-04": {
          "temperature_f": 70.0,
          "cloud_cover_pct": 18.75,
          "wind_speed_mph": 6.41148351257143,
          "wind_gust_mph": 14.960128196000001,
          "overnight_snowfall_in": 0.0,
          "overnight_low_f": 48.0,
          "humidity_pct": 41.26315789473684,
          "precipitation_in": 0.0,
          "visibility_mi": null,
          "precipitation_probability_pct": 3
        }
      },
      "forecastUrl": "https://api.weather.gov/gridpoints/SEW/157,123/forecast",
      "source": "NWS"
    },
    "47.7448,-121.089": {
      "weatherByDay": {
        "2026-04-28": {
          "temperature_f": 48.0,
          "cloud_cover_pct": 75.9090909090909,
          "wind_speed_mph": 6.740277538857143,
          "wind_gust_mph": 20.714023656,
          "overnight_snowfall_in": 0.0,
          "overnight_low_f": 36.0,
          "humidity_pct": 83.14285714285714,
          "precipitation_in": 0.0,
          "visibility_mi": null,
          "precipitation_probability_pct": 11
        },
        "2026-04-29": {
          "temperature_f": 58.0,
          "cloud_cover_pct": 58.5,
          "wind_speed_mph": 3.2605407606666668,
          "wind_gust_mph": 17.26168638,
          "overnight_snowfall_in": 0.0,
          "overnight_low_f": 34.0,
          "humidity_pct": 74.22727272727273,
          "precipitation_in": 0.0,
          "visibility_mi": null,
          "precipitation_probability_pct": 5
        },
        "2026-04-30": {
          "temperature_f": 60.0,
          "cloud_cover_pct": 26.75,
          "wind_speed_mph": 4.027726822,
          "wind_gust_mph": 10.357011828,
          "overnight_snowfall_in": 0.0,
          "overnight_low_f": 39.0,
          "humidity_pct": 63.714285714285715,
          "precipitation_in": 0.0,
          "visibility_mi": null,
          "precipitation_probability_pct": 2
        },
        "2026-05-01": {
          "temperature_f": 58.0,
          "cloud_cover_pct": 42.875,
          "wind_speed_mph": 3.7400320490000003,
          "wind_gust_mph": 12.658570012,
          "overnight_snowfall_in": 0.0,
          "overnight_low_f": 40.0,
          "humidity_pct": 64.83333333333333,
          "precipitation_in": 0.0,
          "visibility_mi": null,
          "precipitation_probability_pct": 5
        },
        "2026-05-02": {
          "temperature_f": 60.0,
          "cloud_cover_pct": 65.25,
          "wind_speed_mph": 2.4659551971428573,
          "wind_gust_mph": 13.809349104,
          "overnight_snowfall_in": 0.0,
          "overnight_low_f": 41.0,
          "humidity_pct": 66.0,
          "precipitation_in": 0.0,
          "visibility_mi": null,
          "precipitation_probability_pct": 16
        },
        "2026-05-03": {
          "temperature_f": 67.0,
          "cloud_cover_pct": 27.0,
          "wind_speed_mph": 2.0714023656,
          "wind_gust_mph": 10.357011828,
          "overnight_snowfall_in": 0.0,
          "overnight_low_f": 42.0,
          "humidity_pct": 59.57142857142857,
          "precipitation_in": 0.0,
          "visibility_mi": null,
          "precipitation_probability_pct": 12
        },
        "2026-05-04": {
          "temperature_f": 69.0,
          "cloud_cover_pct": 24.0,
          "wind_speed_mph": 2.1097616686666667,
          "wind_gust_mph": 12.658570012,
          "overnight_snowfall_in": 0.0,
          "overnight_low_f": 46.0,
          "humidity_pct": 51.5,
          "precipitation_in": 0.0,
          "visibility_mi": null,
          "precipitation_probability_pct": 4
        }
      },
      "forecastUrl": "https://api.weather.gov/gridpoints/SEW/165,67/forecast",
      "source": "NWS"
    },
    "47.4281,-121.4138": {
      "weatherByDay": {
        "2026-04-28": {
          "temperature_f": 51.0,
          "cloud_cover_pct": 73.78260869565217,
          "wind_speed_mph": 4.315421595,
          "wind_gust_mph": 19.563244564,
          "overnight_snowfall_in": 0.0,
          "overnight_low_f": 37.0,
          "humidity_pct": 86.11111111111111,
          "precipitation_in": 0.019999999552965,
          "visibility_mi": null,
          "precipitation_probability_pct": 23
        },
        "2026-04-29": {
          "temperature_f": 60.0,
          "cloud_cover_pct": 46.92307692307692,
          "wind_speed_mph": 2.589252957,
          "wind_gust_mph": 13.809349104,
          "overnight_snowfall_in": 0.0,
          "overnight_low_f": 35.0,
          "humidity_pct": 80.52173913043478,
          "precipitation_in": 0.0,
          "visibility_mi": null,
          "precipitation_probability_pct": 8
        },
        "2026-04-30": {
          "temperature_f": 64.0,
          "cloud_cover_pct": 24.25,
          "wind_speed_mph": 3.452337276,
          "wind_gust_mph": 12.658570012,
          "overnight_snowfall_in": 0.0,
          "overnight_low_f": 40.0,
          "humidity_pct": 69.80952380952381,
          "precipitation_in": 0.0,
          "visibility_mi": null,
          "precipitation_probability_pct": 3
        },
        "2026-05-01": {
          "temperature_f": 58.0,
          "cloud_cover_pct": 41.125,
          "wind_speed_mph": 3.2221814576,
          "wind_gust_mph": 13.809349104,
          "overnight_snowfall_in": 0.0,
          "overnight_low_f": 41.0,
          "humidity_pct": 71.63157894736842,
          "precipitation_in": 0.0,
          "visibility_mi": null,
          "precipitation_probability_pct": 6
        },
        "2026-05-02": {
          "temperature_f": 63.0,
          "cloud_cover_pct": 63.75,
          "wind_speed_mph": 1.8700160245000002,
          "wind_gust_mph": 14.960128196000001,
          "overnight_snowfall_in": 0.0,
          "overnight_low_f": 41.0,
          "humidity_pct": 75.14285714285714,
          "precipitation_in": 0.0,
          "visibility_mi": null,
          "precipitation_probability_pct": 16
        },
        "2026-05-03": {
          "temperature_f": 71.0,
          "cloud_cover_pct": 22.25,
          "wind_speed_mph": 2.301558184,
          "wind_gust_mph": 11.50779092,
          "overnight_snowfall_in": 0.0,
          "overnight_low_f": 42.0,
          "humidity_pct": 62.47826086956522,
          "precipitation_in": 0.0,
          "visibility_mi": null,
          "precipitation_probability_pct": 13
        },
        "2026-05-04": {
          "temperature_f": 72.0,
          "cloud_cover_pct": 15.0,
          "wind_speed_mph": 2.685151214666667,
          "wind_gust_mph": 12.658570012,
          "overnight_snowfall_in": 0.0,
          "overnight_low_f": 48.0,
          "humidity_pct": 54.63636363636363,
          "precipitation_in": 0.0,
          "visibility_mi": null,
          "precipitation_probability_pct": 4
        }
      },
      "forecastUrl": "https://api.weather.gov/gridpoints/SEW/152,54/forecast",
      "source": "NWS"
    },
    "46.9354,-121.5045": {
      "weatherByDay": {
        "2026-04-28": {
          "temperature_f": 46.0,
          "cloud_cover_pct": 61.47826086956522,
          "wind_speed_mph": 10.566244390181819,
          "wind_gust_mph": 29.920256392000002,
          "overnight_snowfall_in": 0.0,
          "overnight_low_f": 31.0,
          "humidity_pct": 80.27272727272727,
          "precipitation_in": 0.0,
          "visibility_mi": null,
          "precipitation_probability_pct": 11
        },
        "2026-04-29": {
          "temperature_f": 55.0,
          "cloud_cover_pct": 50.53333333333333,
          "wind_speed_mph": 6.760827165499999,
          "wind_gust_mph": 20.714023656,
          "overnight_snowfall_in": 0.0,
          "overnight_low_f": 30.0,
          "humidity_pct": 73.63636363636364,
          "precipitation_in": 0.0,
          "visibility_mi": null,
          "precipitation_probability_pct": 5
        },
        "2026-04-30": {
          "temperature_f": 59.0,
          "cloud_cover_pct": 31.375,
          "wind_speed_mph": 6.904674552,
          "wind_gust_mph": 16.110907288,
          "overnight_snowfall_in": 0.0,
          "overnight_low_f": 37.0,
          "humidity_pct": 57.708333333333336,
          "precipitation_in": 0.0,
          "visibility_mi": null,
          "precipitation_probability_pct": 2
        },
        "2026-05-01": {
          "temperature_f": 55.0,
          "cloud_cover_pct": 39.625,
          "wind_speed_mph": 7.288267582666667,
          "wind_gust_mph": 19.563244564,
          "overnight_snowfall_in": 0.0,
          "overnight_low_f": 37.0,
          "humidity_pct": 65.0952380952381,
          "precipitation_in": 0.0,
          "visibility_mi": null,
          "precipitation_probability_pct": 4
        },
        "2026-05-02": {
          "temperature_f": 57.0,
          "cloud_cover_pct": 63.75,
          "wind_speed_mph": 6.137488490666668,
          "wind_gust_mph": 18.412465472,
          "overnight_snowfall_in": 0.0,
          "overnight_low_f": 37.0,
          "humidity_pct": 68.23809523809524,
          "precipitation_in": 0.0,
          "visibility_mi": null,
          "precipitation_probability_pct": 15
        },
        "2026-05-03": {
          "temperature_f": 64.0,
          "cloud_cover_pct": 29.333333333333332,
          "wind_speed_mph": 5.75389546,
          "wind_gust_mph": 18.412465472,
          "overnight_snowfall_in": 0.0,
          "overnight_low_f": 41.0,
          "humidity_pct": 59.04545454545455,
          "precipitation_in": 0.0,
          "visibility_mi": null,
          "precipitation_probability_pct": 10
        },
        "2026-05-04": {
          "temperature_f": 66.0,
          "cloud_cover_pct": 19.5,
          "wind_speed_mph": 7.288267582666667,
          "wind_gust_mph": 20.714023656,
          "overnight_snowfall_in": 0.0,
          "overnight_low_f": 45.0,
          "humidity_pct": 47.5,
          "precipitation_in": 0.0,
          "visibility_mi": null,
          "precipitation_probability_pct": 4
        }
      },
      "forecastUrl": "https://api.weather.gov/gridpoints/SEW/145,31/forecast",
      "source": "NWS"
    }
  }
}